Workbook

Sheet 数据统计
A1: 轻学堂内容数据统计
B2: 课程类型 | D2: 课程数量 | E2: 总集数 | F2: 集数占比 | G2: 总时长/h | H2: 时长占比 | I2: 原价/元
A3: 课程 | B3: 通用课 | D3: =COUNTIFS(通用课!C:C,"通用课") -> 332 | E3: =SUM(通用课!K3:K598) -> 41544 | F3: =E3/E9 -> 0.42216938 | G3: =SUM(通用课!L3:L498) -> 229578.49 | H3: =G3/G9 -> 0.69457652 | I3: =SUM(通用课!N3:N1048576) -> 37030.53
B4: 岗位课 | D4: =COUNTIF(岗位课!C:C,"岗位课") -> 231 | E4: =SUM(岗位课!K3:K469) -> 7874 | F4: =E4/E9 -> 0.080015446 | G4: =SUM(岗位课!L3:L499) -> 1600.69 | H4: =G4/G9 -> 0.0048427956 | I4: =SUM(岗位课!N2:N1048576) -> 35873.1
B5: 商学院 | D5: =COUNTIF(商学院!C3:C103,"商学院") -> 101 | E5: =SUM(商学院!K3:K200) -> 3658 | F5: =E5/E9 -> 0.03717253 | G5: =SUM(商学院!L3:L200) -> 90008.972 | H5: =G5/G9 -> 0.27231697 | I5: =SUM(商学院!N3:N1048576) -> 12871.49
B6: 其他 | D6: =COUNTIFS('课程列表（总）'!C3:C1028,"其他") -> 415 | E6: =SUMIFS('课程列表（总）'!M3:M1028,'课程列表（总）'!C3:C1028,"其他") -> 29646 | F6: =E6/E9 -> 0.30126212 | G6: =SUMIFS('课程列表（总）'!N3:N1028,'课程列表（总）'!C3:C1028,"其他") -> 4252.14 | H6: =G6/G9 -> 0.012864605 | I6: =SUMIFS('课程列表（总）'!P3:P1048576,'课程列表（总）'!C3:C1048576,"其他") -> 6472.7
A7: 书籍 | B7: 有声书 | D7: =COUNTIFS('书籍列表（总）'!B3:B1048576,"有声书") -> 352 | E7: =SUMIFS('书籍列表（总）'!H4:H1153,'书籍列表（总）'!B4:B1153,"有声书") -> 14456 | F7: =E7/E9 -> 0.14690161 | G7: =SUMIFS('书籍列表（总）'!I4:I1153,'书籍列表（总）'!B4:B1153,"讲书") -> 664.1505 | H7: =G7/G9 -> 0.0020093492 | I7: =SUMIFS('书籍列表（总）'!L4:L1048576,'书籍列表（总）'!B4:B1048576,"有声书") -> 10921.93
B8: 讲书 | D8: =COUNTIFS('书籍列表（总）'!B4:B1500,"讲书") -> 882 | E8: =SUMIFS('书籍列表（总）'!H4:H1153,'书籍列表（总）'!B4:B1153,"讲书") -> 1228 | F8: =E8/E9 -> 0.012478914 | G8: =SUMIFS('书籍列表（总）'!L4:L1048576,'书籍列表（总）'!B4:B1048576,"讲书") -> 4425.72 | H8: =G8/G9 -> 0.013389761 | I8: =SUMIFS('书籍列表（总）'!L4:L1048576,'书籍列表（总）'!B4:B1048576,"讲书") -> 4425.72
A9: 总计 | D9: =SUM(D3:D8) -> 2313 | E9: =SUM(E3:E8) -> 98406 | F9: / | G9: =SUM(G3:G8) -> 330530.16 | H9: / | I9: =ROUND(SUM(I3:I8),2)&"(会员畅听价399元/年/人)" -> 107595.47(会员畅听价399元/年/人)

Sheet 课程列表（总）
A1: 轻学堂—课程列表
A2: 内容说明： 1. VIP精品课，适用VIP用户企业，针对不同岗位和层级的能力提升需求，优选头部讲师和资源，打造最专业、权威、实战的课程； 2. 畅听课，适用所有企业，只要注册就可免费畅听，是轻学堂从喜马拉雅资源库引进的优质课程，致力服务更多企业。 3. 企业使用场景建议：挑选课程补充现有人才培养项目；挑选课单打造专题线上学习；挑选企业主推课程进行全员学习，营造学习氛围。
A3: 序号 | B3: 内容大类 | C3: 频道页 | D3: 一级标签 | E3: 二级标签 | F3: 课程名称 | G3: 副标题 | H3: 主讲人 | I3: 课程形式 | J3: 适用岗位 | K3: 适用职级 | L3: 轻学堂上架日期 | M3: 课程总课时/集 | N3: 已上架课时总时间/h | O3: 更新状态 | P3: 单卖价格/元
A4: =ROW()-3 -> 1 | B4: VIP精品课 | C4: 岗位课 | D4: 市场品牌 | E4: 营销思维 | F4: 叶茂中营销课堂：唤醒你的创意 | G4: 策划大师的私房课，向公众公开他营销与策划的法宝 | H4: 叶茂中 | I4: 音频 | J4: 全员 | K4: 基层管理者、中层管理者、职场新人 | L4: 43238 | M4: 72 | N4: 22.9 | O4: 已完结 | P4: 198
A5: =ROW()-3 -> 2 | B5: VIP精品课 | C5: 岗位课 | D5: 市场品牌 | E5: 营销思维 | F5: 林建红的定位营销课 | G5: 汲取商业的经典理论，掌握独创的系统方法论，打开商业和人生的崭新大门 | H5: 林建红 | I5: 音频 | J5: 销售、市场品牌 | K5: 中层管理者、专业人士 | L5: 43238 | M5: 31 | N5: 6.83 | O5: 已完结 | P5: 49.9
A6: =ROW()-3 -> 3 | B6: VIP精品课 | C6: 岗位课 | D6: 市场品牌 | E6: 营销策略 | F6: 李饷：趣读消费心理学 | G6: 有梗、有趣、有料，听着脱口秀，就能秒懂客户心理的消费心理学课程 | H6: 李饷 | I6: 音频 | J6: 销售 | K6: 中层管理者、专业人士 | L6: 43238 | M6: 39 | N6: 6.92 | O6: 已完结 | P6: 86
A7: =ROW()-3 -> 4 | B7: VIP精品课 | C7: 岗位课 | D7: 人力资源 | E7: 人力资源规划 | F7: Lisa的人力资源管理课 | G7: 不讲理论，只解决问题，教你从管人管事到管心，快速打造精英团队 | H7: Lisa | I7: 音频 | J7: CEO、管理者、HR | K7: 中层管理者、专业人士 | L7: 43238 | M7: 41 | N7: 7.65 | O7: 已完结 | P7: 129
A8: =ROW()-3 -> 5 | B8: VIP精品课 | C8: 岗位课 | D8: 销售 | E8: 销售技能 | F8: 倪建伟：销售如何搞定人 | G8: 帮助许多销售新手学到了受用一生的销售思维和技巧 | H8: 倪建伟 | I8: 音频 | J8: 销售 | K8: 中层管理者、专业人士 | L8: 43256 | M8: 67 | N8: 15.37 | O8: 已完结 | P8: 139
A9: =ROW()-3 -> 6 | B9: VIP精品课 | C9: 岗位课 | D9: 销售 | E9: 销售技能 | F9: 倪建伟：顶级销售成长课 | G9: 浓缩20年的大客户销售实战经验和多年的培训管理技巧 | H9: 倪建伟 | I9: 音频 | J9: 销售 | K9: 中层管理者、专业人士 | L9: 43256 | M9: 54 | N9: 12.9 | O9: 已完结 | P9: 139
A10: =ROW()-3 -> 7 | B10: VIP精品课 | C10: 岗位课 | D10: 市场品牌 | E10: 品牌管理 | F10: 李光斗品牌商学院:实战MBA品牌课 | G10: 破解商战背后的秘笈，启迪全新的商业机会，塑造独具竞争优势的盈利模式 | H10: 李光斗 | I10: 音频 | J10: 销售、市场品牌 | K10: 中层管理者、专业人士 | L10: 43262 | M10: 129 | N10: 21.19 | O10: 已完结 | P10: 365
A11: =ROW()-3 -> 8 | B11: VIP精品课 | C11: 岗位课 | D11: 金融理财 | E11: 金融知识与技能 | F11: 向松祚讲货币与金融 | G11: 货币是财富的载体，金融是时间的机器，看透货币本质，理解金融逻辑 | H11: 向松祚 | I11: 音频 | J11: CEO、管理者、财务 | K11: 中层管理者、高层管理者 | L11: 43293 | M11: 114 | N11: 19.71 | O11: 已完结 | P11: 199
A12: =ROW()-3 -> 9 | B12: VIP精品课 | C12: 岗位课 | D12: 人力资源 | E12: 劳动关系管理 | F12: 劳动法实操：企业用工风险防范指南 | G12: 劳动法实操：企业用工风险防范指南 | H12: 孔霞 | I12: 音频 | J12: 法务、HR | K12: 专业人士 | L12: 43321 | M12: 14 | N12: 2.88 | O12: 已完结 | P12: 99
A13: =ROW()-3 -> 10 | B13: VIP精品课 | C13: 岗位课 | D13: 市场品牌 | E13: 市场定位 | F13: 天猫创始总经理黄若的新零售课 | G13: 行业大咖30年的经验总结和100多个新鲜案例剖析，教你具体的商业策略与运营思路 | H13: 黄若 | I13: 音频 | J13: 销售、市场品牌 | K13: 中层管理者、专业人士 | L13: 43340 | M13: 50 | N13: 10.46 | O13: 已完结 | P13: 99
A14: =ROW()-3 -> 11 | B14: VIP精品课 | C14: 岗位课 | D14: 销售 | E14: 大客户销售 | F14: 觉伟讲销售：500强实战精华 | G14: 30年销售经验，6大模块倾力分享，帮助销售人员的个人成长，全面提升销售业绩 | H14: 李觉伟 | I14: 音频 | J14: 销售 | K14: 中层管理者、专业人士 | L14: 43346 | M14: 38 | N14: 7.5 | O14: 已完结 | P14: 199
A15: =ROW()-3 -> 12 | B15: VIP精品课 | C15: 岗位课 | D15: 市场品牌 | E15: 品牌管理 | F15: 品牌和营销：从入门到精通100讲 | G15: 营销=品牌思维+创造价值 | H15: 李婷 | I15: 音频 | J15: 销售、市场品牌 | K15: 中层管理者、专业人士 | L15: 43356 | M15: 100 | N15: 12.57 | O15: 已完结 | P15: 99
... A163: =ROW()-3 -> 160 | B163: VIP精品课 | C163: 岗位课 | D163: 金融理财 | E163: 证券 | F163: 高频交易15讲：探寻纳秒时代的金融市场 | G163: 新时代金融从业者的必修课 | H163: 李路 | I163: 音频 | J163: 管理者、财务 | K163: 专业人士 | L163: 44563 | M163: 17 | N163: 2.8 | O163: 已完结 | P163: 69
A164: =ROW()-3 -> 161 | B164: VIP精品课 | C164: 岗位课 | D164: 金融理财 | E164: 财富管理与资产配置 | F164: 投资理财必修的金融常识课 | G164: #NAME? | H164: 黎京林 | I164: 视频 | J164: 全员 | K164: 基层管理者、职场新人 | L164: 44563 | M164: 12 | N164: 2.3877778 | O164: 已完结 | P164: 39
A165: =ROW()-3 -> 162 | B165: VIP精品课 | C165: 岗位课 | D165: 金融理财 | E165: 财富管理与资产配置 | F165: 如何抓住潜伏的暴涨股 | G165: 识别被大家忽略的牛股 | H165: 闵遥 | I165: 视频 | J165: 全员 | K165: 基层管理者、职场新人 | L165: 44563 | M165: 16 | N165: 1.9572222 | O165: 已完结 | P165: 99
A166: =ROW()-3 -> 163 | B166: VIP精品课 | C166: 岗位课 | D166: 金融理财 | E166: 财富管理与资产配置 | F166: 规避人性的理财攻略 | G166: 规避人性的理财攻略 | H166: 戴翀 | I166: 视频 | J166: 全员 | K166: 基层管理者、职场新人 | L166: 44563 | M166: 16 | N166: 1.6169444 | O166: 已完结 | P166: 69
A167: =ROW()-3 -> 164 | B167: VIP精品课 | C167: 岗位课 | D167: 金融理财 | E167: 财富管理与资产配置 | F167: 港股打新如何提高中签率 | G167: 港股打新如何提高中签率 | H167: 刘怡伶 | I167: 视频 | J167: 全员 | K167: 基层管理者、职场新人 | L167: 44563 | M167: 11 | N167: 1.1744444 | O167: 已完结 | P167: 99
A168: =ROW()-3 -> 165 | B168: VIP精品课 | C168: 岗位课 | D168: 客户服务 | E168: 服务技巧 | F168: 透过结构看客户思维 | G168: 透过结构看客户思维 | H168: 覃曦 | I168: 视频 | J168: 全员 | K168: 基层管理者、中层管理者、职场新人 | L168: 44563 | M168: 12 | N168: 2.4947222 | O168: 已完结 | P168: 99
A169: =ROW()-3 -> 166 | B169: VIP精品课 | C169: 岗位课 | D169: 人力资源 | E169: 培训与开发 | F169: BEST高能经验萃取 | G169: BEST高能经验萃取 | H169: 邱伟 | I169: 视频 | J169: 全员 | K169: 基层管理者、中层管理者、职场新人 | L169: 44563 | M169: 13 | N169: 3.1302778 | O169: 已完结 | P169: 189
A170: =ROW()-3 -> 167 | B170: VIP精品课 | C170: 岗位课 | D170: 人力资源 | E170: 培训与开发 | F170: FAST高效课程开发 | G170: FAST高效课程开发 | H170: 邱伟 | I170: 视频 | J170: 全员 | K170: 基层管理者、中层管理者、专业人士 | L170: 44563 | M170: 17 | N170: 4.1327778 | O170: 已完结 | P170: 189
A171: =ROW()-3 -> 168 | B171: VIP精品课 | C171: 岗位课 | D171: 财务 | E171: 管理会计 | F171: 一名崩溃企业家的财务分析 | G171: 一名崩溃企业家的财务分析 | H171: 朱丽雅 | I171: 视频 | J171: 创始人、管理者 | K171: 高层管理者、专业人士 | L171: 44563 | M171: 14 | N171: 1.6863889 | O171: 已完结 | P171: 69
A172: =ROW()-3 -> 169 | B172: VIP精品课 | C172: 岗位课 | D172: 财务 | E172: 税务管理 | F172: 秒懂的电商财税风险管理 | G172: 秒懂的电商财税风险管理 | H172: 陶雯 | I172: 视频 | J172: 创始人、管理者 | K172: 中层管理者、高层管理者、专业人士 | L172: 44563 | M172: 15 | N172: 2.1155556 | O172: 已完结 | P172: 199
A173: =ROW()-3 -> 170 | B173: VIP精品课 | C173: 岗位课 | D173: 财务 | E173: 税务管理 | F173: 解救创业焦虑的财税课 | G173: 创业型公司的财务解决方案 | H173: 惠玉 | I173: 视频 | J173: 创始人、管理者 | K173: 中层管理者、高层管理者、专业人士 | L173: 44563 | M173: 25 | N173: 2.2175 | O173: 已完结 | P173: 199
A174: =ROW()-3 -> 171 | B174: VIP精品课 | C174: 岗位课 | D174: 金融理财 | E174: 财富管理与资产配置 | F174: 一门课学会基金投资 | G174: 基金上万只，怎么挑？ | H174: 黎京林 | I174: 视频 | J174: 管理者、财务 | K174: 专业人士 | L174: 44566 | M174: 16 | N174: 2.6 | O174: 未完结 | P174: 39
A175: =ROW()-3 -> 172 | B175: VIP精品课 | C175: 岗位课 | D175: 金融理财 | E175: 财富管理与资产配置 | F175: 公募基金的投资攻略课 | G175: 公募基金的投资攻略课 | H175: 黎京林 | I175: 视频 | J175: 全员 | K175: 基层管理者、中层管理者、职场新人 | L175: 44566 | M175: 17 | N175: 17 | O175: 更新中 | P175: 39
A176: =ROW()-3 -> 173 | B176: VIP精品课 | C176: 岗位课 | D176: 金融理财 | E176: 财富管理与资产配置 | F176: 新手投资者的数学投资思维课 | G176: 小白秒懂的数学投资思维 | H176: 顾艳 | I176: 视频 | J176: 全员 | K176: 基层管理者、中层管理者、职场新人 | L176: 44566 | M176: 22 | N176: 2.8519444 | O176: 已完结 | P176: 69
... A200: =ROW()-3 -> 197 | B200: VIP精品课 | C200: 商学院 | D200: 组织管理 | E200: 中层 | F200: 精益组织变革管理 | G200: 精益组织变革管理 | H200: 刘诚 | I200: 视频 | J200: 管理者 | K200: 中高层管理者 | L200: 44627 | M200: 10 | N200: 2.1 | O200: 已完结 | P200: 399
A201: =ROW()-3 -> 198 | B201: VIP精品课 | C201: 商学院 | D201: 战略规划 | E201: 高层 | F201: 张思宏：亚马逊增长双飞轮 | G201: 张思宏：亚马逊增长双飞轮 | H201: 张思宏 | I201: 视频 | J201: 管理者 | K201: 中层管理者，高层管理者 | L201: 44634 | M201: 20 | N201: 4.6 | O201: 已完结
A202: =ROW()-3 -> 199 | B202: VIP精品课 | C202: 其他 | D202: 职场技能 | E202: 职场认知 | F202: 张萌：高效打造个人品牌 | G202: 剖析自身实战经验，高效打造个人品牌养成方法 | H202: 张萌 | I202: 音频 | J202: 全员 | K202: 基层管理者、职场新人 | L202: 43238 | M202: 6 | N202: 1.09 | O202: 已完结 | P202: 9.9
A203: =ROW()-3 -> 200 | B203: VIP精品课 | C203: 其他 | D203: 人文社科 | E203: 情感心理 | F203: 袁春楠：脱胎换骨的人生整理术 | G203: 摆脱焦虑，重整人生、生活、职场、财富，轻装前行 | H203: 袁春楠 | I203: 音频 | J203: 全员 | K203: 中层管理者 | L203: 43238 | M203: 79 | N203: 24.04 | O203: 已完结 | P203: 199
A204: =ROW()-3 -> 201 | B204: VIP精品课 | C204: 其他 | D204: 人文社科 | E204: 人文历史 | F204: 周濂讲西方哲学智慧 | G204: 助你锻炼批判性思维，培养思考的逻辑性，更冷静有效地解决当下的问题 | H204: 周濂 | I204: 音频 | J204: 全员 | K204: 中层管理者 | L204: 43238 | M204: 101 | N204: 28.52 | O204: 已完结 | P204: 199
A205: =ROW()-3 -> 202 | B205: VIP精品课 | C205: 其他 | D205: 市场营销 | E205: 营销思维 | F205: 路长全营销课堂:改变命运的200条秘笈 | G205: 营销泰斗亲授，150堂课让你学会200个营销秘笈 | H205: 路长全 | I205: 音频 | J205: 销售、市场品牌 | K205: 中层管理者、专业人士 | L205: 43262 | M205: 153 | N205: 30.6 | O205: 已完结 | P205: 199
A206: =ROW()-3 -> 203 | B206: VIP精品课 | C206: 其他 | D206: 法律 | E206: 法律 | F206: 企业专利：驾驭未来商业的利器 | G206: 企业专利：驾驭未来商业的利器 | H206: 汤雄军 | I206: 音频 | J206: CEO、法务 | K206: 专业人士 | L206: 43321 | M206: 25 | N206: 4.82 | O206: 已完结 | P206: 59
A207: =ROW()-3 -> 204 | B207: VIP精品课 | C207: 其他 | D207: 人文社科 | E207: 亲子教育 | F207: 如何提升孩子的英语阅读理解能力 | G207: 原新东方名师带你打破英语阅读理解的壁垒 | H207: 孙健 | I207: 音频 | J207: 全员 | K207: 不限 | L207: 43381 | M207: 15 | N207: 3.08 | O207: 已完结 | P207: 99
A208: =ROW()-3 -> 205 | B208: VIP精品课 | C208: 其他 | D208: 人文社科 | E208: 人文历史 | F208: 为生命找道理 | G208: 前台湾大学哲学系教授为你透析人生哲学 | H208: 林火旺 | I208: 音频 | J208: 全员 | K208: 中层管理者 | L208: 43388 | M208: 257 | N208: 40.37 | O208: 已完结 | P208: 199
A209: =ROW()-3 -> 206 | B209: VIP精品课 | C209: 其他 | D209: 市场营销 | E209: 销售管理 | F209: 阿里铁军内训销售课 | G209: 阿里铁军10年10000人实战销售经验 | H209: 李立恒 | I209: 音频 | J209: 销售 | K209: 中层管理者、专业人士 | L209: 43573 | M209: 57 | N209: 12.8 | O209: 未完结 | P209: 99
A210: =ROW()-3 -> 207 | B210: VIP精品课 | C210: 其他 | D210: 法律 | E210: 法律 | F210: 如何打造安全的互联网内容公司 | G210: 规避内容政策风险，把握内容创新尺度 | H210: 压舱石 | I210: 音频 | J210: CEO、法务 | K210: 专业人士 | L210: 43598 | M210: 17 | N210: 2.66 | O210: 未完结 | P210: 198
A211: =ROW()-3 -> 208 | B211: VIP精品课 | C211: 其他 | D211: 人文社科 | E211: 亲子教育 | F211: 尼尔森讲正面管教 | G211: 全球1.5亿父母亲测有效的教育方法 | H211: 简·尼尔森 | I211: 音频 | J211: 全员 | K211: 不限 | L211: 43600 | M211: 70 | N211: 16.07 | O211: 已完结 | P211: 99
A212: =ROW()-3 -> 209 | B212: VIP精品课 | C212: 其他 | D212: 职场技能 | E212: 职场认知 | F212: 连结金融与职场的十本书 | G212: 秒懂金融知识，重塑职场认知 | H212: 王钊 | I212: 音频 | J212: 全员 | K212: 基层管理者、职场新人 | L212: 43634 | M212: 12 | N212: 4.83 | O212: 已完结 | P212: 49
A213: =ROW()-3 -> 210 | B213: VIP精品课 | C213: 其他 | D213: 职场技能 | E213: 外语技能 | F213: 王乐平：培养你的英语思维 | G213: 真正进入英语表达的语境，输出地道英语 | H213: 王乐平 | I213: 音频 | J213: 全员 | K213: 职场新人、专业人士 | L213: 43655 | M213: 59 | N213: 11.94 | O213: 已完结 | P213: 99
... A245: =ROW()-3 -> 242 | B245: VIP精品课 | C245: 其他 | D245: 人文社科 | E245: 生活健康 | F245: 佟彤中医养护50讲 | G245: 了解自愈力，构筑健康天然防御墙 | H245: 佟彤 | I245: 音频 | J245: 全员 | K245: 不限 | L245: 44457 | M245: 70 | N245: 11.6 | O245: 已完结 | P245: 129
A246: =ROW()-3 -> 243 | B246: VIP精品课 | C246: 其他 | D246: 人文社科 | E246: 亲子教育 | F246: 李玫瑾：中国父母家庭教育必修课 | G246: 中国父母家庭教育必修课 | H246: 李玫瑾 | I246: 音频 | J246: 全员 | K246: 不限 | L246: 44463 | M246: 52 | N246: 4.3 | O246: 已完结
A247: =ROW()-3 -> 244 | B247: VIP精品课 | C247: 其他 | D247: 法律 | E247: 法律 | F247: 绕过职场上的那些法律“坑”儿 | G247: 绕过职场上的那些法律“坑”儿 | H247: 张军杰 | I247: 音频 | J247: 法务、HR | K247: 专业人士 | L247: 44550 | M247: 15 | N247: 0.9 | O247: 未完结 | P247: 69
A248: =ROW()-3 -> 245 | B248: VIP精品课 | C248: 商学院 | D248: 管理认知 | E248: 基层 | F248: 陈雪频：新晋经理人十讲 | G248: 为商业管理提供世界级价值参考标准，推进企业管理实践与研究的国际化 | H248: 陈雪频 | I248: 音频 | J248: 管理者 | K248: 中层管理者、高层管理者 | L248: 43227 | M248: 11 | N248: 2.6 | O248: 已完结 | P248: 19.9
A249: =ROW()-3 -> 246 | B249: VIP精品课 | C249: 商学院 | D249: 组织发展 | E249: 基层 | F249: 倪云华的团队管理课 | G249: 最佳团队管理课系统方法论，为你定制最实用的团队管理课 | H249: 倪云华 | I249: 音频 | J249: 管理者 | K249: 中层管理者、高层管理者 | L249: 43238 | M249: 41 | N249: 6.97 | O249: 已完结 | P249: 99
A250: =ROW()-3 -> 247 | B250: VIP精品课 | C250: 商学院 | D250: 组织发展 | E250: 中层 | F250: 孙陶然亲授：企业管理实战兵法 | G250: 管理企业，不仅知道做什么，而且知道怎么做 | H250: 孙陶然 | I250: 音频 | J250: 管理者 | K250: 中层管理者、高层管理者 | L250: 43321 | M250: 30 | N250: 4.79 | O250: 已完结 | P250: 99
A251: =ROW()-3 -> 248 | B251: VIP精品课 | C251: 商学院 | D251: 人才发展 | E251: 中层 | F251: 陈序说教练型领导力 | G251: 国际教练领导力进阶课，提升个人领导能力，激活个人和组织潜能 | H251: 陈序 | I251: 音频 | J251: 管理者 | K251: 中层管理者、高层管理者 | L251: 43381 | M251: 41 | N251: 5.61 | O251: 已完结 | P251: 99
A252: =ROW()-3 -> 249 | B252: VIP精品课 | C252: 商学院 | D252: 管理认知 | E252: 中层 | F252: 叶阿次：高效管理100招 | G252: 100天迈向管人高手 | H252: 叶阿次 | I252: 音频 | J252: 管理者 | K252: 中层管理者、高层管理者 | L252: 43399 | M252: 101 | N252: 11.2 | O252: 已完结 | P252: 99
A253: =ROW()-3 -> 250 | B253: VIP精品课 | C253: 商学院 | D253: 商学院 | E253: 组织发展 | F253: 关苏哲：高效管理者的必备技能 | G253: 私董会总裁教练，带你全面学习管理技能 | H253: 关苏哲 | I253: 音频 | J253: 管理者 | K253: 中层管理者、高层管理者 | L253: 43488 | M253: 72 | N253: 10.77 | O253: 未完结 | P253: 129
A254: =ROW()-3 -> 251 | B254: VIP精品课 | C254: 商学院 | D254: 业务经营/战略规划 | E254: 高层 | F254: 湖畔三板斧：首次公开创业心法 | G254: 阿里合伙人亲授，回顾创业的关键节点、经验以及案例分析，传递决策背后的心法 | H254: 马云、校董冯仑、郭广昌、史玉柱 | I254: 音频 | J254: 创始人、CEO | K254: 高层管理者 | L254: 43552 | M254: 22 | N254: 23.03 | O254: 已完结 | P254: 99
A255: =ROW()-3 -> 252 | B255: VIP精品课 | C255: 商学院 | D255: 管理认知 | E255: 中层 | F255: 徐中：5分钟清晨领导课 | G255: 每天清晨5分钟领导力学习，先人一步获得成功 | H255: 徐中 | I255: 音频 | J255: 管理者 | K255: 中层管理者、高层管理者 | L255: 43553 | M255: 15 | N255: 6.64 | O255: 已完结 | P255: 99
A256: =ROW()-3 -> 253 | B256: VIP精品课 | C256: 商学院 | D256: 组织发展 | E256: 高层 | F256: 实战三板斧 | 阿里巴巴管理模式 | G256: 破译阿里文化基因，揭秘阿里管理系统 | H256: 天机 | I256: 音频 | J256: 管理者 | K256: 中层管理者、高层管理者 | L256: 43563 | M256: 74 | N256: 18.23 | O256: 已完结 | P256: 99
A257: =ROW()-3 -> 254 | B257: VIP精品课 | C257: 商学院 | D257: 文化建设 | E257: 基层 | F257: 顶级团队的八项习惯 | G257: 掌握打造顶级团队的方法与工具 | H257: 何建军 | I257: 音频 | J257: 管理者 | K257: 中层管理者、高层管理者 | L257: 43570 | M257: 17 | N257: 2.22 | O257: 已完结 | P257: 46
A258: =ROW()-3 -> 255 | B258: VIP精品课 | C258: 商学院 | D258: 组织发展 | E258: 基层 | F258: 倪云华：团队管理40条军规 | G258: 全网最受欢迎的团队管理视频课 | H258: 倪云华 | I258: 视频 | J258: 管理者 | K258: 中层管理者、高层管理者 | L258: 43579 | M258: 40 | N258: 3.57 | O258: 已完结 | P258: 99
... A313: =ROW()-3 -> 310 | B313: VIP精品课 | C313: 商学院 | D313: 组织发展 | E313: 高层 | F313: 杨国安的组织管理课 | G313: 杨国安的组织管理课 | H313: 杨国安 | I313: 音频 | J313: CEO、管理者、HR | K313: 中层管理者、专业人士 | L313: 44531 | M313: 33 | N313: 5.5 | O313: 已完结 | P313: 199
A314: =ROW()-3 -> 311 | B314: VIP精品课 | C314: 商学院 | D314: 组织发展 | E314: 中层 | F314: 财经专家张晓刚：商业思维提升课 | G314: 财经专家张晓刚：商业思维提升课 | H314: 张晓刚 | I314: 音频 | J314: 全员 | K314: 基层管理者、职场新人 | L314: 44531 | M314: 24 | N314: 4.0308333 | O314: 已完结
A315: =ROW()-3 -> 312 | B315: VIP精品课 | C315: 商学院 | D315: 组织发展 | E315: 基层 | F315: 橙色领导力 | G315: 橙色领导力 | H315: 新风向 | I315: 视频 | J315: CEO、管理者、HR | K315: 中层管理者、专业人士 | L315: 44550 | M315: 8 | N315: 1.3 | O315: 未完结 | P315: 128
A316: =ROW()-3 -> 313 | B316: VIP精品课 | C316: 商学院 | D316: 组织发展 | E316: 高层 | F316: 打造赋能敏捷组织，实现从0到1创新突破 | G316: 打造赋能敏捷组织，实现从0到1创新突破 | H316: 高松 | I316: 音频 | J316: CEO、管理者、HR | K316: 中层管理者、专业人士 | L316: 44550 | M316: 11 | N316: 2.2 | O316: 未完结 | P316: 129
A317: =ROW()-3 -> 314 | B317: VIP精品课 | C317: 商学院 | D317: 管理认知 | E317: 基层 | F317: 透过结构看管理思维 | G317: 透过结构看管理思维 | H317: 钟锐 | I317: 视频 | J317: 管理者 | K317: 基层管理者 | L317: 44563 | M317: 14 | N317: 3.1819444 | O317: 已完结
A318: =ROW()-3 -> 315 | B318: VIP精品课 | C318: 商学院 | D318: 管理认知 | E318: 中层 | F318: 樊登：可复制的领导力（2021升级版） | G318: 樊登：可复制的领导力（2021升级版） | H318: 樊登 | I318: 视频 | J318: 管理者 | K318: 高层管理者、中层管理者、基层管理者 | L318: 44575 | M318: 31 | N318: 7.0583333 | O318: 已完结 | P318: 218
A319: =ROW()-3 -> 316 | B319: VIP精品课 | C319: 商学院 | D319: 组织发展 | E319: 基层 | F319: 打造卓越团队的五大策略 | G319: 打造卓越团队的五大策略 | H319: 新风向 | I319: 视频 | J319: CEO、管理者 | K319: 中层管理者、高层管理者 | L319: 44599 | M319: 8 | N319: 0.9 | O319: 已完结 | P319: 128
A320: =ROW()-3 -> 317 | B320: VIP精品课 | C320: 商学院 | D320: 战略规划 | E320: 高层 | F320: 潘亦藩：企业战略的定位与配称 | G320: 潘亦藩：企业战略的定位与配称 | H320: 潘亦藩 | I320: 视频 | J320: 管理者 | K320: 中层管理者、高层管理者 | L320: 44620 | M320: 14 | N320: 4.48 | O320: 已完结 | P320: 89
A321: =ROW()-3 -> 318 | B321: VIP精品课 | C321: 商学院 | D321: 战略规划 | E321: 基层 | F321: 从战略到成功的七大行动 | G321: 从战略到成功的七大行动 | H321: 新风向 | I321: 视频 | J321: 管理者 | K321: 中层管理者、高层管理者 | L321: 44620 | M321: 4 | N321: 0.5 | O321: 已完结 | P321: 64
A322: =ROW()-3 -> 319 | B322: VIP精品课 | C322: 通用课 | D322: 沟通表达 | E322: 文案写作 | F322: 维佳：通向晋升之路的职场写作课 | G322: 每期一个职场写作小技巧，迅速提升职场写作功力，助你成为职场达人 | H322: 维佳 | I322: 音频 | J322: 全员 | K322: 职场新人 | L322: 43227 | M322: 33 | N322: 4.63 | O322: 已完结 | P322: 58
A323: =ROW()-3 -> 320 | B323: VIP精品课 | C323: 通用课 | D323: 沟通表达 | E323: 高效沟通 | F323: 乐嘉性格色彩·读心术 | G323: 了解每种性格的优势和过当，找到人与人最平衡的相处之道。 | H323: 乐嘉 | I323: 音频 | J323: CEO、管理者 | K323: 中层管理者 | L323: 43238 | M323: 63 | N323: 33.6 | O323: 已完结 | P323: 89
A324: =ROW()-3 -> 321 | B324: VIP精品课 | C324: 通用课 | D324: 沟通表达 | E324: 高效沟通/说服 | F324: 马东携奇葩天团亲授“好好说话” | G324: 避开沟通雷区，把话说得漂亮得体，听一门不容错过的说话课 | H324: 米果文化 | I324: 音频 | J324: 全员 | K324: 全员 | L324: 43238 | M324: 215 | N324: 32.7 | O324: 更新中 | P324: 0
A325: =ROW()-3 -> 322 | B325: VIP精品课 | C325: 通用课 | D325: 前沿趋势 | E325: 区块链 | F325: 人人能懂的区块链：从基础到实战 | G325: 系统读懂区块链知识，告别碎片化信息，深度学习区块链 | H325: 量子学派 | I325: 音频 | J325: CEO、管理者 | K325: 中层管理者 | L325: 43238 | M325: 22 | N325: 6.01 | O325: 已完结 | P325: 399
A326: =ROW()-3 -> 323 | B326: VIP精品课 | C326: 通用课 | D326: 沟通表达 | E326: 高效沟通 | F326: 奥美达人沟通课：重塑职场竞争力 | G326: 职场如何进行有效沟通，带你揭秘职场加薪晋升秘笈 | H326: 丁菱娟 | I326: 音频 | J326: 全员 | K326: 职场新人、专业人士 | L326: 43238 | M326: 19 | N326: 2.27 | O326: 已完结 | P326: 49
A327: =ROW()-3 -> 324 | B327: VIP精品课 | C327: 通用课 | D327: 沟通表达 | E327: 高效沟通 | F327: 超级聊天术：如何成为沟通高手 | G327: 沟通高手如何练就超级聊天术=人脉通行证+社会竞争力+超强适应 | H327: 张大鹏 | I327: 音频 | J327: 全员 | K327: 职场新人、专业人士 | L327: 43238 | M327: 38 | N327: 8.06 | O327: 已完结 | P327: 99
A328: =ROW()-3 -> 325 | B328: VIP精品课 | C328: 通用课 | D328: 沟通表达 | E328: 谈判 | F328: 快速谈判：用博弈技巧搞定交往难题 | G328: 美国大使馆三次、阿里巴巴27次特邀，谈判专家李力刚主讲 | H328: 李力刚 | I328: 音频 | J328: 全员 | K328: 职场新人、专业人士 | L328: 43238 | M328: 24 | N328: 4.15 | O328: 已完结 | P328: 68
A329: =ROW()-3 -> 326 | B329: VIP精品课 | C329: 通用课 | D329: 高效办公 | E329: 时间管理 | F329: 叶武滨时间管理10堂课-易效能 | G329: 时间管理10堂课，教你如何更有效率地工作和生活 | H329: 叶武滨 | I329: 音频 | J329: 全员 | K329: 基层管理者、职场新人 | L329: 43238 | M329: 17 | N329: 5.42 | O329: 已完结 | P329: 198
... A376: =ROW()-3 -> 373 | B376: VIP精品课 | C376: 通用课 | D376: 沟通表达 | E376: 文案写作 | F376: 灵感来了：李欣频的文案创意课 | G376: 从内核到实战，带你全面升级文案功力​ | H376: 李欣频 | I376: 音频 | J376: 全员 | K376: 职场新人、专业人士 | L376: 43759 | M376: 55 | N376: 11.2 | O376: 已完结 | P376: 199
A377: =ROW()-3 -> 374 | B377: VIP精品课 | C377: 通用课 | D377: 前沿趋势 | E377: 人工智能 | F377: 吕廷杰：5G新机遇60讲 | G377: 一张清晰的5G发展蓝图，让你真正搞懂5G，成为新机遇的受益者 | H377: 吕廷杰 | I377: 音频 | J377: 全员 | K377: 全员 | L377: 43776 | M377: 75 | N377: 12.8 | O377: 已完结 | P377: 199
A378: =ROW()-3 -> 375 | B378: VIP精品课 | C378: 通用课 | D378: 商业财经 | E378: 商业洞察 | F378: 刘澈：18位福布斯富豪的成功法则 | G378: 听大佬故事，学成功经验，让人生少走歪路 | H378: 刘澈 | I378: 音频 | J378: CEO、管理者、财务 | K378: 中层管理者、高层管理者 | L378: 43787 | M378: 106 | N378: 22.09 | O378: 未完结 | P378: 99
A379: =ROW()-3 -> 376 | B379: VIP精品课 | C379: 通用课 | D379: 沟通表达 | E379: 谈判 | F379: 谈判的72战术 | G379: 吴晓波、黄执中、伍思凯也在听的谈判课 | H379: 游梓翔 | I379: 音频 | J379: 全员 | K379: 职场新人、专业人士 | L379: 43832 | M379: 40 | N379: 7.17 | O379: 已完结 | P379: 99
A380: =ROW()-3 -> 377 | B380: VIP精品课 | C380: 通用课 | D380: 职场心理 | E380: 文化修养 | F380: 田艺苗：古典音乐很难吗 | G380: 每天10分钟，穿T恤欣赏古典音乐 | H380: 田艺苗 | I380: 音频 | J380: 全员 | K380: 不限 | L380: 43852 | M380: 637 | N380: 109.4 | O380: 已完结 | P380: 199
A381: =ROW()-3 -> 378 | B381: VIP精品课 | C381: 通用课 | D381: 前沿趋势 | E381: 科技漫谈 | F381: 刘慈欣的思想实验室 | G381: 《三体》之后，再度引爆你的想象力 | H381: 刘慈欣 | I381: 音频 | J381: 全员 | K381: 高层管理者 | L381: 43852 | M381: 34 | N381: 9.68 | O381: 已完结 | P381: 99
A382: =ROW()-3 -> 379 | B382: VIP精品课 | C382: 通用课 | D382: 前沿趋势 | E382: 科技漫谈 | F382: 李开复讲AI：十堂人工智能科学课 | G382: 人工智能领域37年从业经验，精炼十堂人工智能课 | H382: 李开复 | I382: 音频 | J382: CEO、管理者 | K382: 高层管理者 | L382: 43862 | M382: 10 | N382: 3.06 | O382: 已完结 | P382: 39
A383: =ROW()-3 -> 380 | B383: VIP精品课 | C383: 通用课 | D383: 职场心理 | E383: 文化修养 | F383: 余秋雨·中国文化必修课 | G383: 秋雨学院一日一课，提升你的文化修行 | H383: 余秋雨 | I383: 音频 | J383: 全员 | K383: 高层管理者 | L383: 43862 | M383: 290 | N383: 67.03 | O383: 已完结 | P383: 199
A384: =ROW()-3 -> 381 | B384: VIP精品课 | C384: 通用课 | D384: 商业财经 | E384: 商业洞察 | F384: 王玉荣：产业互联网20讲 | G384: 1380个行业成功拥抱互联网的秘诀 | H384: 王玉荣 | I384: 音频 | J384: CEO、管理者 | K384: 中层管理者 | L384: 43906 | M384: 20 | N384: 3.06 | O384: 已完结 | P384: 98
A385: =ROW()-3 -> 382 | B385: VIP精品课 | C385: 通用课 | D385: 商业财经 | E385: 宏观形势 | F385: 52期投资报告：预见下个财富风口 | G385: 四大财富维度着手，全面拆解数据背后的投资价值 | H385: 吴晓波频道 | I385: 音频 | J385: CEO、管理者、财务 | K385: 中层管理者、高层管理者 | L385: 43910 | M385: 68 | N385: 9.43 | O385: 已完结 | P385: 365
A386: =ROW()-3 -> 383 | B386: VIP精品课 | C386: 通用课 | D386: 高效办公 | E386: 时间管理 | F386: 张萌：精力管理50课 | G386: 学会拥有更多的时间保持高效率 | H386: 张萌 | I386: 音频 | J386: 全员 | K386: 基层管理者、职场新人 | L386: 43913 | M386: 68 | N386: 22.21 | O386: 已完结 | P386: 199
A387: =ROW()-3 -> 384 | B387: VIP精品课 | C387: 通用课 | D387: 高效办公 | E387: 时间管理 | F387: 张萌人生效率手册：时间管理50课 | G387: 拥有独属于自己的时间管理秘诀 | H387: 张萌 | I387: 音频 | J387: 全员 | K387: 职场新人 | L387: 43914 | M387: 54 | N387: 14.2 | O387: 已完结 | P387: 199
A388: =ROW()-3 -> 385 | B388: VIP精品课 | C388: 通用课 | D388: 高效办公 | E388: 工作方法 | F388: 笔记大神柯洲带你高效整理知识 | G388: 惠及50万CEO，带你摆脱低效的勤奋 | H388: 笔记侠 | I388: 音频 | J388: 全员 | K388: 职场新人、专业人士 | L388: 43920 | M388: 6 | N388: 1.13 | O388: 已完结 | P388: 19.9
A389: =ROW()-3 -> 386 | B389: VIP精品课 | C389: 通用课 | D389: 职场心理 | E389: 文化修养 | F389: 马未都《国宝100》 | G389: 马未都讲国宝，有知识、有历史、有情义 | H389: 马未都 | I389: 音频 | J389: 全员 | K389: 中层管理者 | L389: 43921 | M389: 101 | N389: 25.25 | O389: 已完结 | P389: 199
... A409: =ROW()-3 -> 406 | B409: VIP精品课 | C409: 通用课 | D409: 逻辑思维 | E409: 创新思维 | F409: 鲁百年：创新设计思维30讲 | G409: 全面掌握创新设计流程和落地 | H409: 鲁百年 | I409: 音频 | J409: 创始人、CEO | K409: 高层管理者 | L409: 44003 | M409: 30 | N409: 3.6 | O409: 已完结 | P409: 99
A410: =ROW()-3 -> 407 | B410: VIP精品课 | C410: 通用课 | D410: 逻辑思维 | E410: 认知思维 | F410: 清华教授吴国盛：科学简史 | G410: 清华教授带你从文理渗透的独特视角重新审视科学 | H410: 吴国盛 | I410: 音频 | J410: 全员 | K410: 高层管理者 | L410: 44019 | M410: 55 | N410: 11 | O410: 已完结 | P410: 89
A411: =ROW()-3 -> 408 | B411: VIP精品课 | C411: 通用课 | D411: 沟通表达 | E411: 高效沟通 | F411: 闪燕：关键对话 | G411: 成为冲突时刻的对话高手 | H411: 闪燕 | I411: 音频 | J411: 全员 | K411: 职场新人、基层管理者 | L411: 44032 | M411: 14 | N411: 2.8 | O411: 已完结 | P411: 99
A412: =ROW()-3 -> 409 | B412: VIP精品课 | C412: 通用课 | D412: 组织发展 | E412: 基层 | F412: 领跑新基建：5G前沿应用60讲 | G412: 5G时代的机遇与挑战 | H412: 刘大成 | I412: 音频 | J412: 全员 | K412: 高层管理者 | L412: 44039 | M412: 61 | N412: 7.5 | O412: 已完结 | P412: 199
A413: =ROW()-3 -> 410 | B413: VIP精品课 | C413: 通用课 | D413: 前沿趋势 | E413: 人工智能 | F413: 舍恩伯格：AI与我们 | 人工智能进阶通识课 | G413: 牛津大学教授的人工智能通识课 | H413: 维克托·迈尔-舍恩伯格 | I413: 音频 | J413: 全员 | K413: 高层管理者 | L413: 44046 | M413: 57 | N413: 14.25 | O413: 已完结 | P413: 69
A414: =ROW()-3 -> 411 | B414: VIP精品课 | C414: 通用课 | D414: 职场心理 | E414: 职场减压 | F414: 刘丰教授：禅修养心课 | G414: 解脱心灵束缚，彻悟人生意义与使命 | H414: 刘丰 | I414: 视频 | J414: 全员 | K414: 不限 | L414: 44054 | M414: 22 | N414: 4.4 | O414: 已完结 | P414: 99
A415: =ROW()-3 -> 412 | B415: VIP精品课 | C415: 通用课 | D415: 职场心理 | E415: 职场智慧 | F415: 职场名师训练营：提升10项竞争力 | G415: 职场高手的生存法则 | H415: 张萌 | I415: 音频 | J415: 全员 | K415: 基层管理者、职场新人 | L415: 44054 | M415: 104 | N415: 17.33 | O415: 已完结 | P415: 399
A416: =ROW()-3 -> 413 | B416: VIP精品课 | C416: 通用课 | D416: 职场心理 | E416: 职场减压 | F416: 减压静心：马老师教你Alex打坐法 | G416: 调节身心，涵养心性 | H416: Alexander Ma | I416: 音频 | J416: 全员 | K416: 不限 | L416: 44061 | M416: 89 | N416: 7.58 | O416: 已完结 | P416: 99
A417: =ROW()-3 -> 414 | B417: VIP精品课 | C417: 通用课 | D417: 高效办公 | E417: 办公工具 | F417: WPS表格极速入门教程 | G417: 零基础小白也能轻松学会 | H417: 秦川 | I417: 视频 | J417: 全员 | K417: 职场新人、专业人士 | L417: 44067 | M417: 50 | N417: 4.16 | O417: 已完结 | P417: 99
A418: =ROW()-3 -> 415 | B418: VIP精品课 | C418: 通用课 | D418: 商学院 | E418: 管理认知 | F418: 王玉荣：产业互联网案例20讲 | G418: 从知道别人的案例，到实现自己的传奇 | H418: 王玉荣 | I418: 音频 | J418: CEO、管理者 | K418: 中层管理者、专业人士 | L418: 44068 | M418: 20 | N418: 5.43 | O418: 已完结 | P418: 98
A419: =ROW()-3 -> 416 | B419: VIP精品课 | C419: 通用课 | D419: 商业财经 | E419: 宏观形势 | F419: 吴晓波领讲：2020经济趋势大课 | G419: 7位重磅大咖解读2020中国经济 | H419: 吴晓波等 | I419: 音频 | J419: CEO、管理者 | K419: 中层管理者、高层管理者 | L419: 44075 | M419: 47 | N419: 9.75 | O419: 未完结 | P419: 199
A420: =ROW()-3 -> 417 | B420: VIP精品课 | C420: 通用课 | D420: 商业财经 | E420: 宏观形势 | F420: 李俊慧的经济学课 | G420: 用经济学视角重新看待世界 | H420: 李俊慧 | I420: 音频 | J420: CEO、管理者 | K420: 中层管理者、高层管理者 | L420: 44075 | M420: 100 | N420: 25.3 | O420: 已完结 | P420: 199
...

Sheet 通用课
A1: 通用课频道
A2: 序号 | B2: 内容大类 | C2: 频道页 | D2: 一级标签 | E2: 二级标签 | F2: 课程名称 | G2: 副标题 | H2: 主讲人 | I2: 课程形式 | J2: 轻学堂上架日期 | K2: 课程总课时/集 | L2: 已上架课时总时间/h | M2: 更新状态 | N2: 单卖价格/元
A3: =ROW()-2 -> 1 | B3: VIP精品课 | C3: 通用课 | D3: 高效办公 | E3: 时间管理 | F3: 叶武滨时间管理10堂课-易效能 | G3: 时间管理10堂课，教你如何更有效率地工作和生活 | H3: 叶武滨 | I3: 音频 | J3: 43238 | K3: 20 | L3: 7.4641667 | M3: 已完结 | N3: 198
A4: =ROW()-2 -> 2 | B4: VIP精品课 | C4: 通用课 | D4: 高效办公 | E4: 工作方法 | F4: 薪资进阶手册：BAT工作法 | G4: 带你洞悉加薪本质，掌握名企工作法，带你摆脱焦虑，找准努力方向 | H4: 鲍艾乐 | I4: 音频 | J4: 43238 | K4: 150 | L4: 17.7025 | M4: 已完结 | N4: 99
A5: =ROW()-2 -> 3 | B5: VIP精品课 | C5: 通用课 | D5: 高效办公 | E5: 工作方法 | F5: 尹志豪：高效竞争力 | G5: 最高的效率达成目标，实现梦想的使用原理和方法 | H5: 尹志豪 | I5: 音频 | J5: 43318 | K5: 72 | L5: 15.259722 | M5: 已完结 | N5: 199
A6: =ROW()-2 -> 4 | B6: VIP精品课 | C6: 通用课 | D6: 高效办公 | E6: 办公工具 | F6: Excel零基础极速入门教程 | G6: 零基础迅速掌握职场高效技能 | H6: 秦川 | I6: 视频 | J6: 43417 | K6: 34 | L6: 3.8472222 | M6: 已完结 | N6: 99
A7: =ROW()-2 -> 5 | B7: VIP精品课 | C7: 通用课 | D7: 高效办公 | E7: 办公工具 | F7: Excel图表职场商务制作教程 | G7: Excel商务图表的精度，决定你工资的厚度 | H7: 秦川 | I7: 视频 | J7: 43426 | K7: 19 | L7: 7.3119444 | M7: 已完结 | N7: 99
A8: =ROW()-2 -> 6 | B8: VIP精品课 | C8: 通用课 | D8: 高效办公 | E8: 办公工具 | F8: Outlook职场快速上手教程 | G8: 职场邮件管理与工作事务管理利器 | H8: 秦川 | I8: 视频 | J8: 43427 | K8: 40 | L8: 2.9275 | M8: 已完结 | N8: 50
A9: =ROW()-2 -> 7 | B9: VIP精品课 | C9: 通用课 | D9: 高效办公 | E9: 办公工具 | F9: photoshop零基础极速入门教程 | G9: 掌握PS图片处理技能，小白也能出作品 | H9: 秦川 | I9: 视频 | J9: 43427 | K9: 50 | L9: 7.6994444 | M9: 已完结 | N9: 99
A10: =ROW()-2 -> 8 | B10: VIP精品课 | C10: 通用课 | D10: 高效办公 | E10: 办公工具 | F10: Word排版教程 | G10: 只有深知word原理，才能搞定word排版 | H10: 秦川 | I10: 视频 | J10: 43430 | K10: 33 | L10: 3.9175 | M10: 更新中 | N10: 50
A11: =ROW()-2 -> 9 | B11: VIP精品课 | C11: 通用课 | D11: 高效办公 | E11: 办公工具 | F11: PPT图形高效绘制教程 | G11: PPT做得好，下班回得早！ | H11: 秦川 | I11: 视频 | J11: 43430 | K11: 10 | L11: 2.4908333 | M11: 已完结 | N11: 59
A12: =ROW()-2 -> 10 | B12: VIP精品课 | C12: 通用课 | D12: 高效办公 | E12: 时间管理 | F12: 跟大神学实用时间管理术 | G12: 最顺应人性的时间管理课程 | H12: 纪元 | I12: 音频 | J12: 43571 | K12: 59 | L12: 7.5022222 | M12: 已完结 | N12: 99
A13: =ROW()-2 -> 11 | B13: VIP精品课 | C13: 通用课 | D13: 高效办公 | E13: 办公工具 | F13: 平面设计：创意思维成长 | G13: 学习如何进行视觉交流 | H13: Michael Loos | I13: 视频 | J13: 43663 | K13: 14 | L13: 5.9477778 | M13: 已完结 | N13: 66
A14: =ROW()-2 -> 12 | B14: VIP精品课 | C14: 通用课 | D14: 高效办公 | E14: 工作方法 | F14: 方军：60项硅谷高效工作法 | G14: 系统学习超级个体工作法与团队工作法 | H14: 方军 | I14: 音频 | J14: 43690 | K14: 73 | L14: 9.6747222 | M14: 已完结 | N14: 180
... A39: =ROW()-2 -> 37 | B39: VIP精品课 | C39: 通用课 | D39: 高效办公 | E39: 办公工具 | F39: 秦川：PPT标准化高效制作设计 | G39: 秦川：PPT标准化高效制作设计 | H39: 秦川 | I39: 视频 | J39: 44627 | K39: 9 | L39: 2.3 | M39: 已完结 | N39: 129
A40: =ROW()-2 -> 38 | B40: VIP精品课 | C40: 通用课 | D40: 高效办公 | E40: 目标管理 | F40: 目标管理 | G40: 目标管理 | H40: 新风向 | I40: 视频 | J40: 管理者 | K40: 中层管理者，高层管理者 | L40: 44634 | M40: 7 | N40: 0.8 | O40: 已完结
A41: =ROW()-2 -> 39 | B41: VIP精品课 | C41: 通用课 | D41: 沟通表达 | E41: 文案写作 | F41: 维佳：通向晋升之路的职场写作课 | G41: 每期一个职场写作小技巧，迅速提升职场写作功力，助你成为职场达人 | H41: 维佳 | I41: 音频 | J41: 43227 | K41: 33 | L41: 4.6330556 | M41: 已完结 | N41: 58
A42: =ROW()-2 -> 40 | B42: VIP精品课 | C42: 通用课 | D42: 沟通表达 | E42: 高效沟通 | F42: 奥美达人沟通课：重塑职场竞争力 | G42: 职场如何进行有效沟通，带你揭秘职场加薪晋升秘笈 | H42: 丁菱娟 | I42: 音频 | J42: 43238 | K42: 23 | L42: 2.5863889 | M42: 已完结 | N42: 49
A43: =ROW()-2 -> 41 | B43: VIP精品课 | C43: 通用课 | D43: 沟通表达 | E43: 高效沟通 | F43: 超级聊天术：如何成为沟通高手 | G43: 沟通高手如何练就超级聊天术=人脉通行证+社会竞争力+超强适应 | H43: 张大鹏 | I43: 音频 | J43: 43238 | K43: 39 | L43: 8.1741667 | M43: 已完结 | N43: 99
A44: =ROW()-2 -> 42 | B44: VIP精品课 | C44: 通用课 | D44: 沟通表达 | E44: 谈判 | F44: 快速谈判：用博弈技巧搞定交往难题 | G44: 美国大使馆三次、阿里巴巴27次特邀，谈判专家李力刚主讲 | H44: 李力刚 | I44: 音频 | J44: 43238 | K44: 24 | L44: 4.15 | M44: 已完结 | N44: 68
A45: =ROW()-2 -> 43 | B45: VIP精品课 | C45: 通用课 | D45: 沟通表达 | E45: 演讲 | F45: 从小白到演讲高手 | G45: 帮你收获最精华的演讲技巧，助你获得好口才，改变人生 | H45: 龙兄 | I45: 音频 | J45: 43238 | K45: 32 | L45: 5.9369444 | M45: 已完结 | N45: 99
A46: =ROW()-2 -> 44 | B46: VIP精品课 | C46: 通用课 | D46: 沟通表达 | E46: 高效沟通 | F46: 乐嘉性格色彩·读心术 | G46: 了解每种性格的优势和过当，找到人与人最平衡的相处之道。 | H46: 乐嘉 | I46: 音频 | J46: 43238 | K46: 111 | L46: 33.6225 | M46: 已完结 | N46: 199
A47: =ROW()-2 -> 45 | B47: VIP精品课 | C47: 通用课 | D47: 沟通表达 | E47: 高效沟通/说服 | F47: 马东携奇葩天团亲授“好好说话” | G47: 避开沟通雷区，把话说得漂亮得体，听一门不容错过的说话课 | H47: 米果文化 | I47: 音频 | J47: 43238 | K47: 280 | L47: 32.7425 | M47: 更新中 | N47: 198
A48: =ROW()-2 -> 46 | B48: VIP精品课 | C48: 通用课 | D48: 沟通表达 | E48: 演讲 | F48: 龙兄：跟乔布斯学演讲 | G48: 5节精品课，收获大师级演讲技巧 | H48: 龙兄 | I48: 音频 | J48: 43318 | K48: 7 | L48: 1.0577778 | M48: 已完结 | N48: 9.9
A49: =ROW()-2 -> 47 | B49: VIP精品课 | C49: 通用课 | D49: 沟通表达 | E49: 文案写作 | F49: 灵感来了：李欣频的文案创意课 | G49: 从内核到实战，带你全面升级文案功力​ | H49: 李欣频 | I49: 音频 | J49: 43759 | K49: 55 | L49: 11.2025 | M49: 已完结 | N49: 199
A50: =ROW()-2 -> 48 | B50: VIP精品课 | C50: 通用课 | D50: 沟通表达 | E50: 谈判 | F50: 谈判的72战术 | G50: 吴晓波、黄执中、伍思凯也在听的谈判课 | H50: 游梓翔 | I50: 音频 | J50: 43832 | K50: 40 | L50: 7.1666667 | M50: 已完结 | N50: 99
A51: =ROW()-2 -> 49 | B51: VIP精品课 | C51: 通用课 | D51: 沟通表达 | E51: 高效沟通/说服 | F51: 闪燕：关键对话 | G51: 成为冲突时刻的对话高手 | H51: 闪燕 | I51: 音频 | J51: 44032 | K51: 14 | L51: 2.5327778 | M51: 已完结 | N51: 99
A52: =ROW()-2 -> 50 | B52: VIP精品课 | C52: 通用课 | D52: 沟通表达 | E52: 说服 | F52: 韩焱：成为说服高手的心理课 | G52: 劝服自己，影响大众 | H52: 韩焱 | I52: 音频 | J52: 44126 | K52: 79 | L52: 19.671667 | M52: 已完结 | N52: 99
... A70: =ROW()-2 -> 68 | B70: VIP精品课 | C70: 通用课 | D70: 沟通表达 | E70: 文案写作 | F70: 徐公子的阅读成长课10讲 | G70: 徐公子的阅读成长课10讲 | H70: 徐玉贞 | I70: 音频 | J70: 44517 | K70: 11 | L70: 1.915 | M70: 已完结 | N70: 69
A71: =ROW()-2 -> 69 | B71: VIP精品课 | C71: 通用课 | D71: 沟通表达 | E71: 工作汇报 | F71: 朱老丝：有说服力的工作汇报 | G71: 朱老丝：有说服力的工作汇报 | H71: 朱老丝 | I71: 音频 | J71: 44533 | K71: 12 | L71: 1.6386111 | M71: 已完结
A72: =ROW()-2 -> 70 | B72: VIP精品课 | C72: 通用课 | D72: 沟通表达 | E72: 文案写作 | F72: 营销实战 | G72: 软文写作与销售文案 | H72: 林杉 | I72: 音频 | J72: 44538 | K72: 9 | L72: 0.81083333 | M72: 已完结 | N72: 19
A73: =ROW()-2 -> 71 | B73: VIP精品课 | C73: 通用课 | D73: 沟通表达 | E73: 高效沟通 | F73: 即兴表达 | G73: 用得上的8个说话秘笈 | H73: 卿杨剑 | I73: 音频 | J73: 44538 | K73: 24 | L73: 5.5297222 | M73: 已完结
A74: =ROW()-2 -> 72 | B74: VIP精品课 | C74: 通用课 | D74: 沟通表达 | E74: 高效沟通 | F74: 用声音搞定成交 | G74: 用声音搞定成交 | H74: 涂梦珊 | I74: 音频 | J74: 全员 | K74: 不限 | L74: 44509 | M74: 26 | N74: 3.53 | O74: 已完结 | P74: 99
A75: =ROW()-2 -> 73 | B75: VIP精品课 | C75: 通用课 | D75: 沟通表达 | E75: 谈判 | F75: 24招变身谈判专家 | G75: 24招变身谈判专家 | H75: 王詠 | I75: 音频 | J75: 全员 | K75: 不限 | L75: 44509 | M75: 25 | N75: 3.86 | O75: 已完结 | P75: 99
A76: =ROW()-2 -> 74 | B76: VIP精品课 | C76: 通用课 | D76: 沟通表达 | E76: 高效沟通 | F76: 李筱懿的职场智慧15条 | G76: 李筱懿的职场智慧15条 | H76: 李筱懿 | I76: 音频 | J76: 全员 | K76: 不限 | L76: 44509 | M76: 16 | N76: 2.54 | O76: 已完结 | P76: 99
A77: =ROW()-2 -> 75 | B77: VIP精品课 | C77: 通用课 | D77: 逻辑思维 | E77: 结构思考 | F77: 职场思维实战20讲 | G77: 逻辑助力职场，思维改变人生；有效提升你的逻辑思维力！ | H77: 耿人健 | I77: 音频 | J77: 43420 | K77: 24 | L77: 4.6563889 | M77: 已完结 | N77: 99
A78: =ROW()-2 -> 76 | B78: VIP精品课 | C78: 通用课 | D78: 逻辑思维 | E78: 结构思考 | F78: 六顶思考帽 | G78: 高效思考的14堂必修课 | H78: 曾婷 | I78: 音频 | J78: 43536 | K78: 14 | L78: 2.6769444 | M78: 已完结 | N78: 69
A79: =ROW()-2 -> 77 | B79: VIP精品课 | C79: 通用课 | D79: 逻辑思维 | E79: 认知思维 | F79: 陈昌凯的心理学课 | G79: 100讲详解心理学原理，从源头重构你的认知体系 | H79: 陈昌凯 | I79: 音频 | J79: 43945 | K79: 103 | L79: 23.793056 | M79: 已完结 | N79: 199
A80: =ROW()-2 -> 78 | B80: VIP精品课 | C80: 通用课 | D80: 逻辑思维 | E80: 结构思考 | F80: 结构思考力 | G80: 最简单、直接和有效的结构思考力训练方法 | H80: 李忠秋 | I80: 音频 | J80: 43960 | K80: 13 | L80: 2.0761111 | M80: 已完结 | N80: 199
A81: =ROW()-2 -> 79 | B81: VIP精品课 | C81: 通用课 | D81: 逻辑思维 | E81: 认知思维 | F81: 全球精英的5分钟成长学院 | G81: 为你交付一套“巨人”的思维工具 | H81: 喜马听世界 | I81: 音频 | J81: 43978 | K81: 504 | L81: 56.043889 | M81: 更新中 | N81: 199
A82: =ROW()-2 -> 80 | B82: VIP精品课 | C82: 通用课 | D82: 逻辑思维 | E82: 创新思维 | F82: 鲁百年：创新设计思维30讲 | G82: 全面掌握创新设计流程和落地 | H82: 鲁百年 | I82: 音频 | J82: 44003 | K82: 30 | L82: 6.365 | M82: 已完结 | N82: 99
A83: =ROW()-2 -> 81 | B83: VIP精品课 | C83: 通用课 | D83: 逻辑思维 | E83: 认知思维 | F83: 清华教授吴国盛：科学简史 | G83: 清华教授带你从文理渗透的独特视角重新审视科学 | H83: 吴国盛 | I83: 音频 | J83: 44019 | K83: 57 | L83: 11.418333 | M83: 已完结 | N83: 99
A84: =ROW()-2 -> 82 | B84: VIP精品课 | C84: 通用课 | D84: 逻辑思维 | E84: 认知思维 | F84: 北大博士李松蔚认知思维16讲 | G84: 快速跳出惯性思维 | H84: 李松蔚 | I84: 音频 | J84: 44120 | K84: 19 | L84: 6.5163889 | M84: 已完结 | N84: 99
A85: =ROW()-2 -> 83 | B85: VIP精品课 | C85: 通用课 | D85: 逻辑思维 | E85: 创新思维 | F85: 哈佛名师Beth的创意思维课 | G85: 英语原声，职场人创业者必备 | H85: 贝丝·奥特林格 | I85: 音频 | J85: 44125 | K85: 53 | L85: 9.1875 | M85: 已完结 | N85: 99
A86: =ROW()-2 -> 84 | B86: VIP精品课 | C86: 通用课 | D86: 逻辑思维 | E86: 创新思维 | F86: 人人都需要的创意思维课 | G86: 科学开脑，创意源源不断 | H86: 王东魁 | I86: 视频 | J86: 44251 | K86: 5 | L86: 2.3808333 | M86: 已完结 | N86: 19.9
A87: =ROW()-2 -> 85 | B87: VIP精品课 | C87: 通用课 | D87: 逻辑思维 | E87: 认知思维 | F87: 魏知超：心理学新知课 | G87: 你不知道的心理学新知 | H87: 魏知超 | I87: 音频 | J87: 44270 | K87: 126 | L87: 26.556389 | M87: 已完结 | N87: 99
A88: =ROW()-2 -> 86 | B88: VIP精品课 | C88: 通用课 | D88: 逻辑思维 | E88: 认知思维 | F88: 傅佩荣的人生哲学课 | G88: 看清纷繁事物背后的本质，找到幸福生活的真谛 | H88: 傅佩荣 | I88: 音频 | J88: 44279 | K88: 152 | L88: 35.080278 | M88: 已完结 | N88: 199
... A100: =ROW()-2 -> 98 | B100: VIP精品课 | C100: 通用课 | D100: 逻辑思维 | E100: 创新思维 | F100: 国际TRIZ学会认证TRIZ课程姜台林 | G100: 国际TRIZ学会认证TRIZ课程姜台林 | H100: 姜台林 | I100: 视频 | J100: 44620 | K100: 19 | L100: 5.81 | M100: 已完结 | N100: 498
A101: =ROW()-2 -> 99 | B101: VIP精品课 | C101: 通用课 | D101: 逻辑思维 | E101: 创新思维 | F101: 超级创新力：设计思考企业实战攻略 | G101: 超级创新力：设计思考企业实战攻略 | H101: 刘恭甫 | I101: 音频 | J101: 管理者和HR | K101: 中层管理者，高层管理者、HR | L101: 44634 | M101: 11 | N101: 2.3 | O101: 未完结
A102: =ROW()-2 -> 100 | B102: VIP精品课 | C102: 通用课 | D102: 前沿趋势 | E102: 区块链 | F102: 人人能懂的区块链：从基础到实战 | G102: 系统读懂区块链知识，告别碎片化信息，深度学习区块链 | H102: 量子学派 | I102: 音频 | J102: 43238 | K102: 64 | L102: 18.416111 | M102: 已完结 | N102: 399
A103: =ROW()-2 -> 101 | B103: VIP精品课 | C103: 通用课 | D103: 前沿趋势 | E103: 科技漫谈 | F103: 方军：读懂互联网未来 | G103: 精选50+本互联网经典与前沿好书，萃取成100+期精华主题 | H103: 方军 | I103: 音频 | J103: 43238 | K103: 116 | L103: 33.506111 | M103: 已完结 | N103: 99
A104: =ROW()-2 -> 102 | B104: VIP精品课 | C104: 通用课 | D104: 前沿趋势 | E104: 5G | F104: 掘金5G通信革命，谁将最终获益？ | G104: 大话5G，听懂未来 | H104: 奥卡姆剃刀 | I104: 音频 | J104: 43700 | K104: 30 | L104: 4.4786111 | M104: 已完结 | N104: 128
A105: =ROW()-2 -> 103 | B105: VIP精品课 | C105: 通用课 | D105: 前沿趋势 | E105: 科技漫谈 | F105: 刘慈欣的思想实验室 | G105: 《三体》之后，再度引爆你的想象力 | H105: 刘慈欣 | I105: 音频 | J105: 43700 | K105: 32 | L105: 9.6791667 | M105: 已完结 | N105: 99
A106: =ROW()-2 -> 104 | B106: VIP精品课 | C106: 通用课 | D106: 前沿趋势 | E106: 人工智能 | F106: 李开复讲AI：十堂人工智能科学课 | G106: 人工智能领域37年从业经验，精炼十堂人工智能课 | H106: 李开复 | I106: 音频 | J106: 43706 | K106: 10 | L106: 3.0597222 | M106: 已完结 | N106: 39
A107: =ROW()-2 -> 105 | B107: VIP精品课 | C107: 通用课 | D107: 前沿趋势 | E107: 5G | F107: 吕廷杰：5G新机遇60讲 | G107: 一张清晰的5G发展蓝图，让你真正搞懂5G，成为新机遇的受益者 | H107: 吕廷杰 | I107: 音频 | J107: 43776 | K107: 75 | L107: 12.760278 | M107: 已完结 | N107: 0
A108: =ROW()-2 -> 106 | B108: VIP精品课 | C108: 通用课 | D108: 前沿趋势 | E108: 物联网 | F108: 王玉荣：产业互联网20讲 | G108: 1380个行业成功拥抱互联网的秘诀 | H108: 王玉荣 | I108: 音频 | J108: 43906 | K108: 21 | L108: 3.2258333 | M108: 已完结 | N108: 98
A109: =ROW()-2 -> 107 | B109: VIP精品课 | C109: 通用课 | D109: 前沿趋势 | E109: 人工智能 | F109: 吴霁虹：人工智能赋能60讲 | G109: 不懂技术也能听懂的AI赋能课 | H109: 吴霁虹 | I109: 音频 | J109: 43938 | K109: 62 | L109: 13.688333 | M109: 更新中 | N109: 99
A110: =ROW()-2 -> 108 | B110: VIP精品课 | C110: 通用课 | D110: 前沿趋势 | E110: 区块链 | F110: 从0到1，全面学透区块链(2020版) | G110: 携中美16位专家精心打造，全新的区块链知识体系 | H110: 朱嘉伟 | I110: 音频 | J110: 43966 | K110: 38 | L110: 7.3430556 | M110: 已完结 | N110: 199
A111: =ROW()-2 -> 109 | B111: VIP精品课 | C111: 通用课 | D111: 前沿趋势 | E111: 5G | F111: 领跑新基建：5G前沿应用60讲 | G111: 5G时代的机遇与挑战 | H111: 刘大成 | I111: 音频 | J111: 44039 | K111: 61 | L111: 10.649167 | M111: 已完结 | N111: 199
A112: =ROW()-2 -> 110 | B112: VIP精品课 | C112: 通用课 | D112: 前沿趋势 | E112: 人工智能 | F112: 舍恩伯格：AI与我们 | 人工智能进阶通识课 | G112: 牛津大学教授的人工智能通识课 | H112: 维克托·迈尔-舍恩伯格 | I112: 音频 | J112: 44046 | K112: 57 | L112: 14.363056 | M112: 已完结 | N112: 69
A113: =ROW()-2 -> 111 | B113: VIP精品课 | C113: 通用课 | D113: 前沿趋势 | E113: 物联网 | F113: 王玉荣：产业互联网案例20讲 | G113: 从知道别人的案例，到实现自己的传奇 | H113: 王玉荣 | I113: 音频 | J113: 44068 | K113: 20 | L113: 5.6111111 | M113: 已完结 | N113: 98
... A170: =ROW()-2 -> 168 | B170: VIP精品课 | C170: 通用课 | D170: 商业财经 | E170: 宏观形势 | F170: 李俊慧的经济学课 · 第三季 | G170: 李俊慧的经济学课 · 第三季 | H170: 李俊慧 | I170: 音频 | J170: 44586 | K170: 102 | L170: 27.007222 | M170: 更新中 | N170: 199
A171: =ROW()-3 -> 168 | B171: VIP精品课 | C171: 通用课 | D171: 商业财经 | E171: 商业洞察 | F171: 商业模式画布 | G171: 商业模式设计与创新 | H171: 倪云华 | I171: 视频 | J171: 44599 | K171: 17 | L171: 3.76 | M171: 未完结 | N171: 199
A172: =ROW()-2 -> 170 | B172: VIP精品课 | C172: 通用课 | D172: 商业财经 | E172: 宏观形势 | F172: 清华韩秀云讲经济·第三季 | G172: 清华韩秀云讲经济·第三季 | H172: 韩秀云 | I172: 音频 | J172: 44606 | K172: 34 | L172: 8 | M172: 已完结 | N172: 299
A173: =ROW()-2 -> 171 | B173: VIP精品课 | C173: 通用课 | D173: 数据分析 | E173: 数据分析/数据挖掘 | F173: 商业数据分析师通识课 | G173: 从数据中精准发现问题，快人一步 | H173: CDA数据分析师 | I173: 视频 | J173: 44140 | K173: 29 | L173: 14.644722 | M173: 已完结 | N173: 699
A174: =ROW()-2 -> 172 | B174: VIP精品课 | C174: 通用课 | D174: 数据分析 | E174: 数据分析 | F174: 业务数据分析基础入门课 | G174: 业务数据分析基础入门课 | H174: 徐双六 | I174: 视频 | J174: 44538 | K174: 10 | L174: 8.6122222 | M174: 已完结 | N174: 99
A175: =ROW()-2 -> 173 | B175: VIP精品课 | C175: 通用课 | D175: 数据分析 | E175: 数据分析 | F175: Python数据可视化分析 | G175: Python数据可视化分析 | H175: 小凯 | I175: 视频 | J175: 44539 | K175: 33 | L175: 6.1780556 | M175: 已完结 | N175: 88
A176: =ROW()-2 -> 174 | B176: VIP精品课 | C176: 通用课 | D176: 项目管理 | E176: 项目管理思维/项目规划/启动 | F176: 郭致星：项目管理的思维与实践 | G176: 掌握项目管理的思维与方法，在不确定性中前行 | H176: 郭致星 | I176: 音频 | J176: 43412 | K176: 76 | L176: 13.188611 | M176: 已完结 | N176: 199
A177: =ROW()-2 -> 175 | B177: VIP精品课 | C177: 通用课 | D177: 项目管理 | E177: 项目过程管理 | F177: 忻宏伟：项目经理实战手册 | G177: 真正让你学会做项目，做出好项目 | H177: 忻宏伟 | I177: 音频 | J177: 43928 | K177: 20 | L177: 3.4988889 | M177: 已完结 | N177: 49.9
A178: =ROW()-2 -> 176 | B178: VIP精品课 | C178: 通用课 | D178: 项目管理 | E178: 项目管理思维 | F178: 项目化思维+高效工作 | G178: 高绩效完成关键任务的制胜法宝 | H178: 新风向 | I178: 视频 | J178: 44403 | K178: 9 | L178: 1.425 | M178: 已完结 | N178: 128
A179: =ROW()-2 -> 177 | B179: VIP精品课 | C179: 通用课 | D179: 项目管理 | E179: 项目过程管理 | F179: 项目的目标计划和过程控制 | G179: 项目的目标计划和过程控制 | H179: 肖振峰 | I179: 视频 | J179: 44538 | K179: 7 | L179: 2.5477778 | M179: 已完结 | N179: 59
A180: =ROW()-2 -> 178 | B180: VIP精品课 | C180: 通用课 | D180: 项目管理 | E180: 项目管理思维 | F180: 人生效率手册：项目管理实战课 | G180: 人生效率手册：项目管理实战课 | H180: 丛雪 | I180: 音频 | J180: 44538 | K180: 35 | L180: 6.465 | M180: 已完结 | N180: 99
A181: =ROW()-2 -> 179 | B181: VIP精品课 | C181: 通用课 | D181: 项目管理 | E181: 项目管理思维 | F181: 高屹：项目经理是怎么炼成的 | G181: 高屹：项目经理是怎么炼成的 | H181: 高屹 | I181: 视频 | J181: 44538 | K181: 38 | L181: 6.9475 | M181: 已完结 | N181: 199
A182: =ROW()-2 -> 180 | B182: VIP精品课 | C182: 通用课 | D182: 项目管理 | E182: 项目管理思维 | F182: 透过结构看项目管理 | G182: 透过结构看项目管理 | H182: 刘磊 | I182: 视频 | J182: 44562 | K182: 12 | L182: 2.8161111 | M182: 已完结 | N182: 129
A183: =ROW()-2 -> 181 | B183: VIP精品课 | C183: 通用课 | D183: 用户思维 | E183: 运营思维 | F183: 阿里老兵增长思维课 | G183: 带你洞悉互联网用户增长的核心玩法 | H183: 聂风 | I183: 音频 | J183: 43368 | K183: 33 | L183: 6.0225 | M183: 已完结 | N183: 99
... A185: =ROW()-2 -> 183 | B185: VIP精品课 | C185: 通用课 | D185: 用户思维 | E185: 运营思维 | F185: 黄有璨运营课：助你赢得用户资源 | G185: 升级认知，做对运营 | H185: 黄有璨 | I185: 音频 | J185: 44160 | K185: 16 | L185: 4.3141667 | M185: 已完结 | N185: 88
A186: =ROW()-2 -> 184 | B186: VIP精品课 | C186: 通用课 | D186: 用户思维 | E186: 产品思维 | F186: 贾伟：产品三观与用户思维10讲 | G186: 产品三观10讲 | H186: 贾伟 | I186: 音频 | J186: 44532 | K186: 4 | L186: 0.60333333 | M186: 更新中
A187: =ROW()-2 -> 185 | B187: VIP精品课 | C187: 通用课 | D187: 用户思维 | E187: 产品思维 | F187: 高雄勇：我在小米做爆品 | G187: 高雄勇：我在小米做爆品 | H187: 高雄勇 | I187: 视频 | J187: 44535 | K187: 50 | L187: 5.5466667 | M187: 已完结 | N187: 199
A188: =ROW()-2 -> 186 | B188: VIP精品课 | C188: 通用课 | D188: 用户思维 | E188: 产品思维 | F188: 感性商业 | G188: 世界500强企业通用的用户体验增长方法论 | H188: 罗浩 | I188: 视频 | J188: 44535 | K188: 10 | L188: 1.5977778 | M188: 已完结 | N188: 59
A189: =ROW()-2 -> 187 | B189: VIP精品课 | C189: 通用课 | D189: 用户思维 | E189: 产品思维 | F189: 10堂课打造系统产品思维 | G189: 10堂课打造系统产品思维 | H189: 水滴产品学院 | I189: 视频 | J189: 44537 | K189: 38 | L189: 21.093889 | M189: 已完结
A190: =ROW()-2 -> 188 | B190: VIP精品课 | C190: 通用课 | D190: 用户思维 | E190: 产品思维 | F190: 腾讯产品方法18讲 | G190: 千款产品背后的关键思考 | H190: 腾讯大学 | I190: 音频 | J190: 44538 | K190: 21 | L190: 4.6052778 | M190: 已完结 | N190: 49
A191: =ROW()-2 -> 189 | B191: VIP精品课 | C191: 通用课 | D191: 职场心理 | E191: 职场智慧 | F191: 老板思维：轻松解决30个职场冲突 | G191: 老板思维：轻松解决30个职场冲突 | H191: 朱小兰 | I191: 音频 | J191: 44613 | K191: 31 | L191: 5.02 | M191: 未完结 | N191: 99
A192: =ROW()-2 -> 190 | B192: VIP精品课 | C192: 通用课 | D192: 职场心理 | E192: 文化修养 | F192: 复旦名师傅杰的《论语》课 | G192: 糅合千年中国传统文化，提炼数百种《论语》研究著作的精华 | H192: 傅杰 | I192: 音频 | J192: 43238 | K192: 221 | L192: 57.087222 | M192: 已完结 | N192: 199
A193: =ROW()-2 -> 191 | B193: VIP精品课 | C193: 通用课 | D193: 职场心理 | E193: 文化修养 | F193: 董平讲王阳明心学 | G193: 传习经典，知行合一，学阳明先生正心诚意而安心 | H193: 董平 | I193: 音频 | J193: 43238 | K193: 114 | L193: 48.737778 | M193: 已完结 | N193: 199
A194: =ROW()-2 -> 192 | B194: VIP精品课 | C194: 通用课 | D194: 职场心理 | E194: 职场智慧 | F194: 张宏杰：曾国藩24锦囊 | G194: 为官、治家、识人、修身之道,带你走进曾国藩这中国近代史上第一人 | H194: 张宏杰 | I194: 音频 | J194: 43238 | K194: 46 | L194: 9.9522222 | M194: 已完结 | N194: 49.9
A195: =ROW()-2 -> 193 | B195: VIP精品课 | C195: 通用课 | D195: 职场心理 | E195: 文化修养 | F195: 纵横奇谋：细读《鬼谷子》 | G195: 听“谋圣”“天书”，成“常胜将军”，以弱胜强、以少胜多的逆袭成功大法 | H195: 韩建君 | I195: 音频 | J195: 43238 | K195: 66 | L195: 24.18 | M195: 已完结 | N195: 128
A196: =ROW()-2 -> 194 | B196: VIP精品课 | C196: 通用课 | D196: 职场心理 | E196: 文化修养 | F196: 张庆祥讲《传习录》 | G196: 致良知，知行合一，跟随王阳明，享受一场精彩绝伦的心灵盛宴 | H196: 张庆祥 | I196: 音频 | J196: 43238 | K196: 234 | L196: 65.746667 | M196: 已完结 | N196: 168
A197: =ROW()-2 -> 195 | B197: VIP精品课 | C197: 通用课 | D197: 职场心理 | E197: 文化修养 | F197: 于丹品经典：过你想要的人生 | G197: 学古圣先贤，读国学智慧，品人生真谛，帮助你找到生命的规律 | H197: 于丹 | I197: 音频 | J197: 43262 | K197: 167 | L197: 69.189722 | M197: 已完结 | N197: 199
A198: =ROW()-2 -> 196 | B198: VIP精品课 | C198: 通用课 | D198: 职场心理 | E198: 文化修养 | F198: 易中天说禅 | G198: 每天10分钟，在生活中随手修行 | H198: 易中天 | I198: 音频 | J198: 43294 | K198: 21 | L198: 5.0188889 | M198: 已完结 | N198: 39
A199: =ROW()-2 -> 197 | B199: VIP精品课 | C199: 通用课 | D199: 职场心理 | E199: 文化修养 | F199: 梁冬私房笔记：庄子的心灵自由之路 | G199: 睡前用庄子给灵魂充满电 | H199: 梁冬 | I199: 音频 | J199: 43315 | K199: 289 | L199: 91.890556 | M199: 已完结 | N199: 199
A200: =ROW()-2 -> 198 | B200: VIP精品课 | C200: 通用课 | D200: 职场心理 | E200: 文化修养 | F200: 钱文忠讲佛 | G200: 还原真实的佛陀和佛学的精华 | H200: 钱文忠 | I200: 音频 | J200: 43322 | K200: 61 | L200: 18.758889 | M200: 已完结 | N200: 99
A201: =ROW()-2 -> 199 | B201: VIP精品课 | C201: 通用课 | D201: 职场心理 | E201: 职场减压 | F201: 治愈失眠：20分钟催眠还你睡眠 | G201: 6大失眠症状的解决方案 | H201: 马春树 | I201: 音频 | J201: 43347 | K201: 18 | L201: 5.1775 | M201: 已完结 | N201: 79
... A258: =ROW()-2 -> 256 | B258: VIP精品课 | C258: 通用课 | D258: 职场心理 | E258: 职场智慧 | F258: 精英都爱的十大思维 | G258: 学会职场思维助力职场突围 | H258: 赵雨润 | I258: 音频 | J258: 44538 | K258: 21 | L258: 3.2141667 | M258: 已完结 | N258: 99
A259: =ROW()-2 -> 257 | B259: VIP精品课 | C259: 通用课 | D259: 职场心理 | E259: 职场智慧 | F259: 职场进阶课：冲出迷雾，发生改变 | G259: 职场进阶课：冲出迷雾，发生改变 | H259: 苏娟 | I259: 音频 | J259: 44538 | K259: 21 | L259: 2.7238889 | M259: 已完结
A260: =ROW()-2 -> 258 | B260: VIP精品课 | C260: 通用课 | D260: 职场心理 | E260: 职场减压 | F260: 国家队队医：5分钟了解运动损伤 | G260: 5分钟了解运动损伤 | H260: 冉令军 | I260: 音频 | J260: 44554 | K260: 27 | L260: 2.9252778 | M260: 已完结
A261: =ROW()-2 -> 259 | B261: VIP精品课 | C261: 通用课 | D261: 职场心理 | E261: 文化修养 | F261: 奥运会的故事 | G261: 奥运会的故事 | H261: 有声主播薇薇 | I261: 音频 | J261: 44555 | K261: 89 | L261: 7.9705556 | M261: 已完结
A262: =ROW()-2 -> 260 | B262: VIP精品课 | C262: 通用课 | D262: 职场心理 | E262: 职场减压 | F262: 可复制的快乐工作法 | G262: 可复制的快乐工作法 | H262: 詹昊宸 | I262: 音频 | J262: 44557 | K262: 12 | L262: 2.6641667 | M262: 更新中 | N262: 89
A263: =ROW()-2 -> 261 | B263: VIP精品课 | C263: 通用课 | D263: 职场心理 | E263: 幸福生活 | F263: 子章老师：亲子运动健康课 | G263: 子章老师：亲子运动健康课 | H263: 子章老师 | I263: 音频 | J263: 44559 | K263: 13 | L263: 1.3186111 | M263: 未完结 | N263: 199
A264: =ROW()-2 -> 262 | B264: VIP精品课 | C264: 通用课 | D264: 职场心理 | E264: 情绪管理 | F264: 透过结构看情绪管理 | G264: 透过结构看情绪管理 | H264: 王明伟 | I264: 视频 | J264: 44562 | K264: 14 | L264: 3.855 | M264: 已完结 | N264: 99
A265: =ROW()-2 -> 263 | B265: VIP精品课 | C265: 通用课 | D265: 职场心理 | E265: 文化修养 | F265: 哲学100问·第1季 | G265: 西方哲学启蒙课 | H265: 书杰 | I265: 音频 | J265: 44565 | K265: 134 | L265: 22.170556 | M265: 已完结 | N265: 98
...

Sheet 岗位课
A1: 岗位课频道
A2: 序号 | B2: 内容大类 | C2: 频道页 | D2: 一级标签 | E2: 二级标签 | F2: 课程名称 | G2: 副标题 | H2: 主讲人 | I2: 课程形式 | J2: 轻学堂上架日期 | K2: 课程总课时/集 | L2: 已上架课时总时间/h | M2: 更新状态 | N2: 单卖价格/元
A3: =ROW()-2 -> 1 | B3: VIP精品课 | C3: 岗位课 | D3: 财务 | E3: 管理会计 | F3: 优秀财务必须掌握的5大核心能力 | G3: 突破财务职业发展的困境，拒绝成为考证达人 | H3: 小安 | I3: 视频 | J3: 43570 | K3: 71 | L3: 26.369444 | M3: 已完结 | N3: 188
A4: =ROW()-2 -> 2 | B4: VIP精品课 | C4: 岗位课 | D4: 财务 | E4: 财资管理 | F4: 肖星的财务课 | G4: 从财务思维看职场，提升工作中的硬实力 | H4: 肖星 | I4: 音频 | J4: 43912 | K4: 72 | L4: 20.74 | M4: 已完结 | N4: 199
A5: =ROW()-2 -> 3 | B5: VIP精品课 | C5: 岗位课 | D5: 财务 | E5: 管理会计 | F5: 投行大师兄的财报速读课 | G5: 深入浅出讲清楚财务分析方法，挖掘有价值的公司 | H5: 吴晓波频道 | I5: 音频 | J5: 43916 | K5: 33 | L5: 4.6575 | M5: 已完结 | N5: 199
A6: =ROW()-2 -> 4 | B6: VIP精品课 | C6: 岗位课 | D6: 财务 | E6: 财资管理 | F6: 韩坤珏: 财务经理实战指南30讲 | G6: 韩坤珏: 财务经理实战指南30讲 | H6: 韩坤珏 | I6: 音频 | J6: 44517 | K6: 31 | L6: 7.9686111 | M6: 已完结 | N6: 99
A7: =ROW()-2 -> 5 | B7: VIP精品课 | C7: 岗位课 | D7: 财务 | E7: 管理会计/财资管理 | F7: 张新民的财报分析实战课38讲 | G7: 张新民教授的财务分析实战课38讲 | H7: 张新民 | I7: 视频 | J7: 44526 | K7: 38 | L7: 13.922222 | M7: 已完结 | N7: 169
A8: =ROW()-2 -> 6 | B8: VIP精品课 | C8: 岗位课 | D8: 财务 | E8: 管理会计 | F8: CFO手把手教你读懂财报 | G8: CFO手把手教你读懂财报 | H8: 郑永强 | I8: 音频 | J8: 44531 | K8: 11 | L8: 2.01 | M8: 已完结 | N8: 49
A9: =ROW()-2 -> 7 | B9: VIP精品课 | C9: 岗位课 | D9: 财务 | E9: 管理会计/税务管理 | F9: 财务管理课：非财务人员的财务管理 | G9: 财务管理课：非财务人员的财务管理 | H9: 郝卯花 | I9: 视频 | J9: 44534 | K9: 36 | L9: 7.7336111 | M9: 已完结 | N9: 199
A10: =ROW()-2 -> 8 | B10: VIP精品课 | C10: 岗位课 | D10: 财务 | E10: 财资管理/管理会计 | F10: 财务管理：现金流分析与营运资本管理 | G10: 财务管理：现金流分析与营运资本管理 | H10: 王艳 | I10: 视频 | J10: 44534 | K10: 20 | L10: 3.0633333 | M10: 已完结 | N10: 199
A11: =ROW()-2 -> 9 | B11: VIP精品课 | C11: 岗位课 | D11: 财务 | E11: 财务会计/财资管理 | F11: 商业语言|快速掌握财务会计精髓 | G11: 帮助企业家从财务报表中看清企业管理中的相关要素 | H11: 江军民 | I11: 视频 | J11: 44546 | K11: 44 | L11: 8.0652778 | M11: 已完结 | N11: 199
A12: =ROW()-2 -> 10 | B12: VIP精品课 | C12: 岗位课 | D12: 财务 | E12: 税务管理 | F12: 三张报表学稽查 | G12: 三张报表学稽查 | H12: 徐箐 | I12: 音频 | J12: 44548 | K12: 15 | L12: 2.2969444 | M12: 已完结 | N12: 138
A13: =ROW()-2 -> 11 | B13: VIP精品课 | C13: 岗位课 | D13: 财务 | E13: 税务管理 | F13: 快速掌握增值税实务操作技巧 | G13: 快速掌握增值税实务操作技巧 | H13: 徐箐 | I13: 音频 | J13: 44548 | K13: 50 | L13: 9.4541667 | M13: 已完结 | N13: 129
A14: =ROW()-2 -> 12 | B14: VIP精品课 | C14: 岗位课 | D14: 财务 | E14: 税务管理 | F14: 涉税基础系列课 | G14: 涉税基础系列课 | H14: 徐箐 | I14: 音频 | J14: 44548 | K14: 19 | L14: 3.4538889 | M14: 已完结 | N14: 129
... A22: =ROW()-2 -> 20 | B22: VIP精品课 | C22: 岗位课 | D22: 产品 | E22: 产品规划/设计 | F22: 从0-1-N爆品持续引爆的密码 | G22: 爆品瘾力 | H22: 江新安 | I22: 视频 | J22: 44437 | K22: 16 | L22: 3.8652778 | M22: 已完结 | N22: 198
A23: =ROW()-2 -> 21 | B23: VIP精品课 | C23: 岗位课 | D23: 产品 | E23: 产品思维 | F23: 贾伟：产品三观与用户思维10讲 | G23: 产品三观10讲 | H23: 贾伟 | I23: 音频 | J23: 44532 | K23: 4 | L23: 0.60333333 | M23: 更新中
A24: =ROW()-2 -> 22 | B24: VIP精品课 | C24: 岗位课 | D24: 产品 | E24: 产品思维 | F24: 高雄勇：我在小米做爆品 | G24: 高雄勇：我在小米做爆品 | H24: 高雄勇 | I24: 视频 | J24: 44535 | K24: 50 | L24: 5.5466667 | M24: 已完结 | N24: 199
A25: =ROW()-2 -> 23 | B25: VIP精品课 | C25: 岗位课 | D25: 产品 | E25: 产品思维 | F25: 感性商业 | G25: 世界500强企业通用的用户体验增长方法论 | H25: 罗浩 | I25: 视频 | J25: 44535 | K25: 10 | L25: 1.5977778 | M25: 已完结 | N25: 59
A26: =ROW()-2 -> 24 | B26: VIP精品课 | C26: 岗位课 | D26: 产品 | E26: 产品思维 | F26: 10堂课打造系统产品思维 | G26: 10堂课打造系统产品思维 | H26: 水滴产品学院 | I26: 视频 | J26: 44537 | K26: 38 | L26: 21.093889 | M26: 已完结
A27: =ROW()-2 -> 25 | B27: VIP精品课 | C27: 岗位课 | D27: 产品 | E27: 产品规划/设计 | F27: 产品高手必修课 | G27: 系统化讲述产品知识，帮你从产品小白迈向产品高手！ | H27: 水滴产品学院 | I27: 视频 | J27: 44537 | K27: 15 | L27: 2.4097222 | M27: 已完结 | N27: 99
A28: =ROW()-2 -> 26 | B28: VIP精品课 | C28: 岗位课 | D28: 产品 | E28: 产品规划/设计 | F28: 腾讯产品方法18讲 | G28: 千款产品背后的关键思考 | H28: 腾讯讲师 | I28: 音频 | J28: 44538 | K28: 21 | L28: 4.6052778 | M28: 已完结 | N28: 49
A29: =ROW()-2 -> 27 | B29: VIP精品课 | C29: 岗位课 | D29: 产品 | E29: 产品思维 | F29: 华为的GTM操盘法：捕捉市场的必备法则|价值 | G29: 向华为学成功法宝：产品打造和GTM操盘 | H29: 王叶鹏 | I29: 视频 | J29: 44546 | K29: 12 | L29: 5.4483333 | M29: 已完结 | N29: 89
A30: =ROW()-2 -> 28 | B30: VIP精品课 | C30: 岗位课 | D30: 产品 | E30: 产品思维 | F30: 卓越产品经理如何思考 | G30: 掌握产品思维，掌握解决问题的综合性思维 | H30: 渊池先生 | I30: 音频 | J30: 44548 | K30: 53 | L30: 6.8336111 | M30: 已完结
A31: =ROW()-2 -> 29 | B31: VIP精品课 | C31: 岗位课 | D31: 金融理财 | E31: 股权投资 | F31: 王英军律师：创业时代 决胜股权 | G31: 王英军律师结合多次股权咨询的实战经验，为创业者制作的创业股权课程 | H31: 王英军 | I31: 音频 | J31: 43227 | K31: 57 | L31: 21.928056 | M31: 已完结 | N31: 198
A32: =ROW()-2 -> 30 | B32: VIP精品课 | C32: 岗位课 | D32: 金融理财 | E32: 金融知识与技能 | F32: 向松祚讲货币与金融 | G32: 货币是财富的载体，金融是时间的机器，看透货币本质，理解金融逻辑 | H32: 向松祚 | I32: 音频 | J32: 43293 | K32: 114 | L32: 19.706667 | M32: 已完结 | N32: 199
A33: =ROW()-2 -> 31 | B33: VIP精品课 | C33: 岗位课 | D33: 金融理财 | E33: 股权投资 | F33: 资本时代的股权战略 | G33: 从战略高度，带你掌握资本时代股权设计的道与术 | H33: 徐怀玉 | I33: 音频 | J33: 43439 | K33: 34 | L33: 5.7619444 | M33: 已完结 | N33: 99
A34: =ROW()-2 -> 32 | B34: VIP精品课 | C34: 岗位课 | D34: 金融理财 | E34: 金融知识与技能 | F34: 首席经济学家管清友的金融课 | G34: 9大金融工具看时局和行业大势，破解投资难题 | H34: 管清友 | I34: 音频 | J34: 43706 | K34: 43 | L34: 8.8069444 | M34: 已完结 | N34: 698
A35: =ROW()-2 -> 33 | B35: VIP精品课 | C35: 岗位课 | D35: 金融理财 | E35: 股权投资 | F35: 雷军、徐小平御用律师私房股权课 | G35: 理论+案例，带你了解股权的基本架构 | H35: 张明若 | I35: 音频 | J35: 43712 | K35: 20 | L35: 1.9491667 | M35: 已完结 | N35: 99
A36: =ROW()-2 -> 34 | B36: VIP精品课 | C36: 岗位课 | D36: 金融理财 | E36: 证券 | F36: 清华王茵田的期货期权等衍生品课 | G36: 来自清华MBA的主题投资课 | H36: 王茵田 | I36: 音频 | J36: 44019 | K36: 36 | L36: 6.0461111 | M36: 已完结 | N36: 99
A37: =ROW()-2 -> 35 | B37: VIP精品课 | C37: 岗位课 | D37: 金融理财 | E37: 财富管理与资产配置 | F37: 苏培科：精英投资指南25讲 | G37: CCTV财经评论员，带你寻找A股投资新机遇 | H37: 苏培科 | I37: 音频 | J37: 44056 | K37: 15 | L37: 2.7252778 | M37: 更新中 | N37: 99
A38: =ROW()-2 -> 36 | B38: VIP精品课 | C38: 岗位课 | D38: 金融理财 | E38: 股权投资 | F38: 张晓丽：中小企业如何融资及上市 | G38: 风投专家教你为企业上市铺路 | H38: 张晓丽 | I38: 视频 | J38: 44061 | K38: 43 | L38: 7.6794444 | M38: 已完结 | N38: 199
A39: =ROW()-2 -> 37 | B39: VIP精品课 | C39: 岗位课 | D39: 金融理财 | E39: 审计风控 | F39: 企业法律风险必知 | G39: 企业经营千万条，知法懂法第一条 | H39: 京城律师天团 | I39: 音频 | J39: 44067 | K39: 62 | L39: 17.071667 | M39: 已完结 | N39: 198
A40: =ROW()-2 -> 38 | B40: VIP精品课 | C40: 岗位课 | D40: 金融理财 | E40: 股权投资 | F40: 陶矜：股权思维30讲 | G40: 股权名师手把手教你用活用股权 | H40: 陶矜 | I40: 音频 | J40: 44084 | K40: 33 | L40: 6.5802778 | M40: 已完结 | N40: 199
A41: =ROW()-2 -> 39 | B41: VIP精品课 | C41: 岗位课 | D41: 金融理财 | E41: 股权投资 | F41: 王英军律师：股权投资实战课 | G41: 王英军律师结合多次股权咨询的实战经验，为创业者制作的创业股权课程 | H41: 王英军 | I41: 音频 | J41: 44098 | K41: 33 | L41: 13.529444 | M41: 已完结 | N41: 198
A42: =ROW()-2 -> 40 | B42: VIP精品课 | C42: 岗位课 | D42: 金融理财 | E42: 财富管理与资产配置 | F42: 孙利平：论社会财富与企业利润 | G42: 教你从根源上理解商业的底层运作规律 | H42: 孙利平 | I42: 视频 | J42: 44141 | K42: 5 | L42: 3.6383333 | M42: 已完结 | N42: 99
... A52: =ROW()-2 -> 50 | B52: VIP精品课 | C52: 岗位课 | D52: 金融理财 | E52: 股权投资 | F52: 李芳：股权｜合伙｜股权设计｜分红 | G52: 付钱给对的人，而不是付钱给人 | H52: 李芳 | I52: 音频 | J52: 44539 | K52: 157 | L52: 14.363889 | M52: 已完结 | N52: 99
A53: =ROW()-2 -> 51 | B53: VIP精品课 | C53: 岗位课 | D53: 金融理财 | E53: 证券 | F53: 资产证券化与结构化金融 | G53: REITs实战 | H53: 宋光辉 | I53: 音频 | J53: 44539 | K53: 7 | L53: 1.4 | M53: 已完结
A54: =ROW()-2 -> 52 | B54: VIP精品课 | C54: 岗位课 | D54: 金融理财 | E54: 金融知识与技能 | F54: 倪云华：八步写出商业融资计划书 | G54: 倪云华：八步写出商业融资计划书 | H54: 倪云华 | I54: 视频 | J54: 44545 | K54: 11 | L54: 2.6447222 | M54: 已完结 | N54: 199
A55: =ROW()-2 -> 53 | B55: VIP精品课 | C55: 岗位课 | D55: 金融理财 | E55: 金融知识与技能 | F55: 律格资本：马博士的资本思维64讲 | G55: 律格资本：马博士的资本思维64讲 | H55: 马正 | I55: 视频 | J55: 44545 | K55: 19 | L55: 2.62 | M55: 已完结 | N55: 199
A56: =ROW()-2 -> 54 | B56: VIP精品课 | C56: 岗位课 | D56: 金融理财 | E56: 审计风控 | F56: 张宁：英文合同起草与审核 | G56: 快速全面的掌握英文合同起草和审核的专业知识 | H56: 张宁律师 | I56: 视频 | J56: 44548 | K56: 19 | L56: 12.612222 | M56: 已完结 | N56: 299
A57: =ROW()-2 -> 55 | B57: VIP精品课 | C57: 岗位课 | D57: 金融理财 | E57: 证券 | F57: 刘俊海教授：详解2020最新版《证券法》 | G57: 详解2020最新版《证券法》 | H57: 刘俊海教授 | I57: 视频 | J57: 44548 | K57: 15 | L57: 6.4983333 | M57: 已完结 | N57: 298
A58: =ROW()-2 -> 56 | B58: VIP精品课 | C58: 岗位课 | D58: 金融理财 | E58: 金融知识与技能 | F58: 金融科技驱动数字化转型|行业趋势、投资风向 | G58: 金融科技创新驱动的银行数字化转型向 | H58: 肖然 | I58: 视频 | J58: 44554 | K58: 8 | L58: 2.0025 | M58: 已完结 | N58: 99
A59: =ROW()-2 -> 57 | B59: VIP精品课 | C59: 岗位课 | D59: 金融理财 | E59: 财富管理与资产配置 | F59: 港股打新如何提高中签率 | G59: 港股打新如何提高中签率 | H59: 刘怡伶 | I59: 视频 | J59: 44563 | K59: 11 | L59: 1.1744444 | M59: 已完结 | N59: 99
A60: =ROW()-2 -> 58 | B60: VIP精品课 | C60: 岗位课 | D60: 金融理财 | E60: 财富管理与资产配置 | F60: 规避人性的理财攻略 | G60: 规避人性的理财攻略 | H60: 戴翀 | I60: 视频 | J60: 44563 | K60: 16 | L60: 1.6169444 | M60: 已完结 | N60: 69
A61: =ROW()-2 -> 59 | B61: VIP精品课 | C61: 岗位课 | D61: 金融理财 | E61: 财富管理与资产配置 | F61: 投资理财必修的金融常识课 | G61: 投资理财必修的金融常识课 | H61: 黎京林 | I61: 视频 | J61: 44563 | K61: 12 | L61: 2.3877778 | M61: 已完结 | N61: 39
A62: =ROW()-2 -> 60 | B62: VIP精品课 | C62: 岗位课 | D62: 金融理财 | E62: 证券 | F62: 高频交易15讲：探寻纳秒时代的金融市场 | G62: 新时代金融从业者的必修课 | H62: 李路 | I62: 音频 | J62: 44563 | K62: 17 | L62: 2.8563889 | M62: 已完结 | N62: 69
A63: =ROW()-2 -> 61 | B63: VIP精品课 | C63: 岗位课 | D63: 金融理财 | E63: 财富管理与资产配置 | F63: 如何抓住潜伏的暴涨股 | G63: 识别被大家忽略的牛股 | H63: 闵遥 | I63: 视频 | J63: 44563 | K63: 16 | L63: 1.9572222 | M63: 已完结 | N63: 99
A64: =ROW()-2 -> 62 | B64: VIP精品课 | C64: 岗位课 | D64: 金融理财 | E64: 财富管理与资产配置 | F64: 公募基金的投资攻略课 | G64: 公募基金的投资攻略课 | H64: 黎京林 | I64: 视频 | J64: 44566 | K64: 17 | L64: 2.0255556 | M64: 已完结 | N64: 39
A65: =ROW()-2 -> 63 | B65: VIP精品课 | C65: 岗位课 | D65: 金融理财 | E65: 财富管理与资产配置 | F65: 新手投资者的数学投资思维课 | G65: 小白秒懂的数学投资思维 | H65: 顾艳 | I65: 视频 | J65: 44566 | K65: 22 | L65: 2.8519444 | M65: 已完结 | N65: 69
... A113: =ROW()-2 -> 111 | B113: VIP精品课 | C113: 岗位课 | D113: 人力资源 | E113: 绩效管理 | F113: 如何搭建战略型绩效体系 | G113: 绩效管理的三大挑战及破解之道 | H113: 韩铁林 | I113: 音频 | J113: 44540 | K113: 39 | L113: 7.2516667 | M113: 已完结 | N113: 99
A114: =ROW()-2 -> 112 | B114: VIP精品课 | C114: 岗位课 | D114: 人力资源 | E114: 绩效管理/薪酬福利管理 | F114: 绩效考核与薪酬挂钩的六个方法 | G114: 绩效考核与薪酬挂钩的六个方法 | H114: 倪铭 | I114: 视频 | J114: 44540 | K114: 13 | L114: 2.4 | M114: 已完结
A115: =ROW()-2 -> 113 | B115: VIP精品课 | C115: 岗位课 | D115: 人力资源 | E115: 薪酬福利管理 | F115: 薪酬体系建设：如何把钱分的更有价值 | G115: 这是一门解决薪酬体系构建的实操课程 | H115: 于彬彬 | I115: 视频 | J115: 44540 | K115: 40 | L115: 4.8927778 | M115: 已完结 | N115: 199
A116: =ROW()-2 -> 114 | B116: VIP精品课 | C116: 岗位课 | D116: 人力资源 | E116: 劳动关系管理 | F116: 三孩政策下HR用工管理的变与不变 | G116: 新手投资者的数学投资思维课 | H116: 陈豪 | I116: 音频 | J116: 44543 | K116: 16 | L116: 3.4694444 | M116: 更新中 | N116: 88
A117: =ROW()-2 -> 115 | B117: VIP精品课 | C117: 岗位课 | D117: 人力资源 | E117: 劳动关系管理 | F117: 王勇：企业劳资合规的7大必备工具 | G117: 企业劳资合规的7大必备工具 | H117: 王勇 | I117: 视频 | J117: 44548 | K117: 7 | L117: 3.5319444 | M117: 已完结 | N117: 99
A118: =ROW()-2 -> 116 | B118: VIP精品课 | C118: 岗位课 | D118: 人力资源 | E118: 培训与开发 | F118: 王钊：专业人士如何做一场在线直播课 | G118: 直播大时代，线下课程的转型之路 | H118: 王钊 | I118: 视频 | J118: 44550 | K118: 25 | L118: 4.5383333 | M118: 已完结 | N118: 1499
A119: =ROW()-2 -> 117 | B119: VIP精品课 | C119: 岗位课 | D119: 人力资源 | E119: 培训与开发 | F119: FAST高效课程开发 | G119: FAST高效课程开发 | H119: 邱伟 | I119: 视频 | J119: 44563 | K119: 17 | L119: 4.1327778 | M119: 已完结 | N119: 189
A120: =ROW()-2 -> 118 | B120: VIP精品课 | C120: 岗位课 | D120: 人力资源 | E120: 培训与开发 | F120: BEST高能经验萃取 | G120: BEST高能经验萃取 | H120: 邱伟 | I120: 视频 | J120: 44563 | K120: 13 | L120: 3.1302778 | M120: 已完结 | N120: 189
A121: =ROW()-2 -> 119 | B121: VIP精品课 | C121: 岗位课 | D121: 人力资源 | E121: 培训与开发 | F121: 孙波：最佳实践萃取 | G121: 孙波：最佳实践萃取 | H121: 孙波 | I121: 音频 | J121: 44563 | K121: 6 | L121: 1.2141667 | M121: 已完结 | N121: 99
A122: =ROW()-2 -> 120 | B122: VIP精品课 | C122: 岗位课 | D122: 人力资源 | E122: 培训与开发 | F122: 从0-1带你完成一场高质量内训课 | G122: 从0-1带你完成一场高质量内训课 | H122: 刘佳 | I122: 音频 | J122: 44578 | K122: 6 | L122: 1.1452778 | M122: 已完结 | N122: 199
A123: =ROW()-2 -> 121 | B123: VIP精品课 | C123: 岗位课 | D123: 人力资源 | E123: 招聘与配置 | F123: 专业面试官八大秘技 | G123: 专业面试官八大秘技 | H123: 黄琼 | I123: 音频 | J123: 44585 | K123: 5 | L123: 0.72805556 | M123: 更新中 | N123: 69
A124: =ROW()-2 -> 122 | B124: VIP精品课 | C124: 岗位课 | D124: 人力资源 | E124: 薪酬福利管理 | F124: HRVP带你30天通关：薪酬福利 | G124: HRVP带你30天通关：薪酬福利 | H124: 马智强 | I124: 音频 | K124: 23 | L124: 6.2 | M124: 已完结 | N124: 119
A125: =ROW()-2 -> 123 | B125: VIP精品课 | C125: 岗位课 | D125: 人力资源 | E125: 招聘与配置 | F125: HRVP带你30天通关：高效招聘 | G125: HRVP带你30天通关：高效招聘 | H125: 马智强 | I125: 音频 | K125: 22 | L125: 4.3 | M125: 已完结 | N125: 119
A126: =ROW()-2 -> 124 | B126: VIP精品课 | C126: 岗位课 | D126: 生产制造 | E126: 供应链 | F126: 华为供应链管理课 | G126: 分享华为应对各种供应链管理问题的解决办法 | H126: 辛童 | I126: 音频 | J126: 43717 | K126: 36 | L126: 5.945 | M126: 已完结 | N126: 99
A127: =ROW()-2 -> 125 | B127: VIP精品课 | C127: 岗位课 | D127: 生产制造 | E127: 供应链 | F127: 精益供应链之路 | G127: 建立精益供应链，降本增效 | H127: 罗意 | I127: 视频 | J127: 44249 | K127: 13 | L127: 2.4833333 | M127: 已完结 | N127: 199
A128: =ROW()-2 -> 126 | B128: VIP精品课 | C128: 岗位课 | D128: 生产制造 | E128: 生产管理 | F128: 精益培训与仿真 | G128: 四种类型问题解决法 | H128: 周宏博 | I128: 视频 | J128: 44251 | K128: 14 | L128: 2.6441667 | M128: 已完结 | N128: 199
A129: =ROW()-2 -> 127 | B129: VIP精品课 | C129: 岗位课 | D129: 生产制造 | E129: 生产管理 | F129: 工厂管理用语大全 | G129: 从零开始，快速习得工厂管理用语 | H129: 蚁创科技 | I129: 音频 | J129: 44286 | K129: 28 | L129: 1.2227778 | M129: 已完结 | N129: 199
A130: =ROW()-2 -> 128 | B130: VIP精品课 | C130: 岗位课 | D130: 生产制造 | E130: 生产管理 | F130: 丰田的生产管理秘诀 | G130: 丰田全球生产中心部长带您学精益 | H130: 水野忠男 | I130: 音频 | J130: 44292 | K130: 15 | L130: 0.75305556 | M130: 更新中 | N130: 199
A131: =ROW()-2 -> 129 | B131: VIP精品课 | C131: 岗位课 | D131: 生产制造 | E131: 供应链 | F131: 需求驱动型供应链管理 | G131: 需求驱动型供应链管理 | H131: 谢智 | I131: 视频 | J131: 44364 | K131: 15 | L131: 5.0261111 | M131: 已完结 | N131: 99
A132: =ROW()-2 -> 130 | B132: VIP精品课 | C132: 岗位课 | D132: 生产制造 | E132: 供应链 | F132: 高效供应链管理实战 | G132: 后疫情时代，韧性视角解读供应链 | H132: 高上 | I132: 音频 | J132: 44385 | K132: 21 | L132: 3.6994444 | M132: 已完结 | N132: 99
A133: =ROW()-2 -> 131 | B133: VIP精品课 | C133: 岗位课 | D133: 生产制造 | E133: 班组长能力提升 | F133: 杨华：向华为学习班组管理 | G133: 金牌班组长必修课 | H133: 杨华 | I133: 视频 | J133: 44463 | K133: 23 | L133: 3.2986111 | M133: 已完结 | N133: 199
A134: =ROW()-2 -> 132 | B134: VIP精品课 | C134: 岗位课 | D134: 生产制造 | E134: 生产管理 | F134: 杨华：向华为学习质量管理 | G134: 精益管理 | H134: 杨华 | I134: 视频 | J134: 44501 | K134: 22 | L134: 3.6586111 | M134: 更新中 | N134: 199
A135: =ROW()-2 -> 133 | B135: VIP精品课 | C135: 岗位课 | D135: 生产制造 | E135: 生产管理 | F135: 刘晓毅：国之重器成本工程体系 | G135: 刘晓毅：国之重器成本工程体系 | H135: 刘晓毅 | I135: 视频 | J135: 44534 | K135: 19 | L135: 3.0972222 | M135: 已完结 | N135: 89
A136: =ROW()-2 -> 134 | B136: VIP精品课 | C136: 岗位课 | D136: 生产制造 | E136: 生产管理 | F136: 杨华：TPS高效精益生产实施 | G136: 精益生产管理 | H136: 杨华 | I136: 视频 | J136: 44578 | K136: 14 | L136: 3.7813889 | M136: 已完结 | N136: 199
A137: =ROW()-2 -> 135 | B137: VIP精品课 | C137: 岗位课 | D137: 生产制造 | E137: 生产管理 | F137: 国际TRIZ学会认证TRIZ课程姜台林 | G137: 国际TRIZ学会认证TRIZ课程姜台林 | H137: 姜台林 | I137: 视频 | J137: 44620 | K137: 19 | L137: 5.81 | M137: 已完结 | N137: 498
... A207: =ROW()-2 -> 205 | B207: VIP精品课 | C207: 岗位课 | D207: 运营 | E207: 社群运营 | F207: 做社群增长：传统企业如何转型 | G207: 做社群增长：传统企业如何转型 | H207: 曾楠 | I207: 视频 | J207: 44599 | K207: 22 | L207: 3.47 | M207: 未完结 | N207: 129
A208: =ROW()-2 -> 206 | B208: 畅听课 | C208: 岗位课 | D208: 财务 | E208: 管理会计 | F208: 半小时搞懂财务报表分析 | G208: 报表分析，会计中的战斗机 | H208: 徐晶 | I208: 音频 | J208: 43391 | K208: 5 | L208: 0.43361111 | M208: 已完结
A209: =ROW()-2 -> 207 | B209: 畅听课 | C209: 岗位课 | D209: 财务 | E209: 财务会计 | F209: 财务防身术 | G209: 你不必精通财务，但应该懂得财务 | H209: 徐晶 | I209: 音频 | J209: 43391 | K209: 30 | L209: 6.1527778 | M209: 已完结
A210: =ROW()-2 -> 208 | B210: 畅听课 | C210: 岗位课 | D210: 财务 | E210: 管理会计 | F210: 管理会计那些事儿 | G210: CGMA会员分享财务实操中的干货 | H210: 财实学苑 | I210: 音频 | J210: 43556 | K210: 19 | L210: 3.2530556 | M210: 已完结
A211: =ROW()-2 -> 209 | B211: 畅听课 | C211: 岗位课 | D211: 财务 | E211: 税务管理 | F211: 超级税客：听蔚青说税 | G211: 科学算税，给自己多发一份年终奖 | H211: 汪蔚青 | I211: 音频 | J211: 43811 | K211: 281 | L211: 89.093333 | M211: 更新中
A212: =ROW()-2 -> 210 | B212: 畅听课 | C212: 岗位课 | D212: 产品 | E212: 产品规划/设计 | F212: 产品高手的50堂商业实战课 | G212: 实战高手分享现象级产品背后的深度思考 | H212: 水滴产品学院 | I212: 音频 | J212: 43557 | K212: 53 | L212: 7.5380556 | M212: 已完结
A213: =ROW()-2 -> 211 | B213: 畅听课 | C213: 岗位课 | D213: 产品 | E213: 产品思维 | F213: 腾大直播间 | G213: 鹅厂产品大咖现身讲述产品之道 | H213: 腾讯大学 | I213: 视频 | J213: 43570 | K213: 14 | L213: 12.767778 | M213: 已完结
A214: =ROW()-2 -> 212 | B214: 畅听课 | C214: 岗位课 | D214: 产品 | E214: 产品思维 | F214: PMCAFF产品干货精选 | G214: 互联网产品干货交流分享 | H214: PMCAFF | I214: 音频 | J214: 43942 | K214: 829 | L214: 71.749444 | M214: 更新中
A215: =ROW()-2 -> 213 | B215: 畅听课 | C215: 岗位课 | D215: 人力资源 | E215: 人力资源规划 | F215: 许锋聊人才供应链 | G215: HR领域第一垂直FM | 打造人才供应链，实现企业可持续发展。 | H215: 许锋博士 | I215: 音频 | J215: 43391 | K215: 134 | L215: 28.861111 | M215: 更新中
A216: =ROW()-2 -> 214 | B216: 畅听课 | C216: 岗位课 | D216: 人力资源 | E216: 人力资源规划 | F216: 人力资源管理新视角 | G216: 巨变时代人力资源管理的新逻辑 | H216: 唐秋勇 | I216: 音频 | J216: 43557 | K216: 9 | L216: 4.6252778 | M216: 已完结
A217: =ROW()-2 -> 215 | B217: 畅听课 | C217: 岗位课 | D217: 人力资源 | E217: 人力资源规划 | F217: 国际人力资源技术大会演讲分享系列 | G217: 大咖云集，探讨人力资源领域的新技术、新趋势 | H217: 大卫.尤里奇 | I217: 音频 | J217: 43599 | K217: 29 | L217: 15.976944 | M217: 更新中
A218: =ROW()-2 -> 216 | B218: 畅听课 | C218: 岗位课 | D218: 人力资源 | E218: 培训与开发 | F218: 线上学习如何设计？ | G218: 疫情下，线上学习如何设计？ | H218: 荆瑞 | I218: 音频 | J218: 43873 | K218: 4 | L218: 1.1641667 | M218: 已完结
A219: =ROW()-2 -> 217 | B219: 畅听课 | C219: 岗位课 | D219: 人力资源 | E219: 劳动关系管理 | F219: 新冠防控期内的劳务关系合规解析 | G219: 疫情期内的劳务关系，怎么做才合规？ | H219: Kelvin Sun | I219: 视频 | J219: 43873 | K219: 1 | L219: 1.0661111 | M219: 已完结
... A233: =ROW()-2 -> 231 | B233: 畅听课 | C233: 岗位课 | D233: 运营 | E233: 平台运营 | F233: 腾讯大学《临厂发挥》 | G233: 有趣、有料的互联网实战分享 | H233: 腾讯大学 | I233: 视频 | J233: 43577 | K233: 6 | L233: 3.3452778 | M233: 更新中

Sheet 商学院
A1: 商学院频道
A2: 序号 | B2: 内容大类 | C2: 频道页 | D2: 一级标签 | E2: 二级标签 | F2: 课程名称 | G2: 副标题 | H2: 主讲人 | I2: 课程形式 | J2: 轻学堂上架日期 | K2: 课程总课时/集 | L2: 已上架课时总时间/h | M2: 更新状态 | N2: 单卖价格/元
A3: =ROW()-2 -> 1 | B3: VIP精品课 | C3: 商学院 | D3: 管理认知 | E3: 基层 | F3: 陈雪频：新晋经理人十讲 | G3: 为商业管理提供世界级价值参考标准，推进企业管理实践与研究的国际化 | H3: 陈雪频 | I3: 音频 | J3: 43227 | K3: 14 | L3: 2.6933333 | M3: 已完结 | N3: 19.9
A4: =ROW()-2 -> 2 | B4: VIP精品课 | C4: 商学院 | D4: 管理认知 | E4: 中层 | F4: 叶阿次：高效管理100招 | G4: 100天迈向管人高手 | H4: 叶阿次 | I4: 音频 | J4: 43399 | K4: 102 | L4: 11.323056 | M4: 已完结 | N4: 99
A5: =ROW()-2 -> 3 | B5: VIP精品课 | C5: 商学院 | D5: 管理认知 | E5: 中层 | F5: 徐中：5分钟清晨领导课 | G5: 每天清晨5分钟领导力学习，先人一步获得成功 | H5: 徐中 | I5: 音频 | J5: 43553 | K5: 64 | L5: 6.64 | M5: 已完结 | N5: 99
A6: =ROW()-2 -> 4 | B6: VIP精品课 | C6: 商学院 | D6: 管理认知 | E6: 中层 | F6: 不懂带人，你就自己干到死 | G6: 管理更高效，带人更轻松 | H6: 姜颖远 | I6: 音频 | J6: 43605 | K6: 12 | L6: 1.5527778 | M6: 已完结 | N6: 49
A7: =ROW()-2 -> 5 | B7: VIP精品课 | C7: 商学院 | D7: 管理认知 | E7: 高层 | F7: 中国式管理【曾仕强原声版】 | G7: 尽揽领袖指挥，引领事业人生至高境界 | H7: 曾仕强 | I7: 音频 | J7: 43862 | K7: 24 | L7: 5.2063889 | M7: 已完结 | N7: 49.8
A8: =ROW()-2 -> 6 | B8: VIP精品课 | C8: 商学院 | D8: 管理认知 | E8: 中层 | F8: 樊登：可复制的领导力 | G8: 快速复制领导能力，破解管理难题 | H8: 樊登 | I8: 视频 | J8: 44004 | K8: 37 | L8: 5.5425 | M8: 已完结 | N8: 199
A9: =ROW()-2 -> 7 | B9: VIP精品课 | C9: 商学院 | D9: 管理认知 | E9: 高层 | F9: 西点军校最受欢迎的领导力课（视频版） | G9: 商界、政界、军界影响力最大的领导力法则 | H9: 拉里·杜尼嵩 | I9: 视频 | J9: 44012 | K9: 27 | L9: 5.9786111 | M9: 已完结 | N9: 199
A10: =ROW()-2 -> 8 | B10: VIP精品课 | C10: 商学院 | D10: 管理认知 | E10: 高层 | F10: 曾仕强教授讲中庸管理之道 | G10: 当企业管理遇上民族文化 | H10: 曾仕强 | I10: 视频 | J10: 44025 | K10: 126 | L10: 23.755 | M10: 已完结 | N10: 99
A11: =ROW()-2 -> 9 | B11: VIP精品课 | C11: 商学院 | D11: 管理认知 | E11: 中层 | F11: 彼得·德鲁克的管理学精讲 | G11: 彼得·德鲁克的管理学精讲 | H11: 李洁 | I11: 音频 | J11: 44089 | K11: 67 | L11: 24.372222 | M11: 已完结 | N11: 99
A12: =ROW()-2 -> 10 | B12: VIP精品课 | C12: 商学院 | D12: 管理认知 | E12: 高层 | F12: 阿里巴巴管理三板斧 | G12: 练好内功，向管理要效益 | H12: 许林芳 | I12: 视频 | J12: 44139 | K12: 12 | L12: 3.0916667 | M12: 已完结 | N12: 99
A13: =ROW()-2 -> 11 | B13: VIP精品课 | C13: 商学院 | D13: 管理认知 | E13: 基层 | F13: 新任经理人的管理必修课 | G13: 8招带你快速从管理自我向管理他人转变 | H13: 陈致宇 | I13: 视频 | J13: 44154 | K13: 10 | L13: 3.8116667 | M13: 已完结 | N13: 599
A14: =ROW()-2 -> 12 | B14: VIP精品课 | C14: 商学院 | D14: 管理认知 | E14: 基层 | F14: 高琳：新手管理者的30堂必修课 | G14: 为新手管理者扫除误区、深度赋能 | H14: 高琳 | I14: 音频 | J14: 44189 | K14: 31 | L14: 5.8352778 | M14: 已完结 | N14: 199
... A61: =ROW()-2 -> 59 | B61: VIP精品课 | C61: 商学院 | D61: 业务经营 | E61: 中层 | F61: 吴婷:快公司生长密码 | G61: 快公司生长密码 | H61: 吴婷 | I61: 音频 | J61: 44449 | K61: 10 | L61: 2.1658333 | M61: 已完结 | N61: 168
A62: =ROW()-2 -> 60 | B62: VIP精品课 | C62: 商学院 | D62: 业务经营 | E62: 基层 | F62: 超级创新力：设计思考企业实战攻略 | G62: 超级创新力：设计思考企业实战攻略 | H62: 刘恭甫 | I62: 音频 | J62: 管理者和HR | K62: 中层管理者，高层管理者、HR | L62: 44634 | M62: 11 | N62: 2.3 | O62: 未完结
A63: =ROW()-2 -> 61 | B63: VIP精品课 | C63: 商学院 | D63: 业务经营/战略规划 | E63: 高层 | F63: 湖畔三板斧：首次公开创业心法 | G63: 阿里合伙人亲授，回顾创业的关键节点、经验以及案例分析，传递决策背后的心法A | H63: 马云等 | I63: 音频 | J63: 43238 | K63: 62 | L63: 23.033333 | M63: 已完结 | N63: 99
A64: =ROW()-2 -> 62 | B64: VIP精品课 | C64: 商学院 | D64: 业务经营/组织发展 | E64: 中层 | F64: 陈春花：数字化企业管理实战课 | G64: 协同数字化时代组织效率的本质 | H64: 陈春花 | I64: 音频 | J64: 44410 | K64: 14 | L64: 1.2255556 | M64: 已完结 | N64: 199
A65: =ROW()-2 -> 63 | B65: VIP精品课 | C65: 商学院 | D65: 战略规划 | E65: 中层 | F65: 倪云华：全球商业模式创新40讲 | G65: 为企业找到十倍盈利突破点的视频课 | H65: 倪云华 | I65: 视频 | J65: 43579 | K65: 41 | L65: 4.6822222 | M65: 已完结 | N65: 99
A66: =ROW()-2 -> 64 | B66: VIP精品课 | C66: 商学院 | D66: 战略规划 | E66: 基层 | F66: 清华朱武祥的商业模式课 | G66: 用小资源撬动大财富，带你打开财富之门 | H66: 朱武祥 | I66: 音频 | J66: 43909 | K66: 56 | L66: 7.9288889 | M66: 已完结 | N66: 199
A67: =ROW()-2 -> 65 | B67: VIP精品课 | C67: 商学院 | D67: 战略规划 | E67: 中层 | F67: 清华名师王勇：活学活用博弈论 | G67: 深度解读博弈论精华 | H67: 王勇 | I67: 音频 | J67: 43941 | K67: 60 | L67: 14.685 | M67: 已完结 | N67: 199
A68: =ROW()-2 -> 66 | B68: VIP精品课 | C68: 商学院 | D68: 战略规划 | E68: 高层 | F68: 航运物流业遇到的困局及破解之道 | G68: 解析航运物流业痛点，提出针对性解决方案 | H68: 黄伟明 | I68: 音频 | J68: 43969 | K68: 10 | L68: 1.7188889 | M68: 已完结 | N68: 46
A69: =ROW()-2 -> 67 | B69: VIP精品课 | C69: 商学院 | D69: 战略规划 | E69: 基层 | F69: 蒋伟良：人人用得上的战略思维课 | G69: 前华为高管的战略课 | H69: 蒋伟良 | I69: 视频 | J69: 44078 | K69: 11 | L69: 2.5383333 | M69: 已完结 | N69: 129
A70: =ROW()-2 -> 68 | B70: VIP精品课 | C70: 商学院 | D70: 战略规划 | E70: 中层 | F70: 领导力@数字时代 | G70: 数字化转型是威胁也是机遇 | H70: 林奕威 | I70: 音频 | J70: 44123 | K70: 8 | L70: 1.3691667 | M70: 已完结 | N70: 99
A71: =ROW()-2 -> 69 | B71: VIP精品课 | C71: 商学院 | D71: 战略规划 | E71: 高层 | F71: 企业家必听柏翔解析BLM战略工具 | G71: 企业家必听柏翔解析BLM战略工具 | H71: 柏翔 | I71: 音频 | J71: 44509 | K71: 13 | L71: 2.1975 | M71: 已完结 | N71: 99
A72: =ROW()-2 -> 70 | B72: VIP精品课 | C72: 商学院 | D72: 战略规划 | E72: 高层 | F72: 商业模式：企业持续增长的双增长引擎|数字化转型 | G72: 商业模式：企业持续增长的双增长引擎 | H72: 高竞 | I72: 视频 | J72: 44531 | K72: 24 | L72: 3.8575 | M72: 已完结 | N72: 199
A73: =ROW()-2 -> 71 | B73: VIP精品课 | C73: 商学院 | D73: 战略规划 | E73: 高层 | F73: 如何运用BLM推动企业战略落地 | G73: |如何运用BLM推动企业战略落地 | H73: 佛洁 | I73: 音频 | J73: 44531 | K73: 32 | L73: 4.9922222 | M73: 已完结 | N73: 99
A74: =ROW()-2 -> 72 | B74: VIP精品课 | C74: 商学院 | D74: 战略规划 | E74: 基层 | F74: 战略管理 | G74: 北京大学教授陈择华主讲 | H74: 陈择华 | I74: 音频 | J74: 44531 | K74: 20 | L74: 3.0661111 | M74: 已完结 | N74: 19.9
... A76: =ROW()-2 -> 74 | B76: VIP精品课 | C76: 商学院 | D76: 战略规划 | E76: 基层 | F76: 从战略到成功的七大行动 | G76: 从战略到成功的七大行动 | H76: 新风向 | I76: 视频 | J76: 44620 | K76: 4 | L76: 0.5 | M76: 已完结 | N76: 64
A77: =ROW()-2 -> 75 | B77: VIP精品课 | C77: 商学院 | D77: 战略规划 | E77: 高层 | F77: 张思宏：亚马逊增长双飞轮 | G77: 张思宏：亚马逊增长双飞轮 | H77: 张思宏 | I77: 视频 | J77: 管理者 | K77: 中层管理者，高层管理者 | L77: 44634 | M77: 20 | N77: 4.6 | O77: 已完结
A78: =ROW()-2 -> 76 | B78: VIP精品课 | C78: 商学院 | D78: 组织发展 | E78: 基层 | F78: 倪云华的团队管理课 | G78: 最佳团队管理课系统方法论，为你定制最实用的团队管理课 | H78: 倪云华 | I78: 音频 | J78: 43238 | K78: 61 | L78: 10.276389 | M78: 已完结 | N78: 99
A79: =ROW()-2 -> 77 | B79: VIP精品课 | C79: 商学院 | D79: 组织发展 | E79: 中层 | F79: 孙陶然亲授：企业管理实战兵法 | G79: 管理企业，不仅知道做什么，而且知道怎么做 | H79: 孙陶然 | I79: 音频 | J79: 43321 | K79: 30 | L79: 4.785 | M79: 已完结 | N79: 99
A80: =ROW()-2 -> 78 | B80: VIP精品课 | C80: 商学院 | D80: 组织发展 | E80: 中层 | F80: 关苏哲：高效管理者的必备技能 | G80: 私董会总裁教练，带你全面学习管理技能 | H80: 关苏哲 | I80: 音频 | J80: 43488 | K80: 72 | L80: 13.571389 | M80: 更新中 | N80: 129
A81: =ROW()-2 -> 79 | B81: VIP精品课 | C81: 商学院 | D81: 组织发展 | E81: 高层 | F81: 实战三板斧 | 阿里巴巴管理模式 | G81: 破译阿里文化基因，揭秘阿里管理系统 | H81: 天机 | I81: 音频 | J81: 43563 | K81: 76 | L81: 20.003611 | M81: 已完结 | N81: 99
A82: =ROW()-2 -> 80 | B82: VIP精品课 | C82: 商学院 | D82: 组织发展 | E82: 基层 | F82: 倪云华：团队管理40条军规 | G82: 全网最受欢迎的团队管理视频课 | H82: 倪云华 | I82: 视频 | J82: 43579 | K82: 40 | L82: 3.5747222 | M82: 已完结 | N82: 99
A83: =ROW()-2 -> 81 | B83: VIP精品课 | C83: 商学院 | D83: 组织发展 | E83: 高层 | F83: 向心力阿米巴经营实战学 | G83: 结合中国企业实情，可落地的阿米巴经营实学 | H83: 何朝来 | I83: 音频 | J83: 43659 | K83: 59 | L83: 9.2888889 | M83: 更新中 | N83: 99
A84: =ROW()-2 -> 82 | B84: VIP精品课 | C84: 商学院 | D84: 组织发展 | E84: 高层 | F84: 吴建国：华为组织管理精要 | G84: 跟华为老将，学华为组织管理之道 | H84: 吴建国 | I84: 音频 | J84: 44053 | K84: 27 | L84: 5.0436111 | M84: 已完结 | N84: 199
A85: =ROW()-2 -> 83 | B85: VIP精品课 | C85: 商学院 | D85: 组织发展 | E85: 基层 | F85: 10人以下小团队管理手册：轻松带出高绩效团队 | G85: 释放小编队潜能，打造高绩效团队 | H85: 徐国允 | I85: 音频 | J85: 44175 | K85: 22 | L85: 3.6963889 | M85: 已完结 | N85: 99
A86: =ROW()-2 -> 84 | B86: VIP精品课 | C86: 商学院 | D86: 组织发展 | E86: 基层 | F86: 小团队高效管理手册 | G86: 28个小团队管理新知 | H86: 姜海舟 | I86: 音频 | J86: 44307 | K86: 29 | L86: 5.0083333 | M86: 已完结 | N86: 129
A87: =ROW()-2 -> 85 | B87: VIP精品课 | C87: 商学院 | D87: 组织发展 | E87: 中层 | F87: 管理者必备的24个管理工具 | G87: 顶级商学院必学的管理方法 | H87: 倪云华 | I87: 视频 | J87: 44357 | K87: 24 | L87: 5.8875 | M87: 已完结 | N87: 199
A88: =ROW()-2 -> 86 | B88: VIP精品课 | C88: 商学院 | D88: 组织发展 | E88: 基层 | F88: 杨华：向华为学习班组管理 | G88: 金牌班组长必修课 | H88: 杨华 | I88: 视频 | J88: 44463 | K88: 23 | L88: 3.2986111 | M88: 已完结 | N88: 199
A89: =ROW()-2 -> 87 | B89: VIP精品课 | C89: 商学院 | D89: 组织发展 | E89: 中层 | F89: 组织精进手册 | G89: 婷姐案例宝典 | H89: 吴婷 | I89: 音频 | J89: 44489 | K89: 10 | L89: 2.1652778 | M89: 更新中 | N89: 168
... A99: =ROW()-2 -> 97 | B99: VIP精品课 | C99: 商学院 | D99: 组织管理 | E99: 中层 | F99: 精益组织变革管理 | G99: 精益组织变革管理 | H99: 刘诚 | I99: 视频 | J99: 44627 | K99: 10 | L99: 2.1 | M99: 已完结 | N99: 399
A100: =ROW()-2 -> 98 | B100: 畅听课 | C100: 商学院 | D100: 管理认知 | E100: 高层 | F100: 领导力发展新趋势 | G100: 解读领导力发展的未来 | H100: CCL美国创新领导力中心 | I100: 音频 | J100: 43640 | K100: 15 | L100: 2.0216667 | M100: 已完结
A101: =ROW()-2 -> 99 | B101: 畅听课 | C101: 商学院 | D101: 目标策略 | E101: 中层 | F101: OKR远程办公的业务突破与目标管理 | G101: OKR源头英特尔背景大咖亲授 | H101: 陈德金 | I101: 音频 | J101: 43886 | K101: 1 | L101: 0.70277778 | M101: 已完结
A102: =ROW()-2 -> 100 | B102: 畅听课 | C102: 商学院 | D102: 业务经营 | E102: 中层 | F102: 马云内部讲话 | G102: 马云首度公开他的互联网思想和战略，阐述了自己在阿里巴巴集团崛起关键阶段的想法和干法 | H102: 王叔叔讲故事 | I102: 音频 | J102: 43461 | K102: 33 | L102: 11.161944 | M102: 已完结
A103: =ROW()-2 -> 101 | B103: 畅听课 | C103: 商学院 | D103: 组织发展 | E103: 高层 | F103: 组织进化论 | G103: 组织进化论 | H103: 声动活泼 | I103: 音频 | J103: 44613 | K103: 26 | L103: 23.2 | M103: 未完结

Sheet 书籍列表（总）
A1: 轻学堂—书籍列表
A2: 内容说明： 1. 适用VIP企业或已购买企业有声图书馆产品的企业，实现全员畅听，打造学习型组织。 2. 讲书，由专业团队编辑，挑选各领域的经典好书，每本书25分钟左右精华音频呈现。 3. 有声书，精听整本书籍，阅读新方式。轻学堂整合喜马拉雅海量、正版有声书资源，打造企业有声图书馆。
A3: 序号 | B3: 书籍大类 | C3: 分类 | D3: 书籍名称 | E3: 作者 | F3: 主讲人 | G3: 适听人群 | H3: 集数 | I3: 已上架课时总时间/h | J3: 轻学堂上架日期 | K3: 更新状态 | L3: 单卖价格/元
A4: =ROW()-3 -> 1 | B4: 讲书 | C4: 财经 | D4: 文明寻思录 | E4: 秦朔 | F4: 秦朔 | G4: 全员 | H4: 1 | I4: 0.63472222 | J4: 43468 | K4: 已完结 | L4: 4.99
A5: =ROW()-3 -> 2 | B5: 讲书 | C5: 财经 | D5: 经营分析与估值 | E5: 克雷沙·G·帕利普 | F5: 薛云奎 | G5: 全员 | H5: 1 | I5: 0.54777778 | J5: 43469 | K5: 已完结 | L5: 4.99
A6: =ROW()-3 -> 3 | B6: 讲书 | C6: 财经 | D6: 华尔街幽灵 | E6: 阿瑟·L·辛普森 | F6: 孟可 | G6: 全员 | H6: 1 | I6: 0.71916667 | J6: 43469 | K6: 已完结 | L6: 4.99
A7: =ROW()-3 -> 4 | B7: 讲书 | C7: 财经 | D7: 魔鬼经济学 | E7: 史蒂芬·列维特/史蒂芬·都伯纳 | F7: 元生 | G7: 全员 | H7: 1 | I7: 0.75722222 | J7: 43469 | K7: 已完结 | L7: 4.99
A8: =ROW()-3 -> 5 | B8: 讲书 | C8: 财经 | D8: 不平等的代价 | E8: 约瑟夫·E·斯蒂格利茨 | F8: 李长安 | G8: 全员 | H8: 1 | I8: 0.49472222 | J8: 43483 | K8: 已完结 | L8: 4.99
A9: =ROW()-3 -> 6 | B9: 讲书 | C9: 财经 | D9: 新财富管理 | E9: 哈罗德·埃文斯基，斯蒂芬·M·霍伦，托马斯·R·罗宾逊 | F9: 李清昊 | G9: 全员 | H9: 29 | I9: 8.8205556 | J9: 43483 | K9: 已完结 | L9: 4.99
A10: =ROW()-3 -> 7 | B10: 讲书 | C10: 财经 | D10: 1844年经济学哲学手稿 | E10: 卡尔·马克思 | F10: 薛晓明 | G10: 全员 | H10: 1 | I10: 0.40611111 | J10: 43962 | K10: 已完结 | L10: 4.99
A11: =ROW()-3 -> 8 | B11: 讲书 | C11: 财经 | D11: 游戏改变世界 | E11: 简·麦戈尼格尔 | F11: 英国报姐 | G11: 全员 | H11: 1 | I11: 0.35777778 | J11: 43962 | K11: 已完结 | L11: 4.99
A12: =ROW()-3 -> 9 | B12: 讲书 | C12: 财经 | D12: 爆裂 | E12: 伊藤穰一，杰夫·豪 | F12: 曹易伦 | G12: 全员 | H12: 1 | I12: 0.45055556 | J12: 43962 | K12: 已完结 | L12: 4.99
A13: =ROW()-3 -> 10 | B13: 讲书 | C13: 财经 | D13: 逃不开的经济周期 | E13: 拉斯·特维德 | F13: 魏强斌 | G13: 全员 | H13: 1 | I13: 0.42055556 | J13: 43962 | K13: 已完结 | L13: 4.99
A14: =ROW()-3 -> 11 | B14: 讲书 | C14: 财经 | D14: 行动的勇气 | E14: 本·伯南克 | F14: 李长安 | G14: 全员 | H14: 1 | I14: 0.46555556 | J14: 43962 | K14: 已完结 | L14: 4.99
A15: =ROW()-3 -> 12 | B15: 讲书 | C15: 财经 | D15: 引爆点 | E15: 马尔科姆·格拉德威尔 | F15: 耿人健 | G15: 全员 | H15: 1 | I15: 0.30138889 | J15: 43962 | K15: 已完结 | L15: 4.99
... A130: =ROW()-3 -> 127 | B130: 讲书 | C130: 财经 | D130: 极简法则 | E130: 理查德·科克 | F130: 西蒙 | G130: 全员 | H130: 1 | I130: 0.52 | J130: 44186 | K130: 已完结 | L130: 4.99
A131: =ROW()-3 -> 128 | B131: 讲书 | C131: 财经 | D131: 未来银行 | E131: 乔纳森·马米兰 | F131: 刘美 | G131: 全员 | H131: 1 | I131: 0.5 | J131: 44263 | K131: 已完结 | L131: 4..99
A132: =ROW()-3 -> 129 | B132: 讲书 | C132: 财经 | D132: 财富的起源 | E132: 埃里克·拜因霍克 | F132: 章永宏 | G132: 全员 | H132: 1 | I132: 0.5 | J132: 44522 | K132: 已完结 | L132: 4..99
A133: =ROW()-3 -> 130 | B133: 讲书 | C133: 财经 | D133: 中间人经济 | E133: 玛丽娜·克拉科夫斯基 | F133: 陈曦 | G133: 全员 | H133: 1 | I133: 0.5 | J133: 44543 | K133: 已完结 | L133: 4..99
A134: =ROW()-3 -> 131 | B134: 讲书 | C134: 财经 | D134: 一本书读懂财报 | E134: 肖星 | F134: 刘美 | G134: 全员 | H134: 1 | I134: 0.49 | J134: 44551 | K134: 已完结 | L134: 4.99
A135: =ROW()-3 -> 132 | B135: 讲书 | C135: 财经 | D135: 与运气竞争 | E135: 克莱顿·克里斯坦森 | F135: 陈曦 | G135: 全员 | H135: 1 | I135: 0.48 | J135: 44578 | K135: 已完结 | L135: 4..100
A136: =ROW()-3 -> 133 | B136: 讲书 | C136: 财经 | D136: 价值 | E136: 张磊 | F136: 武京丽 | G136: 全员 | H136: 1 | I136: 0.5 | J136: 44620 | K136: 已完结 | L136: 4.9
A137: =ROW()-3 -> 134 | B137: 讲书 | C137: 创业 | D137: 一胜九败：优衣库风靡全球的秘密 | E137: 柳井正 | F137: 徐静波 | G137: 全员 | H137: 1 | I137: 0.52888889 | J137: 43469 | K137: 已完结 | L137: 4.99
A138: =ROW()-3 -> 135 | B138: 讲书 | C138: 创业 | D138: 创新公司 | E138: 艾德·卡特姆/埃米·华莱士 | F138: 图南 | G138: 全员 | H138: 1 | I138: 0.46666667 | J138: 43962 | K138: 已完结 | L138: 4.99
A139: =ROW()-3 -> 136 | B139: 讲书 | C139: 创业 | D139: 疯传 | E139: 乔纳·伯杰 | F139: 周华明 | G139: 全员 | H139: 1 | I139: 0.73194444 | J139: 43962 | K139: 已完结 | L139: 4.99
A140: =ROW()-3 -> 137 | B140: 讲书 | C140: 创业 | D140: 一网打尽 | E140: 布拉德·斯通 | F140: 陈聪明 | G140: 全员 | H140: 1 | I140: 0.42777778 | J140: 43978 | K140: 已完结 | L140: 4.99
A141: =ROW()-3 -> 138 | B141: 讲书 | C141: 创业 | D141: 鞋狗 | E141: 菲尔·奈特 | F141: 邹大湿 | G141: 全员 | H141: 1 | I141: 0.56611111 | J141: 43978 | K141: 已完结 | L141: 4.99
A142: =ROW()-3 -> 139 | B142: 讲书 | C142: 创业 | D142: 孙正义：未来的机遇在哪里 | E142: 井上笃夫 | F142: 钱老师 | G142: 全员 | H142: 1 | I142: 1.9375 | J142: 43978 | K142: 已完结 | L142: 4.99
A143: =ROW()-3 -> 140 | B143: 讲书 | C143: 创业 | D143: 从0到1 | E143: 彼得·蒂尔 | F143: 沈攀 | G143: 全员 | H143: 1 | I143: 0.79277778 | J143: 43978 | K143: 已完结 | L143: 4.99
A144: =ROW()-3 -> 141 | B144: 讲书 | C144: 创业 | D144: 重新定义公司:谷歌是如何运营的 | E144: 埃里克·施密特/乔纳森·罗森伯格 | F144: 沈攀 | G144: 全员 | H144: 1 | I144: 0.4175 | J144: 43978 | K144: 已完结 | L144: 4.99
A145: =ROW()-3 -> 142 | B145: 讲书 | C145: 创业 | D145: Facebook效应 | E145: 大卫·柯克帕特里克 | F145: 韩春苗 | G145: 全员 | H145: 1 | I145: 0.55444444 | J145: 43978 | K145: 已完结 | L145: 4.99
A146: =ROW()-3 -> 143 | B146: 讲书 | C146: 创业 | D146: 硅谷钢铁侠 | E146: 阿什利·万斯 | F146: 高融 | G146: 全员 | H146: 1 | I146: 0.3075 | J146: 43978 | K146: 已完结 | L146: 4.99
A147: =ROW()-3 -> 144 | B147: 讲书 | C147: 创业 | D147: 单点突破 | E147: 张本伟/赵鑫 /杨琰华 | F147: 施襄 | G147: 全员 | H147: 1 | I147: 0.43944444 | J147: 43978 | K147: 已完结 | L147: 4.99
... A161: =ROW()-3 -> 158 | B161: 讲书 | C161: 创业 | D161: 微创新 | E161: 雅各布·哥登堡 | F161: 严智砾 | G161: 全员 | H161: 1 | I161: 0.4 | J161: 44102 | K161: 已完结 | L161: 4.99
A162: =ROW()-3 -> 159 | B162: 讲书 | C162: 创业 | D162: 翻转课堂的可汗学院 | E162: 萨尔曼·可汗 | F162: 陈曦 | G162: 全员 | H162: 1 | I162: 0.36 | J162: 44123 | K162: 已完结 | L162: 4..99
A163: =ROW()-3 -> 160 | B163: 讲书 | C163: 创业 | D163: 事实（上） | E163: 汉斯·罗斯林 | F163: 林伯虎 | G163: 全员 | H163: 1 | I163: 0.49555556 | J163: 44158 | K163: 已完结 | L163: 4.99
A164: =ROW()-3 -> 161 | B164: 讲书 | C164: 创业 | D164: 富甲美国 | E164: 山姆·沃尔顿 | F164: 果真 | G164: 全员 | H164: 1 | I164: 0.4 | J164: 44529 | K164: 已完结 | L164: 4.99
A165: =ROW()-3 -> 162 | B165: 讲书 | C165: 管理 | D165: 罗伯特议事规则 | E165: 亨利·罗伯特 | F165: 图南 | G165: 全员 | H165: 1 | I165: 0.36666667 | J165: 43468 | K165: 已完结 | L165: 4.99
A166: =ROW()-3 -> 163 | B166: 讲书 | C166: 管理 | D166: 驱动力 | E166: 丹尼尔·平克 | F166: 元生 | G166: 全员 | H166: 1 | I166: 0.405 | J166: 43468 | K166: 已完结 | L166: 4.99
A167: =ROW()-3 -> 164 | B167: 讲书 | C167: 管理 | D167: 商业的本质 | E167: 杰克·韦尔奇，苏茜·韦尔奇 | F167: 曾言 | G167: 全员 | H167: 1 | I167: 0.50305556 | J167: 43469 | K167: 已完结 | L167: 4.99
A168: =ROW()-3 -> 165 | B168: 讲书 | C168: 管理 | D168: 第五项修炼 | E168: 彼得·圣吉 | F168: 刘杰辉 | G168: 全员 | H168: 1 | I168: 0.70555556 | J168: 43469 | K168: 已完结 | L168: 4.99
A169: =ROW()-3 -> 166 | B169: 讲书 | C169: 管理 | D169: 思考力：潮爆东京大学的思维公开课 | E169: 上田正仁 | F169: 耿人健 | G169: 全员 | H169: 1 | I169: 0.59555556 | J169: 43483 | K169: 已完结 | L169: 4.99
A170: =ROW()-3 -> 167 | B170: 讲书 | C170: 管理 | D170: 谈判力 | E170: 费希尔/尤里/巴顿 | F170: 熊浩 | G170: 全员 | H170: 1 | I170: 0.61388889 | J170: 43893 | K170: 已完结 | L170: 4.99
A171: =ROW()-3 -> 168 | B171: 讲书 | C171: 管理 | D171: 基业长青 | E171: 吉姆·柯林斯/杰里·波勒斯 | F171: 浦宇平 | G171: 全员 | H171: 1 | I171: 0.74722222 | J171: 43893 | K171: 已完结 | L171: 4.99
A172: =ROW()-3 -> 169 | B172: 讲书 | C172: 管理 | D172: 领导力 | E172: 亚历克斯·弗格森 | F172: 王利杰 | G172: 全员 | H172: 1 | I172: 0.39833333 | J172: 43913 | K172: 已完结 | L172: 4.99
A173: =ROW()-3 -> 170 | B173: 讲书 | C173: 管理 | D173: 沃顿商学院最受欢迎的谈判课 | E173: 斯图尔特·戴蒙德 | F173: 陈泓霖 | G173: 全员 | H173: 1 | I173: 0.42583333 | J173: 43962 | K173: 已完结 | L173: 4.99
A174: =ROW()-3 -> 171 | B174: 讲书 | C174: 管理 | D174: 领导变革 | E174: 约翰·科特 | F174: 章郎 | G174: 全员 | H174: 1 | I174: 0.41194444 | J174: 43962 | K174: 已完结 | L174: 4.99
... A221: =ROW()-3 -> 218 | B221: 讲书 | C221: 管理 | D221: 德鲁克经典五问 | E221: 彼得·德鲁克 | F221: 李洁 | G221: 全员 | H221: 4 | I221: 2 | J221: 44032 | K221: 已完结 | L221: 4.99
A222: =ROW()-3 -> 219 | B222: 讲书 | C222: 管理 | D222: 管理的实践 | E222: 彼得·德鲁克 | F222: 李洁 | G222: 全员 | H222: 3 | I222: 1.1819444 | J222: 44032 | K222: 已完结
A223: =ROW()-3 -> 220 | B223: 讲书 | C223: 管理 | D223: 公司的概念 | E223: 彼得·德鲁克 | F223: 李清昊 | G223: 全员 | H223: 3 | I223: 1.23 | J223: 44039 | K223: 已完结 | L223: 4.99
A224: =ROW()-3 -> 221 | B224: 讲书 | C224: 管理 | D224: 成果管理 | E224: 彼得·德鲁克 | F224: 李洁 | G224: 全员 | H224: 6 | I224: 2.44 | J224: 44046 | K224: 已完结 | L224: 4.99
A225: =ROW()-3 -> 222 | B225: 讲书 | C225: 管理 | D225: 管理：任务、责任和实践 | E225: 彼得·德鲁克 | F225: 李洁 | G225: 全员 | H225: 2 | I225: 0.82 | J225: 44046 | K225: 已完结 | L225: 4.99
A226: =ROW()-3 -> 223 | B226: 讲书 | C226: 管理 | D226: 创新与企业家精神 | E226: 彼得·德鲁克 | F226: 李洁 | G226: 全员 | H226: 3 | I226: 1.2 | J226: 44053 | K226: 已完结 | L226: 4.99
A227: =ROW()-3 -> 224 | B227: 讲书 | C227: 管理 | D227: 卓有成效的管理者 | E227: 彼得·德鲁克 | F227: 李洁 | G227: 全员 | H227: 3 | I227: 1.2 | J227: 44060 | K227: 已完结 | L227: 4.99
A228: =ROW()-3 -> 225 | B228: 讲书 | C228: 管理 | D228: 管理未来 | E228: 彼得·德鲁克 | F228: 李洁 | G228: 全员 | H228: 3 | I228: 1.2 | J228: 44060 | K228: 已完结 | L228: 4.99
A229: =ROW()-3 -> 226 | B229: 讲书 | C229: 管理 | D229: 后资本主义社会 | E229: 彼得·德鲁克 | F229: 李洁 | G229: 全员 | H229: 3 | I229: 1.3 | J229: 44067 | K229: 已完结 | L229: 4.99
A230: =ROW()-3 -> 227 | B230: 讲书 | C230: 管理 | D230: 非营利组织的管理 | E230: 彼得·德鲁克 | F230: 李洁 | G230: 全员 | H230: 4 | I230: 2.66 | J230: 44067 | K230: 已完结 | L230: 4.99
A231: =ROW()-3 -> 228 | B231: 讲书 | C231: 管理 | D231: 重新定义公司：谷歌是如何运营的 | E231: 埃里克·施密特 | F231: 李清昊 | G231: 全员 | H231: 3 | I231: 1.2 | J231: 44067 | K231: 已完结 | L231: 4.99
A232: =ROW()-3 -> 229 | B232: 讲书 | C232: 管理 | D232: 变革中的管理 | E232: 彼得·德鲁克 | F232: 李洁 | G232: 全员 | H232: 3 | I232: 1.22 | J232: 44067 | K232: 已完结 | L232: 4.99
A233: =ROW()-3 -> 230 | B233: 讲书 | C233: 管理 | D233: 已经发生的未来 | E233: 彼得·德鲁克 | F233: 李洁 | G233: 全员 | H233: 3 | I233: 1.23 | J233: 44067 | K233: 已完结 | L233: 4.99
A234: =ROW()-3 -> 231 | B234: 讲书 | C234: 管理 | D234: 德鲁克52周教练指南 | E234: 约瑟夫·马恰列洛 | F234: 李洁 | G234: 全员 | H234: 3 | I234: 1.3 | J234: 44074 | K234: 已完结 | L234: 5.99
... A387: =ROW()-3 -> 384 | B387: 讲书 | C387: 历史 | D387: 全球化简史 | E387: 杰弗里•萨克斯 | F387: 刀劈三观抱老师 | G387: 全员 | H387: 1 | I387: 0.48 | J387: 44578 | K387: 已完结 | L387: 4.99
A388: =ROW()-3 -> 385 | B388: 讲书 | C388: 历史 | D388: 登月第一人 | E388: 詹姆斯·汉森 | F388: 林雨 | G388: 全员 | H388: 1 | I388: 0.5 | J388: 44606 | K388: 已完结
A389: =ROW()-3 -> 386 | B389: 讲书 | C389: 亲子 | D389: 由内而外的教养 | E389: 丹尼尔·西格尔/玛丽·哈策尔 | F389: 黎明 | G389: 全员 | H389: 1 | I389: 0.44083333 | J389: 43962 | K389: 已完结 | L389: 4.99
A390: =ROW()-3 -> 387 | B390: 讲书 | C390: 亲子 | D390: 游戏力II | E390: 劳伦斯·科恩 | F390: 孙曙 | G390: 全员 | H390: 1 | I390: 0.45722222 | J390: 43962 | K390: 已完结 | L390: 4.99
A391: =ROW()-3 -> 388 | B391: 讲书 | C391: 亲子 | D391: 正面管教 | E391: 简·尼尔森 | F391: 林瑜 | G391: 全员 | H391: 1 | I391: 0.49333333 | J391: 43978 | K391: 已完结 | L391: 4.99
A392: =ROW()-3 -> 389 | B392: 讲书 | C392: 亲子 | D392: 给孩子的未来脑计划 | E392: 魏坤琳 | F392: 陈曦 | G392: 全员 | H392: 1 | I392: 0.54944444 | J392: 43978 | K392: 已完结 | L392: 4.99
A393: =ROW()-3 -> 390 | B393: 讲书 | C393: 亲子 | D393: 童年的秘密 | E393: 玛丽亚·蒙台梭利 | F393: 托德老师 | G393: 全员 | H393: 1 | I393: 0.28333333 | J393: 43978 | K393: 已完结 | L393: 4.99
A394: =ROW()-3 -> 391 | B394: 讲书 | C394: 亲子 | D394: 小夜曲 | E394: 石黑一雄 | F394: 田艺苗 | G394: 全员 | H394: 1 | I394: 0.4625 | J394: 43978 | K394: 已完结 | L394: 4.99
A395: =ROW()-3 -> 392 | B395: 讲书 | C395: 亲子 | D395: 有吸收力的心灵 | E395: 玛丽亚·蒙台梭利 | F395: 于玲娜 | G395: 全员 | H395: 1 | I395: 0.47 | J395: 44151 | K395: 已完结 | L395: 4.99
A396: =ROW()-3 -> 393 | B396: 讲书 | C396: 亲子 | D396: 不平等的童年 | E396: 安妮特·拉鲁 | F396: 尼德罗 | G396: 全员 | H396: 1 | I396: 19.139444 | J396: 44162 | K396: 已完结 | L396: 4.99
A397: =ROW()-3 -> 394 | B397: 讲书 | C397: 亲子 | D397: 无条件养育 | E397: 艾尔菲.科恩 | F397: 陈曦 | G397: 全员 | H397: 1 | I397: 0.5 | J397: 44292 | K397: 已完结 | L397: 4.99
A398: =ROW()-3 -> 395 | B398: 讲书 | C398: 亲子 | D398: 高效能家庭的7个习惯 | E398: 史蒂芬・柯维 | F398: 安牧 | G398: 全员 | H398: 1 | I398: 0.5 | J398: 44312 | K398: 已完结 | L398: 4.99
A399: =ROW()-3 -> 396 | B399: 讲书 | C399: 亲子 | D399: 如何让孩子成年有成人 | E399: 朱莉•利思科特-海姆斯 | F399: 陈曦 | G399: 全员 | H399: 1 | I399: 0.5 | J399: 44340 | K399: 已完结 | L399: 4.99
A400: =ROW()-3 -> 397 | B400: 讲书 | C400: 亲子 | D400: 学习树 | E400: 斯坦利·格林斯潘 | F400: 陈曦 | G400: 全员 | H400: 1 | I400: 0.5 | J400: 44431 | K400: 已完结 | L400: 4.99
... A627: =ROW()-3 -> 624 | B627: 讲书 | C627: 生活 | D627: 癌症·防御 | E627: 李治中 | F627: 林雨 | G627: 全员 | H627: 1 | I627: 0.48 | J627: 44565 | K627: 已完结 | L627: 4.99
A628: =ROW()-3 -> 625 | B628: 讲书 | C628: 生活 | D628: 优雅老去：你的前100岁健康指南 | E628: 杰罗尔德·温特 | F628: 阿玖 | G628: 全员 | H628: 1 | I628: 0.5 | J628: 44606 | K628: 已完结
A629: =ROW()-3 -> 626 | B629: 讲书 | C629: 文学 | D629: 不能承受的生命之轻 | E629: 米兰·昆德拉 | F629: 木文 | G629: 全员 | H629: 1 | I629: 0.49388889 | J629: 43962 | K629: 已完结 | L629: 4.99
A630: =ROW()-3 -> 627 | B630: 讲书 | C630: 文学 | D630: 变形记 | E630: 卡夫卡 | F630: 梁锡江 | G630: 全员 | H630: 1 | I630: 0.33111111 | J630: 43962 | K630: 已完结 | L630: 4.99
A631: =ROW()-3 -> 628 | B631: 讲书 | C631: 文学 | D631: 追忆似水年华 | E631: 马塞尔·普鲁斯特 | F631: 徐兆正 | G631: 全员 | H631: 1 | I631: 0.42055556 | J631: 43962 | K631: 已完结 | L631: 4.99
A632: =ROW()-3 -> 629 | B632: 讲书 | C632: 文学 | D632: 三体 | E632: 刘慈欣 | F632: 沈律君 | G632: 全员 | H632: 1 | I632: 0.38222222 | J632: 43962 | K632: 已完结 | L632: 4.99
A633: =ROW()-3 -> 630 | B633: 讲书 | C633: 文学 | D633: 三体Ⅱ·黑暗森林 | E633: 刘慈欣 | F633: 沈律君 | G633: 全员 | H633: 1 | I633: 0.48138889 | J633: 43962 | K633: 已完结 | L633: 4.99
A634: =ROW()-3 -> 631 | B634: 讲书 | C634: 文学 | D634: 三体Ⅲ·死神永生 | E634: 刘慈欣 | F634: 沈律君 | G634: 全员 | H634: 1 | I634: 0.74888889 | J634: 43962 | K634: 已完结 | L634: 4.99
A635: =ROW()-3 -> 632 | B635: 讲书 | C635: 文学 | D635: 霍乱时期的爱情 | E635: 加西亚·马尔克斯 | F635: 云也退 | G635: 全员 | H635: 1 | I635: 0.51 | J635: 43962 | K635: 已完结 | L635: 4.99
A636: =ROW()-3 -> 633 | B636: 讲书 | C636: 文学 | D636: 关于他人的痛苦 | E636: 苏珊·桑塔格 | F636: 蒋方舟 | G636: 全员 | H636: 1 | I636: 0.78666667 | J636: 43978 | K636: 已完结 | L636: 4.99
A637: =ROW()-3 -> 634 | B637: 讲书 | C637: 文学 | D637: 倾城之恋 | E637: 张爱玲 | F637: 止庵 | G637: 全员 | H637: 1 | I637: 0.68 | J637: 43978 | K637: 已完结 | L637: 4.99
A638: =ROW()-3 -> 635 | B638: 讲书 | C638: 文学 | D638: 小王子 | E638: 圣埃克苏佩里 | F638: 安东尼 | G638: 全员 | H638: 1 | I638: 0.36777778 | J638: 43978 | K638: 已完结 | L638: 4.99
A639: =ROW()-3 -> 636 | B639: 讲书 | C639: 文学 | D639: 徒然草 | E639: 吉田兼好 | F639: 程璧 | G639: 全员 | H639: 1 | I639: 0.52138889 | J639: 43978 | K639: 已完结 | L639: 4.99
A640: =ROW()-3 -> 637 | B640: 讲书 | C640: 文学 | D640: 飞鸟集 | E640: 罗宾德拉纳特·泰戈尔 | F640: 胡德夫 | G640: 全员 | H640: 1 | I640: 0.38555556 | J640: 43978 | K640: 已完结 | L640: 4.99
... A650: =ROW()-3 -> 647 | B650: 讲书 | C650: 文学 | D650: 不能承受的生命之轻 | E650: 米兰·昆德拉 | F650: 路上读书 | G650: 全员 | H650: 2 | I650: 0.98 | J650: 44074 | K650: 已完结 | L650: 4.99
A651: =ROW()-3 -> 648 | B651: 讲书 | C651: 文学 | D651: 呼啸山庄 | E651: 艾米莉·勃朗特 | F651: 路上读书 | G651: 全员 | H651: 3 | I651: 1.5358333 | J651: 44074 | K651: 已完结
A652: =ROW()-3 -> 649 | B652: 讲书 | C652: 文学 | D652: 芳华 | E652: 严歌苓 | F652: 路上读书 | G652: 全员 | H652: 2 | I652: 0.95 | J652: 44081 | K652: 已完结 | L652: 4.99
A653: =ROW()-3 -> 650 | B653: 讲书 | C653: 文学 | D653: 半生缘 | E653: 张爱玲 | F653: 路上读书 | G653: 全员 | H653: 2 | I653: 0.95 | J653: 44088 | K653: 已完结 | L653: 4.99
A654: =ROW()-3 -> 651 | B654: 讲书 | C654: 文学 | D654: 长恨歌 | E654: 王安忆 | F654: 路上读书 | G654: 全员 | H654: 2 | I654: 1.14 | J654: 44088 | K654: 已完结 | L654: 4.99
A655: =ROW()-3 -> 652 | B655: 讲书 | C655: 文学 | D655: 白夜行 | E655: 东野圭吾 | F655: 路上读书 | G655: 全员 | H655: 1 | I655: 0.5 | J655: 44088 | K655: 未完结 | L655: 4.99
A656: =ROW()-3 -> 653 | B656: 讲书 | C656: 文学 | D656: 东方快车谋杀案 | E656: 阿加莎·克里斯蒂 | F656: 路上读书 | G656: 全员 | H656: 2 | I656: 1.12 | J656: 44088 | K656: 已完结 | L656: 4.99
A657: =ROW()-3 -> 654 | B657: 讲书 | C657: 文学 | D657: 无人生还 | E657: 阿加莎·克里斯蒂 | F657: 路上读书 | G657: 全员 | H657: 1 | I657: 0.62 | J657: 44088 | K657: 未完结 | L657: 4.99
A658: =ROW()-3 -> 655 | B658: 讲书 | C658: 文学 | D658: 旁观者 | E658: 彼得·德鲁克 | F658: 李洁 | G658: 全员 | H658: 2 | I658: 0.66 | J658: 44088 | K658: 已完结 | L658: 4.99
A659: =ROW()-3 -> 656 | B659: 讲书 | C659: 文学 | D659: 爱因斯坦传 | E659: 沃尔特·艾萨克森 | F659: 尹铮铮 | G659: 全员 | H659: 1 | I659: 0.6 | J659: 44102 | K659: 已完结 | L659: 4.99
A660: =ROW()-3 -> 657 | B660: 讲书 | C660: 文学 | D660: 霍华德·休斯传 | E660: 詹姆斯·B.斯蒂尔，唐纳德·L.巴特利特 | F660: 尹铮铮 | G660: 全员 | H660: 1 | I660: 0.61 | J660: 44102 | K660: 已完结 | L660: 4.99
...

Sheet 有声书
A1: 有声书
A2: 序号 | B2: 书籍大类 | C2: 分类 | D2: 书籍名称 | E2: 作者 | F2: 主讲人 | G2: 适听人群 | H2: 集数 | I2: 已上架课时总时间/h | J2: 轻学堂上架日期 | K2: 更新状态 | L2: 单卖价格/元
A3: =ROW()-2 -> 1 | B3: 有声书 | C3: 财经 | D3: 读懂经济学的第一本书：国富论 | E3: 斯密 | F3: 子小苏 | G3: 全员 | H3: 115 | I3: 65.919167 | J3: 43273 | K3: 已完结 | L3: 99
A4: =ROW()-2 -> 2 | B4: 有声书 | C4: 财经 | D4: 李清昊带你精读40本投资经典 | E4: 亚当·斯密，本杰明·格雷厄姆，古斯塔夫·勒庞，吉姆·柯林斯，杰里·波勒斯 等 | F4: 李清昊 | G4: 全员 | H4: 27 | I4: 11.923333 | J4: 43325 | K4: 已完结 | L4: 99
A5: =ROW()-2 -> 3 | B5: 有声书 | C5: 财经 | D5: 檀书：叶檀的投资读书笔记 | E5: 彼得·考夫曼，贾雷德·戴蒙，彼得·林奇，约翰·罗瑟查尔德 等 | F5: 叶檀 | G5: 全员 | H5: 27 | I5: 11.923333 | J5: 43325 | K5: 已完结
A6: =ROW()-2 -> 4 | B6: 有声书 | C6: 财经 | D6: 非理性繁荣与金融危机 | E6: 罗伯特·席勒 | F6: 中信书院 | G6: 全员 | H6: 66 | I6: 23.936667 | J6: 43468 | K6: 已完结 | L6: 29.5
A7: =ROW()-2 -> 5 | B7: 有声书 | C7: 财经 | D7: 滚雪球：巴菲特和他的财富人生(上) | E7: 艾丽斯·施罗德 | F7: 中信书院 | G7: 全员 | H7: 40 | I7: 15.357222 | J7: 43468 | K7: 已完结 | L7: 90
A8: =ROW()-2 -> 6 | B8: 有声书 | C8: 财经 | D8: 魔鬼经济学系列 | E8: 史蒂芬·列维特 | F8: 中信书院 | G8: 全员 | H8: 52 | I8: 19.7 | J8: 43468 | K8: 已完结 | L8: 29.5
A9: =ROW()-2 -> 7 | B9: 有声书 | C9: 财经 | D9: 激荡十年，水大鱼大 | E9: 吴晓波 | F9: 蓝狮子FM | G9: 全员 | H9: 45 | I9: 15.616944 | J9: 43468 | K9: 已完结 | L9: 24.5
A10: =ROW()-2 -> 8 | B10: 有声书 | C10: 财经 | D10: 王传福传：比亚迪神话 | E10: 成杰 | F10: 司南时代 | G10: 全员 | H10: 28 | I10: 7.7316667 | J10: 43469 | K10: 已完结 | L10: 33.6
A11: =ROW()-2 -> 9 | B11: 有声书 | C11: 财经 | D11: 钓愚 | E11: 乔治·阿克洛夫 | F11: 中信书院 | G11: 全员 | H11: 22 | I11: 7.7125 | J11: 43469 | K11: 已完结 | L11: 29.5
A12: =ROW()-2 -> 10 | B12: 有声书 | C12: 财经 | D12: 穷查理宝典 | E12: 彼得·考夫曼 | F12: 中信书院 | G12: 全员 | H12: 45 | I12: 17.126389 | J12: 43469 | K12: 已完结 | L12: 19.9
A13: =ROW()-2 -> 11 | B13: 有声书 | C13: 财经 | D13: 销售女神董明珠书写商界传奇 | E13: 肖文键 | F13: 司南时代 | G13: 全员 | H13: 33 | I13: 11.003889 | J13: 43481 | K13: 已完结 | L13: 39.9
A14: =ROW()-2 -> 12 | B14: 有声书 | C14: 财经 | D14: 新制造时代：李书福与吉利、沃尔沃的超级制造 | E14: 王千马，梁冬梅 | F14: 狮声FM | G14: 全员 | H14: 23 | I14: 9.0175 | J14: 43483 | K14: 已完结 | L14: 6.99
A15: =ROW()-2 -> 13 | B15: 有声书 | C15: 财经 | D15: 互联网金融九堂课 | E15: 谢平 | F15: 一度和围脖 | G15: 全员 | H15: 13 | I15: 4.5516667 | J15: 43483 | K15: 已完结 | L15: 24.5
A16: =ROW()-2 -> 14 | B16: 有声书 | C16: 财经 | D16: 灰犀牛：如何应对大概率危机 | E16: 米歇尔·渥克 | F16: 中信书院 | G16: 全员 | H16: 63 | I16: 32.301667 | J16: 43483 | K16: 已完结 | L16: 24.5
A17: =ROW()-2 -> 15 | B17: 有声书 | C17: 财经 | D17: 滚雪球：巴菲特和他的财富人生(下) | E17: 艾丽斯·施罗德 | F17: 中信书院 | G17: 全员 | H17: 22 | I17: 7.5147222 | J17: 43483 | K17: 已完结 | L17: 29.99
... A40: =ROW()-2 -> 38 | B40: 有声书 | C40: 财经 | D40: 财报思维 | E40: 王峰 | F40: 旧时烟 | G40: 全员 | H40: 143 | I40: 15.295 | J40: 44566 | K40: 已完结 | L40: 49.99
A41: =ROW()-2 -> 39 | B41: 有声书 | C41: 财经 | D41: 世界是部金融史 | E41: 陈雨露 | F41: 索析文化 | G41: 全员 | H41: 95 | I41: 15.151667 | J41: 44566 | K41: 已完结
A42: =ROW()-2 -> 40 | B42: 有声书 | C42: 财经 | D42: 读懂双循环新发展格局 | E42: 刘元春 | F42: 中信书院 | G42: 全员 | H42: 29 | I42: 4.8 | J42: 44585 | K42: 已完结 | L42: 34
A43: =ROW()-2 -> 41 | B43: 有声书 | C43: 财经 | D43: 一套书弄懂全球经济命脉 | E43: 赵伟、胡晓磊 | F43: 何建军 | G43: 全员 | H43: 176 | I43: 35.2 | J43: 44599 | K43: 已完结 | L43: 59.99
A44: =ROW()-2 -> 42 | B44: 有声书 | C44: 财经 | D44: 读懂未来中国经济：”十四五“到2035 | E44: ​蔡昉 | F44: 中信书院 | G44: 全员 | H44: 54 | I44: 10.395278 | J44: 44614 | K44: 已完结 | L44: 34.5
A45: =ROW()-2 -> 43 | B45: 有声书 | C45: 财经 | D45: 一本书读懂财务报表 | E45: 文杨 | F45: 流星星 | G45: 全员 | H45: 32 | I45: 5.4488889 | J45: 44614 | K45: 已完结 | L45: 19.99
A46: =ROW()-2 -> 44 | B46: 有声书 | C46: 创业 | D46: 小米生态链战地笔记 | E46: 小米生态链谷仓学院 | F46: 中信书院 | G46: 全员 | H46: 17 | I46: 4.6116667 | J46: 43468 | K46: 已完结 | L46: 59.99
A47: =ROW()-2 -> 45 | B47: 有声书 | C47: 创业 | D47: 华为教父任正非 | E47: 刘世英，彭征明 | F47: kting北京东方视角 | G47: 全员 | H47: 32 | I47: 10.848056 | J47: 43469 | K47: 已完结 | L47: 39.99
A48: =ROW()-2 -> 46 | B48: 有声书 | C48: 创业 | D48: 创业无畏 | E48: 彼得·戴曼迪斯，史蒂芬·科特勒 | F48: 湛庐阅读 | G48: 全员 | H48: 30 | I48: 8.9858333 | J48: 43469 | K48: 已完结 | L48: 49
A49: =ROW()-2 -> 47 | B49: 有声书 | C49: 创业 | D49: 投资异类 | E49: 王利杰 | F49: 湛庐阅读 | G49: 全员 | H49: 78 | I49: 13.182222 | J49: 43469 | K49: 已完结 | L49: 24.5
A50: =ROW()-2 -> 48 | B50: 有声书 | C50: 创业 | D50: 从0到1:开启商业与未来的秘密 | E50: 彼得·蒂尔，布莱克·马斯特斯 | F50: 中信书院 | G50: 全员 | H50: 37 | I50: 15.908611 | J50: 43469 | K50: 已完结 | L50: 8.99
A51: =ROW()-2 -> 49 | B51: 有声书 | C51: 创业 | D51: 精益创业 | E51: 埃里克.莱斯 | F51: 中信书院 | G51: 全员 | H51: 20 | I51: 2.5325 | J51: 43483 | K51: 已完结 | L51: 22.5
A52: =ROW()-2 -> 50 | B52: 有声书 | C52: 创业 | D52: 创业合伙人实战课 | E52: 武帅 | F52: 中信书院 | G52: 全员 | H52: 24 | I52: 8.3763889 | J52: 43483 | K52: 已完结 | L52: 9.9
A53: =ROW()-2 -> 51 | B53: 有声书 | C53: 创业 | D53: 鞋狗 | E53: 菲尔·奈特 | F53: 湛庐阅读 | G53: 全员 | H53: 15 | I53: 5.7608333 | J53: 43691 | K53: 已完结 | L53: 34.5
... A88: =ROW()-2 -> 86 | B88: 有声书 | C88: 管理 | D88: 数字化转型方法论 | E88: 马晓东 | F88: 马晓东 | G88: 全员 | H88: 38 | I88: 12 | J88: 44390 | K88: 已完结 | L88: 49.9
A89: =ROW()-2 -> 87 | B89: 有声书 | C89: 管理 | D89: 稻盛和夫：企业经营实战系列合集 | E89: 稻盛和夫 | F89: HE北笙 | G89: 全员 | H89: 137 | I89: 18.596667 | J89: 44614 | K89: 已完结
A90: =ROW()-2 -> 88 | B90: 有声书 | C90: 管理 | D90: 竞争战略 | E90: 迈克尔·波特 | F90: 中信书院 | G90: 全员 | H90: 37 | I90: 15.389444 | J90: 44614 | K90: 未完结 | L90: 44
A91: =ROW()-2 -> 89 | B91: 有声书 | C91: 管理 | D91: 创新型组织：构建组织可持续的创新力 | E91: 薛旭亮 | G91: 全员 | H91: 44 | I91: 6.7505556 | J91: 44614 | K91: 已完结 | L91: 33.9
A92: =ROW()-2 -> 90 | B92: 有声书 | C92: 管理 | D92: 赋能 | E92: 斯坦利·麦克里斯特尔 | F92: 中信书院 | G92: 全员 | H92: 34 | I92: 12.6275 | J92: 44614 | K92: 未完结 | L92: 24.5
A93: =ROW()-2 -> 91 | B93: 有声书 | C93: 管理 | D93: 增长结构 | E93: 王赛 | F93: 中信书院 | G93: 全员 | H93: 58 | I93: 9.9238889 | J93: 44614 | K93: 已完结 | L93: 34
A94: =ROW()-2 -> 92 | B94: 有声书 | C94: 管理 | D94: 德鲁克的管理秘诀 | E94: 郑一群 | F94: 梦语阁文化传媒 | G94: 全员 | H94: 37 | I94: 12.129167 | J94: 44614 | K94: 已完结 | L94: 14.99
A95: =ROW()-2 -> 93 | B95: 有声书 | C95: 管理 | D95: 600位富商的经营之道 | E95: 张俊杰 | F95: 天下书盟精品图书 | G95: 全员 | H95: 171 | I95: 24.944167 | J95: 44614 | K95: 已完结 | L95: 56.88
A96: =ROW()-2 -> 94 | B96: 有声书 | C96: 管理 | D96: 逆势增长的商业模式 | E96: 石泽杰 | F96: 电子工业出版社 | G96: 全员 | H96: 33 | I96: 8.0291667 | J96: 44614 | K96: 已完结 | L96: 39
A97: =ROW()-2 -> 95 | B97: 有声书 | C97: 管理 | D97: 平台战略 | E97: 陈威如 | F97: 中信书院 | G97: 全员 | H97: 21 | I97: 7.4219444 | J97: 44614 | K97: 已完结 | L97: 29
A98: =ROW()-2 -> 96 | B98: 有声书 | C98: 管理 | D98: 沸腾新十年 | E98: 林军，​胡喆 | F98: 蓝狮子FM | G98: 全员 | H98: 173 | I98: 42.985833 | J98: 44614 | K98: 未完结 | L98: 129
A99: =ROW()-2 -> 97 | B99: 有声书 | C99: 国学 | D99: 齐善鸿讲《道德经》 | E99: 老子 | F99: 齐善鸿 | G99: 全员 | H99: 114 | I99: 31.92 | J99: 43276 | K99: 已完结 | L99: 199
A100: =ROW()-2 -> 98 | B100: 有声书 | C100: 国学 | D100: 于晓非《金刚经》导读 | E100: 鸠摩罗什 | F100: 于晓非 | G100: 全员 | H100: 112 | I100: 46.896111 | J100: 43276 | K100: 已完结 | L100: 49
A101: =ROW()-2 -> 99 | B101: 有声书 | C101: 国学 | D101: 人生不过一念间：南怀瑾的15堂人生智慧课 | E101: 柠檬树 | F101: 人文社科大讲堂 | G101: 全员 | H101: 21 | I101: 2.9205556 | J101: 43691 | K101: 已完结 | L101: 16.99
A102: =ROW()-2 -> 100 | B102: 有声书 | C102: 国学 | D102: 名家朗诵丨儒家经典：论语 | E102: 论语 | F102: 大音倾听 | G102: 全员 | H102: 55 | I102: 14.234722 | J102: 43691 | K102: 已完结 | L102: 199
A103: =ROW()-2 -> 101 | B103: 有声书 | C103: 国学 | D103: 听林清玄讲禅意 | E103: 凌龙 | F103: 亘古皓月 | G103: 全员 | H103: 302 | I103: 60.519722 | J103: 43913 | K103: 未完结 | L103: 199
... A118: =ROW()-2 -> 116 | B118: 有声书 | C118: 科技 | D118: 直播与短视频深度运营 | E118: 王斌；曹三省 | F118: 颉腾数媒 | G118: 全员 | H118: 20 | I118: 7.7683333 | J118: 44566 | K118: 已完结 | L118: 19.9
A119: =ROW()-2 -> 117 | B119: 有声书 | C119: 科技 | D119: 元宇宙通证 | E119: 邢杰，赵国栋，徐远重，易欢欢，余晨 | F119: 杨大妍 | G119: 全员 | H119: 26 | I119: 2.1 | J119: 44571 | K119: 未完结
A120: =ROW()-2 -> 118 | B120: 有声书 | C120: 科技 | D120: 智能机器如何思考 | E120: 肖恩·格里什 | F120: 中信书院 | G120: 全员 | H120: 29 | I120: 8.9036111 | J120: 44571 | K120: 已完结 | L120: 34.5
A121: =ROW()-2 -> 119 | B121: 有声书 | C121: 科技 | D121: 终极算法 | E121: 佩德罗•多明戈斯 | F121: 中信书院 | G121: 全员 | H121: 36 | I121: 12.719722 | J121: 44571 | K121: 已完结 | L121: 34
A122: =ROW()-2 -> 120 | B122: 有声书 | C122: 科技 | D122: 数智驱动新增长 | E122: 智篆商业研究院 | F122: 电子工业出版社 | G122: 全员 | H122: 115 | I122: 13.890556 | J122: 44571 | K122: 已完结 | L122: 79
A123: =ROW()-2 -> 121 | B123: 有声书 | C123: 历史 | D123: 万水朝东 | E123: 陈延武 | F123: 延悦 | G123: 全员 | H123: 9 | I123: 1.5916667 | J123: 43483 | K123: 已完结 | L123: 68
A124: =ROW()-2 -> 122 | B124: 有声书 | C124: 历史 | D124: 从黄河文明到“一带一路” | E124: 李晓鹏 | F124: 国研智库之声 | G124: 全员 | H124: 34 | I124: 13.685278 | J124: 43691 | K124: 已完结 | L124: 15.88
A125: =ROW()-2 -> 123 | B125: 有声书 | C125: 历史 | D125: 逃亡与拯救：二战中的犹太难民与上海 | E125: 王健 | F125: 南洋书苑 | G125: 全员 | H125: 46 | I125: 15.397222 | J125: 43691 | K125: 已完结 | L125: 59.99
A126: =ROW()-2 -> 124 | B126: 有声书 | C126: 历史 | D126: 中央帝国的财政密码 | E126: 郭建龙 | F126: 鹭江出版社 | G126: 全员 | H126: 154 | I126: 53.880278 | J126: 43691 | K126: 已完结 | L126: 19
A127: =ROW()-2 -> 125 | B127: 有声书 | C127: 历史 | D127: 中国时代：美国人眼中的中国 | E127: 师永刚 | F127: 迷_ | G127: 全员 | H127: 15 | I127: 5.3325 | J127: 43691 | K127: 已完结 | L127: 8.99
A128: =ROW()-2 -> 126 | B128: 有声书 | C128: 历史 | D128: 一战简史 | E128: 诺曼·斯通，王东兴，张蓉 | F128: 中信书院 | G128: 全员 | H128: 28 | I128: 5.9572222 | J128: 43691 | K128: 已完结 | L128: 6.6
A129: =ROW()-2 -> 127 | B129: 有声书 | C129: 历史 | D129: 易中天中华史：安史之乱 | E129: 易中天 | F129: 果麦文化 | G129: 全员 | H129: 25 | I129: 8.1122222 | J129: 43691 | K129: 已完结 | L129: 8.4
A130: =ROW()-2 -> 128 | B130: 有声书 | C130: 历史 | D130: 历史真的很有料：历史上的1分钟 | E130: 雾满拦江 | F130: 影子兵 | G130: 全员 | H130: 42 | I130: 14.164722 | J130: 43691 | K130: 已完结 | L130: 6
A131: =ROW()-2 -> 129 | B131: 有声书 | C131: 历史 | D131: 荣归 | E131: 余玮 | F131: 中版去听 | G131: 全员 | H131: 26 | I131: 12.000556 | J131: 43845 | K131: 已完结 | L131: 34
... A133: =ROW()-2 -> 131 | B133: 有声书 | C133: 历史 | D133: 决战朝鲜 | E133: 李峰 | F133: 现代军吧 | G133: 全员 | H133: 178 | I133: 29.6 | J133: 44137 | K133: 已完结 | L133: 35.6
A134: =ROW()-2 -> 132 | B134: 有声书 | C134: 历史 | D134: 铸梦百年——中国宝武130年简史 | E134: 中国宝武 | F134: 中国宝武 | G134: 全员 | H134: 37 | I134: 3.08 | J134: 44403 | K134: 已完结
A135: =ROW()-2 -> 133 | B135: 有声书 | C135: 历史 | D135: 声波里的中国航天 | E135: 中国航天科技集团 | F135: 声波里的中国航天 | G135: 全员 | H135: 22 | I135: 5.5 | J135: 44424 | K135: 未完结
A136: =ROW()-2 -> 134 | B136: 有声书 | C136: 历史 | D136: 为什么是中国 | E136: 金一南 | F136: 金一南 | G136: 全员 | H136: 83 | I136: 8.3 | J136: 44488 | K136: 已完结 | L136: 19.99
A137: =ROW()-2 -> 135 | B137: 有声书 | C137: 亲子 | D137: 让天赋自由 | E137: 肯·罗宾逊，卢·阿罗尼卡 | F137: 湛庐阅读 | G137: 全员 | H137: 21 | I137: 7.3613889 | J137: 43691 | K137: 已完结 | L137: 49.99
A138: =ROW()-2 -> 136 | B138: 有声书 | C138: 亲子 | D138: 父母情商 | E138: 谭一平 | F138: 不太老的老季头 | G138: 全员 | H138: 23 | I138: 6.2013889 | J138: 43691 | K138: 已完结 | L138: 18.99
A139: =ROW()-2 -> 137 | B139: 有声书 | C139: 亲子 | D139: 这样培养孩子才优秀 | E139: 戴东 | F139: 时代光华图书 | G139: 全员 | H139: 103 | I139: 10.498056 | J139: 43691 | K139: 已完结 | L139: 19.9
A140: =ROW()-2 -> 138 | B140: 有声书 | C140: 亲子 | D140: 爱的教育 | E140: 亚米契斯 | F140: 三五闲人 | G140: 全员 | H140: 12 | I140: 3.5211111 | J140: 43691 | K140: 已完结 | L140: 6.99
A141: =ROW()-2 -> 139 | B141: 有声书 | C141: 亲子 | D141: 给孩子讲相对论 | E141: 李淼，王爽 | F141: 铃音频道 | G141: 全员 | H141: 18 | I141: 6.2366667 | J141: 43691 | K141: 已完结 | L141: 28.8
A142: =ROW()-2 -> 140 | B142: 有声书 | C142: 亲子 | D142: 陶行知教育箴言 | E142: 陶行知 | F142: 卓纳文化传媒 | G142: 全员 | H142: 18 | I142: 6.4158333 | J142: 43691 | K142: 已完结 | L142: 6
A143: =ROW()-2 -> 141 | B143: 有声书 | C143: 亲子 | D143: 活出完整自己的妈妈情商课 | E143: 海文颖 | F143: 电子工业出版社 | G143: 全员 | H143: 30 | I143: 9.1269444 | J143: 43691 | K143: 已完结 | L143: 5.6
A144: =ROW()-2 -> 142 | B144: 有声书 | C144: 亲子 | D144: 别为小事误了孩子未来 | E144: 张雪松 | F144: 司南时代 | G144: 全员 | H144: 28 | I144: 9.4958333 | J144: 43691 | K144: 已完结 | L144: 20.99
A145: =ROW()-2 -> 143 | B145: 有声书 | C145: 亲子 | D145: 智商情商加速跑 | E145: 张雅莲 | F145: 司南时代 | G145: 全员 | H145: 54 | I145: 18.1725 | J145: 43691 | K145: 已完结 | L145: 49.98
A146: =ROW()-2 -> 144 | B146: 有声书 | C146: 亲子 | D146: 尼尔斯骑鹅旅行记 | E146: 塞尔玛·拉格洛夫 | G146: 全员 | H146: 76 | I146: 27.428333 | J146: 44553 | K146: 已完结 | L146: 26
A147: =ROW()-2 -> 145 | B147: 有声书 | C147: 人文 | D147: 精读全球好书100本【第一季】 | E147: 卡兰·马哈詹，斯特凡·赫特曼斯，韩江，科尔森·怀特黑德 等 | F147: 路上读书 | G147: 全员 | H147: 152 | I147: 77.72 | J147: 43273 | K147: 已完结
A148: =ROW()-2 -> 146 | B148: 有声书 | C148: 人文 | D148: 杨绛传 | E148: 桑尼 | F148: 颠倒的完美 | G148: 全员 | H148: 69 | I148: 30.674444 | J148: 43481 | K148: 已完结 | L148: 19
A149: =ROW()-2 -> 147 | B149: 有声书 | C149: 人文 | D149: 极简人类史 | E149: 尤瓦尔·赫拉利 | F149: 中信书院 | G149: 全员 | H149: 48 | I149: 11.660278 | J149: 43483 | K149: 已完结 | L149: 99
A150: =ROW()-2 -> 148 | B150: 有声书 | C150: 人文 | D150: 人类简史+未来简史 | E150: 尤瓦尔·赫拉利 | F150: 中信书院 | G150: 全员 | H150: 23 | I150: 3.9411111 | J150: 43516 | K150: 已完结 | L150: 39
A151: =ROW()-2 -> 149 | B151: 有声书 | C151: 人文 | D151: 中国哲学简史 | E151: 冯友兰 | F151: 道法自然_Dy | G151: 全员 | H151: 29 | I151: 9.39 | J151: 43691 | K151: 已完结 | L151: 39.99
A152: =ROW()-2 -> 150 | B152: 有声书 | C152: 人文 | D152: 英雄之旅 | E152: 约瑟夫·坎贝尔 | F152: 湛庐阅读 | G152: 全员 | H152: 27 | I152: 12.286389 | J152: 43691 | K152: 已完结 | L152: 56.99
A153: =ROW()-2 -> 151 | B153: 有声书 | C153: 人文 | D153: 千面英雄 | E153: 约瑟夫·坎贝尔 | F153: 湛庐阅读 | G153: 全员 | H153: 47 | I153: 13.857222 | J153: 43691 | K153: 已完结 | L153: 44
A154: =ROW()-2 -> 152 | B154: 有声书 | C154: 人文 | D154: 大国速度：中国高铁崛起之路 | E154: 高铁见闻 | F154: 湖南科学技术出版社 | G154: 全员 | H154: 12 | I154: 4.1180556 | J154: 43691 | K154: 已完结 | L154: 8.99
A155: =ROW()-2 -> 153 | B155: 有声书 | C155: 人文 | D155: 海派文化地图：沪东风云 | E155: 李晓栋 | F155: 南洋书苑 | G155: 全员 | H155: 35 | I155: 10.899167 | J155: 43691 | K155: 已完结 | L155: 25.99
A156: =ROW()-2 -> 154 | B156: 有声书 | C156: 人文 | D156: 曾国藩家书（白话全译精读版） | E156: 曾国藩 | F156: 王浩 | G156: 全员 | H156: 69 | I156: 18.689167 | J156: 43691 | K156: 已完结 | L156: 21.99
A157: =ROW()-2 -> 155 | B157: 有声书 | C157: 人文 | D157: 跟哲学家谈幸福 | E157: 罗芬芬 | F157: 铃音频道 | G157: 全员 | H157: 24 | I157: 9.5880556 | J157: 43692 | K157: 已完结 | L157: 49.99
A158: =ROW()-2 -> 156 | B158: 有声书 | C158: 人文 | D158: 《自然辩证法》导读 | E158: 艾四林 | F158: 中版去听 | G158: 全员 | H158: 43 | I158: 14.696389 | J158: 43845 | K158: 已完结 | L158: 4
A159: =ROW()-2 -> 157 | B159: 有声书 | C159: 人文 | D159: 《反杜林论》导读 | E159: 崔伟奇 | F159: 中版去听 | G159: 全员 | H159: 31 | I159: 11.770556 | J159: 43845 | K159: 已完结 | L159: 9.9
... A170: =ROW()-2 -> 168 | B170: 有声书 | C170: 人文 | D170: 雷军传 | E170: 陈润 | F170: 韩熙达 | G170: 全员 | H170: 68 | I170: 11.3 | J170: 44494 | K170: 未完结 | L170: 16.99
A171: =ROW()-2 -> 169 | B171: 有声书 | C171: 人文 | D171: 三十六计智慧故事 | E171: 无声的大可 | F171: 无声的大可 | G171: 全员 | H171: 308 | I171: 25.1 | J171: 44522 | K171: 未完结
A172: =ROW()-2 -> 170 | B172: 有声书 | C172: 人文 | D172: 周国平孤独哲学 | E172: 周国平 | F172: 读者 | G172: 全员 | H172: 241 | I172: 32.1 | J172: 44543 | K172: 已完结
A173: =ROW()-2 -> 171 | B173: 有声书 | C173: 人文 | D173: 人类群星闪耀时 | E173: 斯蒂芬·茨威格 | F173: 喜马创造 | G173: 全员 | H173: 57 | I173: 13.1 | J173: 44634 | K173: 未完结 | L173: 69
A174: =ROW()-2 -> 172 | B174: 有声书 | C174: 人文 | D174: 人世间 | E174: 梁晓声 | F174: 喜马讲书 | G174: 全员 | H174: 137 | I174: 50.3 | J174: 44634 | K174: 已完结
A175: =ROW()-2 -> 173 | B175: 有声书 | C175: 社科 | D175: 七堂极简物理课 | E175: 卡洛·罗韦利 | F175: 企鹅兰登有声书 | G175: 全员 | H175: 47 | I175: 14.901667 | J175: 43469 | K175: 已完结 | L175: 29.8
A176: =ROW()-2 -> 174 | B176: 有声书 | C176: 社科 | D176: 平易近人—习近平的语言力量 | E176: 陈锡喜 | F176: 喜马拉雅小红花 | G176: 全员 | H176: 63 | I176: 8.5116667 | J176: 43815 | K176: 已完结 | L176: 28.99
A177: =ROW()-2 -> 175 | B177: 有声书 | C177: 社科 | D177: 平易近人—习近平的语言力量（军事卷） | E177: 刘志辉 | F177: 喜马拉雅小红花 | G177: 全员 | H177: 77 | I177: 9.2844444 | J177: 43815 | K177: 已完结 | L177: 4
A178: =ROW()-2 -> 176 | B178: 有声书 | C178: 社科 | D178: 平易近人：习近平的语言力量（外交卷） | E178: 苏格 | F178: 微距海清 | G178: 全员 | H178: 12 | I178: 4.1052778 | J178: 43815 | K178: 已完结 | L178: 4
A179: =ROW()-2 -> 177 | B179: 有声书 | C179: 社科 | D179: 《共产党宣言》导读 | E179: 艾四林 | F179: 中版去听 | G179: 全员 | H179: 13 | I179: 4.6416667 | J179: 43815 | K179: 已完结 | L179: 4
A180: =ROW()-2 -> 178 | B180: 有声书 | C180: 社科 | D180: 《新民主主义论》导读 | E180: 总主编艾四林，康沛竹，江大伟 | F180: 中版去听 | G180: 全员 | H180: 17 | I180: 5.7336111 | J180: 43815 | K180: 已完结 | L180: 4
A181: =ROW()-2 -> 179 | B181: 有声书 | C181: 社科 | D181: 《论十大关系》导读 | E181: 艾四林，史春风 | F181: 中版去听 | G181: 全员 | H181: 18 | I181: 6.7627778 | J181: 43815 | K181: 已完结 | L181: 4
...

Sheet 讲书
A1: 讲书
A2: 序号 | B2: 书籍大类 | C2: 分类 | D2: 书籍名称 | E2: 作者 | F2: 主讲人 | G2: 适听人群 | H2: 集数 | I2: 已上架课时总时间/h | J2: 轻学堂上架日期 | K2: 更新状态 | L2: 单卖价格/元
A3: =ROW()-2 -> 1 | B3: 讲书 | C3: 财经 | D3: 文明寻思录 | E3: 秦朔 | F3: 秦朔 | G3: 全员 | H3: 1 | I3: 0.63472222 | J3: 43468 | K3: 已完结 | L3: 4.99
A4: =ROW()-2 -> 2 | B4: 讲书 | C4: 财经 | D4: 经营分析与估值 | E4: 克雷沙·G·帕利普 | F4: 薛云奎 | G4: 全员 | H4: 1 | I4: 0.54777778 | J4: 43469 | K4: 已完结 | L4: 4.99
A5: =ROW()-2 -> 3 | B5: 讲书 | C5: 财经 | D5: 华尔街幽灵 | E5: 阿瑟·L·辛普森 | F5: 孟可 | G5: 全员 | H5: 1 | I5: 0.71916667 | J5: 43469 | K5: 已完结 | L5: 4.99
A6: =ROW()-2 -> 4 | B6: 讲书 | C6: 财经 | D6: 魔鬼经济学 | E6: 史蒂芬·列维特/史蒂芬·都伯纳 | F6: 元生 | G6: 全员 | H6: 1 | I6: 0.75722222 | J6: 43469 | K6: 已完结 | L6: 4.99
A7: =ROW()-2 -> 5 | B7: 讲书 | C7: 财经 | D7: 不平等的代价 | E7: 约瑟夫·E·斯蒂格利茨 | F7: 李长安 | G7: 全员 | H7: 1 | I7: 0.49472222 | J7: 43483 | K7: 已完结 | L7: 4.99
A8: =ROW()-2 -> 6 | B8: 讲书 | C8: 财经 | D8: 新财富管理 | E8: 哈罗德·埃文斯基，斯蒂芬·M·霍伦，托马斯·R·罗宾逊 | F8: 李清昊 | G8: 全员 | H8: 29 | I8: 8.8205556 | J8: 43483 | K8: 已完结 | L8: 4.99
A9: =ROW()-2 -> 7 | B9: 讲书 | C9: 财经 | D9: 1844年经济学哲学手稿 | E9: 卡尔·马克思 | F9: 薛晓明 | G9: 全员 | H9: 1 | I9: 0.40611111 | J9: 43962 | K9: 已完结 | L9: 4.99
A10: =ROW()-2 -> 8 | B10: 讲书 | C10: 财经 | D10: 游戏改变世界 | E10: 简·麦戈尼格尔 | F10: 英国报姐 | G10: 全员 | H10: 1 | I10: 0.35777778 | J10: 43962 | K10: 已完结 | L10: 4.99
A11: =ROW()-2 -> 9 | B11: 讲书 | C11: 财经 | D11: 爆裂 | E11: 伊藤穰一，杰夫·豪 | F11: 曹易伦 | G11: 全员 | H11: 1 | I11: 0.45055556 | J11: 43962 | K11: 已完结 | L11: 4.99
A12: =ROW()-2 -> 10 | B12: 讲书 | C12: 财经 | D12: 逃不开的经济周期 | E12: 拉斯·特维德 | F12: 魏强斌 | G12: 全员 | H12: 1 | I12: 0.42055556 | J12: 43962 | K12: 已完结 | L12: 4.99
A13: =ROW()-2 -> 11 | B13: 讲书 | C13: 财经 | D13: 行动的勇气 | E13: 本·伯南克 | F13: 李长安 | G13: 全员 | H13: 1 | I13: 0.46555556 | J13: 43962 | K13: 已完结 | L13: 4.99
A14: =ROW()-2 -> 12 | B14: 讲书 | C14: 财经 | D14: 引爆点 | E14: 马尔科姆·格拉德威尔 | F14: 耿人健 | G14: 全员 | H14: 1 | I14: 0.30138889 | J14: 43962 | K14: 已完结 | L14: 4.99
... A129: =ROW()-2 -> 127 | B129: 讲书 | C129: 财经 | D129: 极简法则 | E129: 理查德·科克 | F129: 西蒙 | G129: 全员 | H129: 1 | I129: 0.52 | J129: 44186 | K129: 已完结 | L129: 4.99
A130: =ROW()-2 -> 128 | B130: 讲书 | C130: 财经 | D130: 未来银行 | E130: 乔纳森·马米兰 | F130: 刘美 | G130: 全员 | H130: 1 | I130: 0.5 | J130: 44263 | K130: 已完结 | L130: 4..99
A131: =ROW()-2 -> 129 | B131: 讲书 | C131: 财经 | D131: 财富的起源 | E131: 埃里克·拜因霍克 | F131: 章永宏 | G131: 全员 | H131: 1 | I131: 0.5 | J131: 44522 | K131: 已完结 | L131: 4..99
A132: =ROW()-2 -> 130 | B132: 讲书 | C132: 财经 | D132: 中间人经济 | E132: 玛丽娜·克拉科夫斯基 | F132: 陈曦 | G132: 全员 | H132: 1 | I132: 0.5 | J132: 44543 | K132: 已完结 | L132: 4..99
A133: =ROW()-2 -> 131 | B133: 讲书 | C133: 财经 | D133: 一本书读懂财报 | E133: 肖星 | F133: 刘美 | G133: 全员 | H133: 1 | I133: 0.49 | J133: 44551 | K133: 已完结 | L133: 4.99
A134: =ROW()-2 -> 132 | B134: 讲书 | C134: 财经 | D134: 与运气竞争 | E134: 克莱顿·克里斯坦森 | F134: 陈曦 | G134: 全员 | H134: 1 | I134: 0.48 | J134: 44578 | K134: 已完结 | L134: 4..100
A135: =ROW()-2 -> 133 | B135: 讲书 | C135: 财经 | D135: 价值 | E135: 张磊 | F135: 武京丽 | G135: 全员 | H135: 1 | I135: 0.5 | J135: 44620 | K135: 已完结 | L135: 4.9
A136: =ROW()-2 -> 134 | B136: 讲书 | C136: 创业 | D136: 一胜九败：优衣库风靡全球的秘密 | E136: 柳井正 | F136: 徐静波 | G136: 全员 | H136: 1 | I136: 0.52888889 | J136: 43469 | K136: 已完结 | L136: 4.99
A137: =ROW()-2 -> 135 | B137: 讲书 | C137: 创业 | D137: 创新公司 | E137: 艾德·卡特姆/埃米·华莱士 | F137: 图南 | G137: 全员 | H137: 1 | I137: 0.46666667 | J137: 43962 | K137: 已完结 | L137: 4.99
A138: =ROW()-2 -> 136 | B138: 讲书 | C138: 创业 | D138: 疯传 | E138: 乔纳·伯杰 | F138: 周华明 | G138: 全员 | H138: 1 | I138: 0.73194444 | J138: 43962 | K138: 已完结 | L138: 4.99
A139: =ROW()-2 -> 137 | B139: 讲书 | C139: 创业 | D139: 一网打尽 | E139: 布拉德·斯通 | F139: 陈聪明 | G139: 全员 | H139: 1 | I139: 0.42777778 | J139: 43978 | K139: 已完结 | L139: 4.99
A140: =ROW()-2 -> 138 | B140: 讲书 | C140: 创业 | D140: 鞋狗 | E140: 菲尔·奈特 | F140: 邹大湿 | G140: 全员 | H140: 1 | I140: 0.56611111 | J140: 43978 | K140: 已完结 | L140: 4.99
A141: =ROW()-2 -> 139 | B141: 讲书 | C141: 创业 | D141: 孙正义：未来的机遇在哪里 | E141: 井上笃夫 | F141: 钱老师 | G141: 全员 | H141: 1 | I141: 1.9375 | J141: 43978 | K141: 已完结 | L141: 4.99
A142: =ROW()-2 -> 140 | B142: 讲书 | C142: 创业 | D142: 从0到1 | E142: 彼得·蒂尔 | F142: 沈攀 | G142: 全员 | H142: 1 | I142: 0.79277778 | J142: 43978 | K142: 已完结 | L142: 4.99
A143: =ROW()-2 -> 141 | B143: 讲书 | C143: 创业 | D143: 重新定义公司:谷歌是如何运营的 | E143: 埃里克·施密特/乔纳森·罗森伯格 | F143: 沈攀 | G143: 全员 | H143: 1 | I143: 0.4175 | J143: 43978 | K143: 已完结 | L143: 4.99
A144: =ROW()-2 -> 142 | B144: 讲书 | C144: 创业 | D144: Facebook效应 | E144: 大卫·柯克帕特里克 | F144: 韩春苗 | G144: 全员 | H144: 1 | I144: 0.55444444 | J144: 43978 | K144: 已完结 | L144: 4.99
A145: =ROW()-2 -> 143 | B145: 讲书 | C145: 创业 | D145: 硅谷钢铁侠 | E145: 阿什利·万斯 | F145: 高融 | G145: 全员 | H145: 1 | I145: 0.3075 | J145: 43978 | K145: 已完结 | L145: 4.99
A146: =ROW()-2 -> 144 | B146: 讲书 | C146: 创业 | D146: 单点突破 | E146: 张本伟/赵鑫 /杨琰华 | F146: 施襄 | G146: 全员 | H146: 1 | I146: 0.43944444 | J146: 43978 | K146: 已完结 | L146: 4.99
... A160: =ROW()-2 -> 158 | B160: 讲书 | C160: 创业 | D160: 微创新 | E160: 雅各布·哥登堡 | F160: 严智砾 | G160: 全员 | H160: 1 | I160: 0.4 | J160: 44102 | K160: 已完结 | L160: 4.99
A161: =ROW()-2 -> 159 | B161: 讲书 | C161: 创业 | D161: 翻转课堂的可汗学院 | E161: 萨尔曼·可汗 | F161: 陈曦 | G161: 全员 | H161: 1 | I161: 0.36 | J161: 44123 | K161: 已完结 | L161: 4..99
A162: =ROW()-2 -> 160 | B162: 讲书 | C162: 创业 | D162: 事实（上） | E162: 汉斯·罗斯林 | F162: 林伯虎 | G162: 全员 | H162: 1 | I162: 0.49555556 | J162: 44158 | K162: 已完结 | L162: 4.99
A163: =ROW()-2 -> 161 | B163: 讲书 | C163: 创业 | D163: 富甲美国 | E163: 山姆·沃尔顿 | F163: 果真 | G163: 全员 | H163: 1 | I163: 0.4 | J163: 44529 | K163: 已完结 | L163: 4.99
A164: =ROW()-2 -> 162 | B164: 讲书 | C164: 管理 | D164: 罗伯特议事规则 | E164: 亨利·罗伯特 | F164: 图南 | G164: 全员 | H164: 1 | I164: 0.36666667 | J164: 43468 | K164: 已完结 | L164: 4.99
A165: =ROW()-2 -> 163 | B165: 讲书 | C165: 管理 | D165: 驱动力 | E165: 丹尼尔·平克 | F165: 元生 | G165: 全员 | H165: 1 | I165: 0.405 | J165: 43468 | K165: 已完结 | L165: 4.99
A166: =ROW()-2 -> 164 | B166: 讲书 | C166: 管理 | D166: 商业的本质 | E166: 杰克·韦尔奇，苏茜·韦尔奇 | F166: 曾言 | G166: 全员 | H166: 1 | I166: 0.50305556 | J166: 43469 | K166: 已完结 | L166: 4.99
A167: =ROW()-2 -> 165 | B167: 讲书 | C167: 管理 | D167: 第五项修炼 | E167: 彼得·圣吉 | F167: 刘杰辉 | G167: 全员 | H167: 1 | I167: 0.70555556 | J167: 43469 | K167: 已完结 | L167: 4.99
A168: =ROW()-2 -> 166 | B168: 讲书 | C168: 管理 | D168: 思考力：潮爆东京大学的思维公开课 | E168: 上田正仁 | F168: 耿人健 | G168: 全员 | H168: 1 | I168: 0.59555556 | J168: 43483 | K168: 已完结 | L168: 4.99
A169: =ROW()-2 -> 167 | B169: 讲书 | C169: 管理 | D169: 谈判力 | E169: 费希尔/尤里/巴顿 | F169: 熊浩 | G169: 全员 | H169: 1 | I169: 0.61388889 | J169: 43893 | K169: 已完结 | L169: 4.99
A170: =ROW()-2 -> 168 | B170: 讲书 | C170: 管理 | D170: 基业长青 | E170: 吉姆·柯林斯/杰里·波勒斯 | F170: 浦宇平 | G170: 全员 | H170: 1 | I170: 0.74722222 | J170: 43893 | K170: 已完结 | L170: 4.99
A171: =ROW()-2 -> 169 | B171: 讲书 | C171: 管理 | D171: 领导力 | E171: 亚历克斯·弗格森 | F171: 王利杰 | G171: 全员 | H171: 1 | I171: 0.39833333 | J171: 43913 | K171: 已完结 | L171: 4.99
A172: =ROW()-2 -> 170 | B172: 讲书 | C172: 管理 | D172: 沃顿商学院最受欢迎的谈判课 | E172: 斯图尔特·戴蒙德 | F172: 陈泓霖 | G172: 全员 | H172: 1 | I172: 0.42583333 | J172: 43962 | K172: 已完结 | L172: 4.99
A173: =ROW()-2 -> 171 | B173: 讲书 | C173: 管理 | D173: 领导变革 | E173: 约翰·科特 | F173: 章郎 | G173: 全员 | H173: 1 | I173: 0.41194444 | J173: 43962 | K173: 已完结 | L173: 4.99
... A218: =ROW()-2 -> 216 | B218: 讲书 | C218: 管理 | D218: 德鲁克经典五问 | E218: 彼得·德鲁克 | F218: 李洁 | G218: 全员 | H218: 4 | I218: 2 | J218: 44032 | K218: 已完结 | L218: 4.99
A219: =ROW()-2 -> 217 | B219: 讲书 | C219: 管理 | D219: 管理的实践 | E219: 彼得·德鲁克 | F219: 李洁 | G219: 全员 | H219: 3 | I219: 1.1819444 | J219: 44032 | K219: 已完结
A220: =ROW()-2 -> 218 | B220: 讲书 | C220: 管理 | D220: 公司的概念 | E220: 彼得·德鲁克 | F220: 李清昊 | G220: 全员 | H220: 3 | I220: 1.23 | J220: 44039 | K220: 已完结 | L220: 4.99
A221: =ROW()-2 -> 219 | B221: 讲书 | C221: 管理 | D221: 成果管理 | E221: 彼得·德鲁克 | F221: 李洁 | G221: 全员 | H221: 6 | I221: 2.44 | J221: 44046 | K221: 已完结 | L221: 4.99
A222: =ROW()-2 -> 220 | B222: 讲书 | C222: 管理 | D222: 管理：任务、责任和实践 | E222: 彼得·德鲁克 | F222: 李洁 | G222: 全员 | H222: 2 | I222: 0.82 | J222: 44046 | K222: 已完结 | L222: 4.99
A223: =ROW()-2 -> 221 | B223: 讲书 | C223: 管理 | D223: 创新与企业家精神 | E223: 彼得·德鲁克 | F223: 李洁 | G223: 全员 | H223: 3 | I223: 1.2 | J223: 44053 | K223: 已完结 | L223: 4.99
A224: =ROW()-2 -> 222 | B224: 讲书 | C224: 管理 | D224: 卓有成效的管理者 | E224: 彼得·德鲁克 | F224: 李洁 | G224: 全员 | H224: 3 | I224: 1.2 | J224: 44060 | K224: 已完结 | L224: 4.99
A225: =ROW()-2 -> 223 | B225: 讲书 | C225: 管理 | D225: 管理未来 | E225: 彼得·德鲁克 | F225: 李洁 | G225: 全员 | H225: 3 | I225: 1.2 | J225: 44060 | K225: 已完结 | L225: 4.99
A226: =ROW()-2 -> 224 | B226: 讲书 | C226: 管理 | D226: 后资本主义社会 | E226: 彼得·德鲁克 | F226: 李洁 | G226: 全员 | H226: 3 | I226: 1.3 | J226: 44067 | K226: 已完结 | L226: 4.99
A227: =ROW()-2 -> 225 | B227: 讲书 | C227: 管理 | D227: 非营利组织的管理 | E227: 彼得·德鲁克 | F227: 李洁 | G227: 全员 | H227: 4 | I227: 2.66 | J227: 44067 | K227: 已完结 | L227: 4.99
A228: =ROW()-2 -> 226 | B228: 讲书 | C228: 管理 | D228: 重新定义公司：谷歌是如何运营的 | E228: 埃里克·施密特 | F228: 李清昊 | G228: 全员 | H228: 3 | I228: 1.2 | J228: 44067 | K228: 已完结 | L228: 4.99
A229: =ROW()-2 -> 227 | B229: 讲书 | C229: 管理 | D229: 变革中的管理 | E229: 彼得·德鲁克 | F229: 李洁 | G229: 全员 | H229: 3 | I229: 1.22 | J229: 44067 | K229: 已完结 | L229: 4.99
A230: =ROW()-2 -> 228 | B230: 讲书 | C230: 管理 | D230: 已经发生的未来 | E230: 彼得·德鲁克 | F230: 李洁 | G230: 全员 | H230: 3 | I230: 1.23 | J230: 44067 | K230: 已完结 | L230: 4.99
A231: =ROW()-2 -> 229 | B231: 讲书 | C231: 管理 | D231: 德鲁克52周教练指南 | E231: 约瑟夫·马恰列洛 | F231: 李洁 | G231: 全员 | H231: 3 | I231: 1.3 | J231: 44074 | K231: 已完结 | L231: 4.99
... A647: =ROW()-2 -> 645 | B647: 讲书 | C647: 文学 | D647: 不能承受的生命之轻 | E647: 米兰·昆德拉 | F647: 路上读书 | G647: 全员 | H647: 2 | I647: 0.98 | J647: 44074 | K647: 已完结 | L647: 4.99
A648: =ROW()-2 -> 646 | B648: 讲书 | C648: 文学 | D648: 呼啸山庄 | E648: 艾米莉·勃朗特 | F648: 路上读书 | G648: 全员 | H648: 3 | I648: 1.5358333 | J648: 44074 | K648: 已完结
A649: =ROW()-2 -> 647 | B649: 讲书 | C649: 文学 | D649: 芳华 | E649: 严歌苓 | F649: 路上读书 | G649: 全员 | H649: 2 | I649: 0.95 | J649: 44081 | K649: 已完结 | L649: 4.99
A650: =ROW()-2 -> 648 | B650: 讲书 | C650: 文学 | D650: 半生缘 | E650: 张爱玲 | F650: 路上读书 | G650: 全员 | H650: 2 | I650: 0.95 | J650: 44088 | K650: 已完结 | L650: 4.99
A651: =ROW()-2 -> 649 | B651: 讲书 | C651: 文学 | D651: 长恨歌 | E651: 王安忆 | F651: 路上读书 | G651: 全员 | H651: 2 | I651: 1.14 | J651: 44088 | K651: 已完结 | L651: 4.99
A652: =ROW()-2 -> 650 | B652: 讲书 | C652: 文学 | D652: 白夜行 | E652: 东野圭吾 | F652: 路上读书 | G652: 全员 | H652: 1 | I652: 0.5 | J652: 44088 | K652: 未完结 | L652: 4.99
A653: =ROW()-2 -> 651 | B653: 讲书 | C653: 文学 | D653: 东方快车谋杀案 | E653: 阿加莎·克里斯蒂 | F653: 路上读书 | G653: 全员 | H653: 2 | I653: 1.12 | J653: 44088 | K653: 已完结 | L653: 4.99
A654: =ROW()-2 -> 652 | B654: 讲书 | C654: 文学 | D654: 无人生还 | E654: 阿加莎·克里斯蒂 | F654: 路上读书 | G654: 全员 | H654: 1 | I654: 0.62 | J654: 44088 | K654: 未完结 | L654: 4.99
A655: =ROW()-2 -> 653 | B655: 讲书 | C655: 文学 | D655: 旁观者 | E655: 彼得·德鲁克 | F655: 李洁 | G655: 全员 | H655: 2 | I655: 0.66 | J655: 44088 | K655: 已完结 | L655: 4.99
A656: =ROW()-2 -> 654 | B656: 讲书 | C656: 文学 | D656: 爱因斯坦传 | E656: 沃尔特·艾萨克森 | F656: 尹铮铮 | G656: 全员 | H656: 1 | I656: 0.6 | J656: 44102 | K656: 已完结 | L656: 4.99
A657: =ROW()-2 -> 655 | B657: 讲书 | C657: 文学 | D657: 霍华德·休斯传 | E657: 詹姆斯·B.斯蒂尔，唐纳德·L.巴特利特 | F657: 尹铮铮 | G657: 全员 | H657: 1 | I657: 0.61 | J657: 44102 | K657: 已完结 | L657: 4.99
A658: =ROW()-2 -> 656 | B658: 讲书 | C658: 文学 | D658: 这样写出好故事 | E658: 詹姆斯·斯科特·贝尔 | F658: 舍丽儿 | G658: 全员 | H658: 1 | I658: 0.49 | J658: 44123 | K658: 已完结 | L658: 4.99
A659: =ROW()-2 -> 657 | B659: 讲书 | C659: 文学 | D659: 写作这回事（上） | E659: 斯蒂芬·金 | F659: 舍丽尔 | G659: 全员 | H659: 1 | I659: 0.21 | J659: 44130 | K659: 已完结 | L659: 4.99
A660: =ROW()-2 -> 658 | B660: 讲书 | C660: 文学 | D660: 写作这回事（下） | E660: 斯蒂芬·金 | F660: 舍丽尔 | G660: 全员 | H660: 1 | I660: 0.21 | J660: 44130 | K660: 已完结 | L660: 4.99
... A760: =ROW()-2 -> 758 | B760: 讲书 | C760: 心理 | D760: 幸福超越完美 | E760: 蒂姆·斯佩克特 | F760: 安仁 | G760: 全员 | H760: 1 | I760: 0.5 | J760: 44620 | K760: 已完结 | L760: 4.9
A761: =ROW()-2 -> 759 | B761: 讲书 | C761: 心理 | D761: 艺术的慰藉 | E761: 阿兰·德波顿 | F761: 褚笑 | G761: 全员 | H761: 1 | I761: 0.5 | J761: 2021/12//6 | K761: 已完结 | L761: 4.99
A762: =ROW()-2 -> 760 | B762: 讲书 | C762: 职场 | D762: 掌控谈话 | E762: 克里斯·沃斯 | F762: 西蒙 | G762: 全员 | H762: 1 | I762: 0.46722222 | J762: 43962 | K762: 已完结 | L762: 4.99
A763: =ROW()-2 -> 761 | B763: 讲书 | C763: 职场 | D763: 精准表达 | E763: 高田贵久 | F763: 于靖童 | G763: 全员 | H763: 1 | I763: 0.30222222 | J763: 43962 | K763: 已完结 | L763: 4.99
A764: =ROW()-2 -> 762 | B764: 讲书 | C764: 职场 | D764: 哈佛经典谈判术 | E764: 迪帕克·马哈拉 马克斯·巴泽曼 | F764: 徐劭旸 | G764: 全员 | H764: 1 | I764: 0.43777778 | J764: 43962 | K764: 已完结 | L764: 4.99
A765: =ROW()-2 -> 763 | B765: 讲书 | C765: 职场 | D765: 一个广告人的自白 | E765: 大卫·奥格威 | F765: 半亩方塘 | G765: 全员 | H765: 1 | I765: 0.39861111 | J765: 43962 | K765: 已完结 | L765: 4.99
A766: =ROW()-2 -> 764 | B766: 讲书 | C766: 职场 | D766: 道歉的力量 | E766: 艾伦·拉扎尔 | F766: 墨菲 | G766: 全员 | H766: 1 | I766: 0.48055556 | J766: 43962 | K766: 已完结 | L766: 4.99
A767: =ROW()-2 -> 765 | B767: 讲书 | C767: 职场 | D767: 另一种选择 | E767: 谢丽尔·桑德伯格 亚当·格兰特 | F767: 陈曦 | G767: 全员 | H767: 1 | I767: 0.43277778 | J767: 43962 | K767: 已完结 | L767: 4.99
A768: =ROW()-2 -> 766 | B768: 讲书 | C768: 职场 | D768: 真实的幸福 | E768: 马丁·塞利格曼 | F768: 西蒙 | G768: 全员 | H768: 1 | I768: 0.44083333 | J768: 43962 | K768: 已完结 | L768: 4.99
A769: =ROW()-2 -> 767 | B769: 讲书 | C769: 职场 | D769: 非暴力沟通（下） | E769: 马歇尔·卢森堡 | F769: 耿人健 | G769: 全员 | H769: 1 | I769: 0.42333333 | J769: 43962 | K769: 已完结 | L769: 4.99
A770: =ROW()-2 -> 768 | B770: 讲书 | C770: 职场 | D770: 搞定 | E770: 戴维·艾伦 | F770: 张独白 | G770: 全员 | H770: 1 | I770: 0.37333333 | J770: 43978 | K770: 已完结 | L770: 4.99
A771: =ROW()-2 -> 769 | B771: 讲书 | C771: 职场 | D771: 让创意更有黏性 | E771: 奇普·希思/丹·希思 | F771: 图南 | G771: 全员 | H771: 1 | I771: 0.55472222 | J771: 43978 | K771: 已完结 | L771: 4.99
A772: =ROW()-2 -> 770 | B772: 讲书 | C772: 职场 | D772: 运营之光 | E772: 黄有璨 | F772: 黄有璨 | G772: 全员 | H772: 1 | I772: 0.455 | J772: 43978 | K772: 已完结 | L772: 4.99
A773: =ROW()-2 -> 771 | B773: 讲书 | C773: 职场 | D773: 启示录 | E773: 马蒂·卡根 | F773: 邹大湿 | G773: 全员 | H773: 1 | I773: 0.52333333 | J773: 43978 | K773: 已完结 | L773: 4.99
... A884: =ROW()-2 -> 882 | B884: 讲书 | C884: 职场 | D884: 工作的意义 | E884: 詹姆斯‧苏兹曼 | F884: 史钧 | G884: 全员 | H884: 1 | I884: 0.48 | J884: 44627 | K884: 已完结 | L884: 4.99
