Workbook

Sheet 利润表
A1: 利润表
A2: 西安赛格 | B2: 45869 | E2: 单位：元
A3: 项 目 | B3: 本期金额 | C3: 本期占比流水 | D3: 本期占比净收 | E3: 本年累计金额 | F3: 本年占比流水 | G3: 本年占比净收
A4: 一、主营业务数据
A5: 1、主营业务收入 | B5: 870370.9 | C5: 1 | E5: 4753310.8 | F5: 1
A6: (1)、烘焙收入 | B6: 693886.4 | C6: 0.8 | E6: 3707259.3 | F6: 0.78
A7: (2)、三明治收入 | B7: 0 | C7: 0 | E7: 0 | F7: 0
A8: (3)、水吧收入 | B8: 0 | C8: 0 | E8: 0 | F8: 0
A9: (4)、果酱收入 | B9: 0 | C9: 0 | E9: 0 | F9: 0
A10: (5)、西点收入 | B10: 174033 | C10: 0.2 | E10: 1043600 | F10: 0.22
A11: (6)、商品收入 | B11: 2451.5 | C11: 0 | E11: 2451.5 | F11: 0
A12: 2、销售折扣折让 | B12: 101754.79 | C12: 0.12 | E12: 584178 | F12: 0.12
A13: (1)、烘焙折扣折让 | B13: 91348.98 | C13: 0.13 | E13: 492622.87 | F13: 0.13
A14: (2)、三明治折扣折让 | B14: 0 | C14: #DIV/0! | E14: 0 | F14: #DIV/0!
A15: (3)、水吧折扣折让 | B15: 0 | C15: #DIV/0! | E15: 0 | F15: #DIV/0!
A16: (4)、果酱折扣折让 | B16: 0 | C16: #DIV/0! | E16: 0 | F16: #DIV/0!
A17: (5)、西点折扣折让 | B17: 9830.89 | C17: 0.06 | E17: 90980.21 | F17: 0.09
A18: (6)、商品折扣折让 | B18: 574.92 | C18: 0.23 | E18: 574.92 | F18: 0.23
A19: 3、销售试吃 | B19: 34714 | C19: 0.04 | E19: 200127.97 | F19: 0.04
A20: (1)、烘焙试吃 | B20: 33495 | C20: 0.05 | E20: 194586.62 | F20: 0.05
A21: (2)、三明治试吃 | B21: 0 | C21: #DIV/0! | E21: 0 | F21: #DIV/0!
A22: (3)、水吧试吃 | B22: 0 | C22: #DIV/0! | E22: 0 | F22: #DIV/0!
A23: (4)、果酱试吃 | B23: 0 | C23: #DIV/0! | E23: 0 | F23: #DIV/0!
A24: (5)、西点试吃 | B24: 1219 | C24: 0.01 | E24: 5541.35 | F24: 0.01
A25: (6)、商品试吃 | B25: 0 | C25: 0 | E25: 0 | F25: 0
A26: 4、销售报损 | B26: 19595 | C26: 0.02 | E26: 147755 | F26: 0.03
A27: (1)、烘焙报损 | B27: 19559 | C27: 0.03 | E27: 145492 | F27: 0.04
A28: (2)、三明治报损 | B28: 0 | C28: #DIV/0! | E28: 0 | F28: #DIV/0!
A29: (3)、水吧报损 | B29: 0 | C29: #DIV/0! | E29: 0 | F29: #DIV/0!
A30: (4)、果酱报损 | B30: 0 | C30: #DIV/0! | E30: 0 | F30: #DIV/0!
A31: (5)、西点报损 | B31: 36 | C31: 0 | E31: 2263 | F31: 0
A32: (6)、商品报损 | B32: 0 | C32: 0 | E32: 0 | F32: 0
A33: 5、主营业务净收入 | B33: 714307.11 | C33: 0.82 | D33: 1 | E33: 3821249.8 | F33: 0.8 | G33: 1
A34: (1)、烘焙净收入 | B34: 549483.42 | C34: 0.79 | D34: 0.77 | E34: 2874557.8 | F34: 0.78 | G34: 0.75
A35: (2)、三明治净收入 | B35: 0 | C35: #DIV/0! | D35: 0 | E35: 0 | F35: #DIV/0! | G35: 0
A36: (3)、水吧净收入 | B36: 0 | C36: #DIV/0! | D36: 0 | E36: 0 | F36: #DIV/0! | G36: 0
A37: (4)、果酱净收入 | B37: 0 | C37: #DIV/0! | D37: 0 | E37: 0 | F37: #DIV/0! | G37: 0
A38: (5)、西点净收入 | B38: 162947.11 | C38: 0.94 | D38: 0.23 | E38: 944815.44 | F38: 0.91 | G38: 0.25
A39: (6)、商品净收入 | B39: 1876.58 | C39: 0.77 | D39: 0 | E39: 1876.58 | F39: 0.77 | G39: 0
A40: 6、减：主营业务成本 | B40: 271880.72 | C40: 0.31 | D40: 0.38 | E40: 1498220.3 | F40: 0.32 | G40: 0.39
A41: (1)、烘焙成本 | B41: 207032.37 | C41: 0.3 | D41: 0.38 | E41: 1106655.8 | F41: 0.3 | G41: 0.38
A42: (2)、三明治成本 | B42: 0 | C42: #DIV/0! | D42: #DIV/0! | E42: 0 | F42: #DIV/0! | G42: #DIV/0!
A43: (3)、水吧成本 | B43: 0 | C43: #DIV/0! | D43: #DIV/0! | E43: 0 | F43: #DIV/0! | G43: #DIV/0!
A44: (4)、果酱成本 | B44: 0 | C44: #DIV/0! | D44: #DIV/0! | E44: 0 | F44: #DIV/0! | G44: #DIV/0!
A45: (5)、西点成本 | B45: 64096.35 | C45: 0.37 | D45: 0.39 | E45: 390812.56 | F45: 0.37 | G45: 0.41
A46: (6)、商品成本 | B46: 752 | C46: 0.31 | D46: 0.4 | E46: 752 | F46: 0.31 | G46: 0.4
A47: 7、销售费用 | B47: 372073.29 | C47: 0.43 | D47: 0.52 | E47: 1977347.7 | F47: 0.42 | G47: 0.52
A48: 人事费用小计 | B48: 160127.07 | C48: 0.18 | D48: 0.22 | E48: 928222.57 | F48: 0.2 | G48: 0.24
A49: 人事费用-工资及津贴 | B49: 132461.52 | C49: 0.15 | D49: 0.19 | E49: 776919.17 | F49: 0.16 | G49: 0.2
A50: 人事费用-奖金及提成 | B50: -12000 | C50: -0.01 | D50: -0.02 | E50: 6300 | F50: 0 | G50: 0
A51: 人事费用-员工保险费 | B51: 21524.75 | C51: 0.02 | D51: 0.03 | E51: 39093.31 | F51: 0.01 | G51: 0.01
A52: 人事费用-员工福利费 | B52: 0 | C52: 0 | D52: 0 | E52: 2853.11 | F52: 0 | G52: 0
A53: 人事费用-宿舍租赁费 | B53: 6900 | C53: 0.01 | D53: 0.01 | E53: 31783.92 | F53: 0.01 | G53: 0.01
A54: 人事费用-员工餐费 | B54: 10096 | C54: 0.01 | D54: 0.01 | E54: 51001.92 | F54: 0.01 | G54: 0.01
A55: 人事费用-员工工服 | B55: 0 | C55: 0 | D55: 0 | E55: 6451 | F55: 0 | G55: 0
A56: 人事费用-招聘费用 | B56: 1144.8 | C56: 0 | D56: 0 | E56: 13820.14 | F56: 0 | G56: 0
... A64: 能源费用-电费 | B64: 13412.86 | C64: 0.02 | D64: 0.02 | E64: 47713.29 | F64: 0.01 | G64: 0.01
C65: 0 | D65: 0 | F65: 0 | G65: 0
A66: 物耗费用小计： | B66: 8516.39 | C66: 0.01 | D66: 0.01 | E66: 55566.93 | F66: 0.01 | G66: 0.01
A67: 物耗费用-物料消耗 | B67: 8135.59 | C67: 0.01 | D67: 0.01 | E67: 48013.3 | F67: 0.01 | G67: 0.01
A68: 物耗费用-低值易耗品 | B68: 380.8 | C68: 0 | D68: 0 | E68: 7553.63 | F68: 0 | G68: 0
C69: 0 | D69: 0 | F69: 0 | G69: 0
A70: 物业费用小计： | B70: 140895 | C70: 0.16 | D70: 0.2 | E70: 637939.36 | F70: 0.13 | G70: 0.17
A71: 物业费用-商铺租金 | B71: 120520 | C71: 0.14 | D71: 0.17 | E71: 547030.01 | F71: 0.12 | G71: 0.14
A72: 物业费用-商场推广费 | B72: 0 | C72: 0 | D72: 0 | E72: 0 | F72: 0 | G72: 0
A73: 物业费用-商场物业费 | B73: 15720 | C73: 0.02 | D73: 0.02 | E73: 70479.35 | F73: 0.01 | G73: 0.02
A74: 物业费用-库房租金 | B74: 4655 | C74: 0.01 | D74: 0.01 | E74: 20430 | F74: 0 | G74: 0.01
A75: 物业费用-办公室租金 | B75: 0 | C75: 0 | D75: 0 | E75: 0 | F75: 0 | G75: 0
C76: 0 | D76: 0 | F76: 0 | G76: 0
A77: 其他运营费用小计： | B77: 48827.97 | C77: 0.06 | D77: 0.07 | E77: 306316.58 | F77: 0.06 | G77: 0.08
A78: 其他运营费用-办公费 | B78: 100 | C78: 0 | D78: 0 | E78: 6517.88 | F78: 0 | G78: 0
A79: 其他运营费用-电话费/网费 | B79: 0 | C79: 0 | D79: 0 | E79: 9603.8 | F79: 0 | G79: 0
A80: 其他运营费用-广告宣传费 | B80: 6104.12 | C80: 0.01 | D80: 0.01 | E80: 76874.12 | F80: 0.02 | G80: 0.02
A81: 其他运营费用-交通费 | B81: 0 | C81: 0 | D81: 0 | E81: 144.4 | F81: 0 | G81: 0
A82: 其他运营费用-运输费 | B82: 816 | C82: 0 | D82: 0 | E82: 6201.74 | F82: 0 | G82: 0
A83: 其他运营费用-业务招待费 | B83: 0 | C83: 0 | D83: 0 | E83: 2496 | F83: 0 | G83: 0
A84: 其他运营费用-公关费 | B84: 0 | C84: 0 | D84: 0 | E84: 111.78 | F84: 0 | G84: 0
A85: 其他运营费用-差旅费 | B85: 1690.6 | C85: 0 | D85: 0 | E85: 24379.35 | F85: 0.01 | G85: 0.01
A86: 其他运营费用-品牌使用费 | B86: 28825.81 | C86: 0.03 | D86: 0.04 | E86: 154588.09 | F86: 0.03 | G86: 0.04
A87: 其他运营费用-车辆加油费 | B87: 0 | C87: 0 | D87: 0 | E87: 0 | F87: 0 | G87: 0
A88: 其他运营费用-车辆保险费 | B88: 0 | C88: 0 | D88: 0 | E88: 0 | F88: 0 | G88: 0
... A98: 其他运营费用-费用分摊 | B98: 0 | C98: 0 | D98: 0 | E98: 0 | F98: 0 | G98: 0
C99: 0 | D99: 0 | F99: 0 | G99: 0
A100: 8、管理费用 | B100: 0 | C100: 0 | D100: 0 | E100: 0 | F100: 0 | G100: 0
A101: 9、财务费用 | B101: 8 | C101: 0 | D101: 0 | E101: 8.7 | F101: 0 | G101: 0
A102: 二、 主营业务利润（亏损以“-”号填列） | B102: 70345.1 | C102: 0.08 | D102: 0.1 | E102: 345673.06 | F102: 0.07 | G102: 0.09
A103: 资产减值损失 | C103: 0 | D103: 0 | F103: 0 | G103: 0
A104: 加：公允价值变动收益（损失以“-”号填列） | C104: 0 | D104: 0 | F104: 0 | G104: 0
A105: 投资收益（损失以“-”号填列） | B105: 0 | C105: 0 | D105: 0 | E105: 0 | F105: 0 | G105: 0
A106: 其中：对联营企业和合营企业的投资收益 | C106: 0 | D106: 0 | F106: 0 | G106: 0
A107: 加：营业外收入 | B107: 500 | C107: 0 | D107: 0 | E107: 500.53 | F107: 0 | G107: 0
A108: 减：营业外支出 | B108: 0 | C108: 0 | D108: 0 | E108: 0 | F108: 0 | G108: 0
A109: 其中：非流动资产处置损失 | C109: 0 | D109: 0 | F109: 0 | G109: 0
A110: 三、利润总额（不含摊销） | B110: 70845.1 | C110: 0.08 | D110: 0.1 | E110: 346173.59 | F110: 0.07 | G110: 0.09
A111: 其他收入（减免及奖励） | B111: 0 | C111: 0 | D111: 0 | E111: 0 | F111: 0 | G111: 0
A112: 其他支出（与主营业务无直接关联） | B112: 0 | C112: 0 | D112: 0 | E112: 0 | F112: 0 | G112: 0
A113: 四、税金及附加 | B113: 5189.93 | C113: 0.01 | D113: 0.01 | E113: 11146.48 | F113: 0 | G113: 0
A114: 增值税金及附加 | B114: 5189.93 | C114: 0.0059628947 | D114: 0.0072656844 | E114: 11146.48 | F114: 0.0023449929 | G114: 0
A115: 所得税费用 | B115: 0 | C115: 0 | D115: 0 | E115: 0 | F115: 0 | G115: 0
A116: 五、折旧摊销 | B116: 62492.78 | C116: 0.07 | D116: 0.09 | E116: 244002.14 | F116: 0.05 | G116: 0.06
...

Sheet 资产负债表
A1: 资产负债表
F2: 会企01表
A3: 编制单位：西安赛格 | D3: 45869 | F3: 单位：元
A4: 资产 | B4: 期末余额 | C4: 上年年末余额 | D4: 负债和所有者权益（或股东权益） | E4: 期末余额 | F4: 上年年末余额
A5: 流动资产: | D5: 流动负债:
A6: 货币资金 | B6: 491477.16 | C6: 0 | D6: 短期借款 | E6: 0 | F6: 0
A7: 以公允价值计量且其变动计入当期损益的金融资产 | B7: 0 | C7: 0 | D7: 以公允价值计量且其变动计入当期损益的金融负债 | E7: 0 | F7: 0
A8: 衍生金融资产 | B8: 0 | C8: 0 | D8: 衍生金融负债 | E8: 0 | F8: 0
A9: 应收票据 | B9: 0 | C9: 0 | D9: 应付票据 | E9: 0 | F9: 0
A10: 应收账款 | B10: 83686.43 | C10: 0 | D10: 应付账款 | E10: 61912.29 | F10: 0
A11: 预付款项 | B11: 241371.45 | C11: 0 | D11: 预收款项 | E11: 120944.61 | F11: 0
A12: 其他应收款 | B12: 7126.85 | C12: 0 | D12: 应付职工薪酬 | E12: 165741.65 | F12: 0
A13: 存货 | B13: 269867.51 | C13: 0 | D13: 应交税费 | E13: 0 | F13: 0
A14: 持有待售资产 | B14: 0 | C14: 0 | D14: 其他应付款 | E14: 18632.99 | F14: 0
A15: 一年内到期的非流动资产 | D15: 持有待售负债 | E15: 0 | F15: 0
A16: 其他流动资产 | B16: 0 | C16: 0 | D16: 一年内到期的非流动负债
D17: 其他流动负债 | E17: 0 | F17: 0
A18: 流动资产合计 | B18: 1093529.4 | C18: 0 | D18: 流动负债合计 | E18: 367231.54 | F18: 0
A19: 非流动资产: | D19: 非流动负债:
A20: 可供出售金融资产 | B20: 0 | C20: 0 | D20: 长期借款 | E20: 0 | F20: 0
A21: 持有至到期投资 | B21: 0 | C21: 0 | D21: 应付债券 | E21: 0 | F21: 0
A22: 长期应收款 | B22: 0 | C22: 0 | D22: 其中：优先股
A23: 长期股权投资 | B23: 0 | C23: 0 | D23: 永续债
A24: 投资性房地产 | B24: 0 | C24: 0 | D24: 长期应付款 | E24: 0 | F24: 0
A25: 固定资产 | B25: 438898.36 | C25: 0 | D25: 预计负债 | E25: 0 | F25: 0
A26: 在建工程 | B26: 0 | C26: 0 | D26: 递延收益 | E26: 0 | F26: 0
A27: 生产性生物资产 | B27: 0 | C27: 0 | D27: 递延所得税负债 | E27: 0 | F27: 0
A28: 油气资产 | B28: 0 | C28: 0 | D28: 其他非流动负债
A29: 无形资产 | B29: 19259.41 | C29: 0 | D29: 非流动负债合计 | E29: 0 | F29: 0
A30: 开发支出 | B30: 0 | C30: 0 | D30: 负债合计 | E30: 367231.54 | F30: 0
A31: 商誉 | B31: 0 | C31: 0 | D31: 所有者权益（或股东权益）:
A32: 长期待摊费用 | B32: 836817.44 | C32: 0 | D32: 实收资本(股本) | E32: 2018110.7 | F32: 0
A33: 递延所得税资产 | B33: 0 | C33: 0 | D33: 其他权益工具 | E33: 0 | F33: 0
A34: 其他非流动资产 | B34: 0 | C34: 0 | D34: 其中：优先股
A35: 非流动资产合计 | B35: 1294975.2 | C35: 0 | D35: 永续债
D36: 资本公积 | E36: 0 | F36: 0
D37: 减:库存股 | E37: 0 | F37: 0
D38: 其他综合收益 | E38: 0 | F38: 0
D39: 专项储备 | E39: 0 | F39: 0
D40: 盈余公积 | E40: 0 | F40: 0
D41: 未分配利润 | E41: 3162.39 | F41: 0
D42: 外币折算差额
D43: 所有者权益（或股东权益）合计 | E43: 2021273.1 | F43: 0
A44: 资产总计 | B44: 2388504.6 | C44: 0 | D44: 负债和所有者权益（或股东权益）合计 | E44: 2388504.6 | F44: 0

Sheet 现金流量表
A1: 账簿:西安赛格 | B1: 币别:人民币 | C1: 查询范围:2025.7 -- 2025.7
A2: 项目类别 | B2: 现金流量项目 | C2: 行次 | D2: 金额
A3: 1 | B3: 经营活动产生的现金流量
B4: 销售商品、提供劳务收到的现金 | C4: 1 | D4: 705948.7
B5: 收到的税费返还 | C5: 2
B6: 收到其他与经营活动有关的现金 | C6: 3 | D6: 10987.26
B7: 现金流入小计 | C7: 4 | D7: 716935.96
B8: 购买商品、接受劳务支付的现金 | C8: 5 | D8: 276390.85
B9: 支付给职工以及为职工支付的现金 | C9: 6 | D9: 158336.8
B10: 支付的各项税费 | C10: 7 | D10: 11541.51
B11: 支付其他与经营活动有关的现金 | C11: 8 | D11: 85647.91
B12: 现金流出小计 | C12: 9 | D12: 531917.07
B13: 经营活动产生的现金流量净额 | C13: 10 | D13: 185018.89
A14: 2 | B14: 投资活动产生的现金流量
B15: 收回投资收到的现金 | C15: 11
B16: 取得投资收益收到的现金 | C16: 12
B17: 处置固定资产、无形资产和其他长期资产收回的现金净额 | C17: 13
B18: 处置子公司及其他营业单位收到的现金净额 | C18: 14
B19: 收到其他与投资活动有关的现金 | C19: 15
B20: 现金流入小计 | C20: 16
B21: 购建固定资产、无形资产和其他长期资产支付的现金 | C21: 17
B22: 投资支付的现金 | C22: 18
B23: 取得子公司及其他营业单位支付的现金净额 | C23: 19
B24: 支付其他与投资活动有关的现金 | C24: 20
B25: 现金流出小计 | C25: 21
B26: 投资活动产生的现金流量净额 | C26: 22
A27: 3 | B27: 筹资活动产生的现金流量
B28: 吸收投资收到的现金 | C28: 23
B29: 取得借款收到的现金 | C29: 24
B30: 收到其他与筹资活动有关的现金 | C30: 25
B31: 现金流入小计 | C31: 26
B32: 偿还债务支付的现金 | C32: 27
B33: 分配股利、利润或偿付利息支付的现金 | C33: 28 | D33: 30751.9
B34: 支付其他与筹资活动有关的现金 | C34: 29
B35: 现金流出小计 | C35: 30 | D35: 30751.9
B36: 筹资活动产生的现金流量净额 | C36: 31 | D36: -30751.9
A37: 4 | B37: 汇率变动对现金及现金等价物的影响 | C37: 35
A38: 5 | B38: 现金及现金等价物净增加额 | C38: 36 | D38: 154266.99
B39: 加：期初现金及现金等价物余额 | C39: 37 | D39: 337210.17
A40: 6 | B40: 期末现金及现金等价物余额 | C40: 38 | D40: 491477.16
A41: 补充资料：
B42: 现金流量附表项目
A43: 1 | B43: 将净利润调节为经营活动现金流量
B44: 净利润 | C44: 39 | D44: 3162.39
B45: 资产减值准备 | C45: 40
B46: 固定资产折旧、油气资产折耗、生产性生物资产折旧 | C46: 41 | D46: ='[1]6月资产负债'!B25-'[1]7月资产负债'!B25 -> 20758.23
B47: 无形资产摊销 | C47: 42 | D47: ='[1]6月资产负债'!B29-'[1]7月资产负债'!B29 -> 958.33
B48: 长期待摊费用摊销 | C48: 43 | D48: ='[1]6月资产负债'!B32-'[1]7月资产负债'!B32 -> 37446.52
B49: 处置固定资产、无形资产和其他长期资产的损失 | C49: 44
B50: 固定资产报废损失 | C50: 45
B51: 公允价值变动损失 | C51: 46
B52: 财务费用 | C52: 47
B53: 投资损失 | C53: 48
B54: 递延所得税资产减少 | C54: 49
B55: 递延所得税负债增加 | C55: 50
B56: 存货的减少 | C56: 51 | D56: ='[1]6月资产负债'!B13-'[1]7月资产负债'!B13 -> 5094.98
B57: 经营性应收项目的减少 | C57: 52 | D57: ='[1]6月资产负债'!B10+'[1]6月资产负债'!B11+'[1]6月资产负债'!B12-'[1]7月资产负债'!B10-'[1]7月资产负债'!B11-'[1]7月资产负债'!B12 -> 120633.1
B58: 经营性应付项目的增加 | C58: 53 | D58: ='[1]7月资产负债'!E18-'[1]6月资产负债'!E18 -> -85120.18
B59: 其他 | C59: 54 | D59: 82085.52
B60: 经营活动产生的现金流量净额 | C60: 55 | D60: =SUM(D44:D59) -> 185018.89
A61: 2 | B61: 不涉及现金收支的重大投资和筹资活动
B62: 债务转为资本 | C62: 56
B63: 一年内到期的可转换公司债券 | C63: 57
B64: 融资租入固定资产 | C64: 58
A65: 3 | B65: 现金及现金等价物净变动情况
B66: 现金的期末余额 | C66: 59 | D66: 491477.16
B67: 减：现金的期初余额 | C67: 60 | D67: 337210.17
B68: 加：现金等价物的期末余额 | C68: 61
B69: 减：现金等价物的期初余额 | C69: 62
B70: 现金及现金等价物的净增加额 | C70: 63 | D70: 154266.99

Sheet 资产负债表附表
A1: 资产负债表科目 | B1: 资产负债表余额 | C1: 科目名称 | D1: 期初借方余额 | E1: 期初贷方余额 | F1: 本期借方发生额 | G1: 本期贷方发生额 | H1: 期末借方余额 | I1: 期末贷方余额 | J1: 备注说明 | K1: 校验
A2: 货币资金 | B2: =资产负债表!B6 -> 491477.16 | C2: 库存现金 | D2: 12890.78 | F2: 10508.5 | G2: 19992.28 | H2: 3407 | K2: =B2-SUM(H2:H3) -> 0
C3: 银行存款 | D3: 324319.39 | F3: 1053005.1 | G3: 889254.34 | H3: 488070.16
A4: 应收账款 | B4: =资产负债表!B10 -> 83686.43 | C4: [001]美团团购 | D4: 21544.26 | F4: 114816.55 | G4: 104527.4 | H4: 31833.41 | K4: =B4-SUM(H4:H12) -> 0
C5: [002]美团外卖 | D5: 1920.95 | F5: 11166.7 | G5: 12136.86 | H5: 950.79
C6: [003]饿了么外卖 | D6: 1737.07 | F6: 17663.97 | G6: 17996.46 | H6: 1404.58
C7: [004]抖音团购 | D7: 13877.94 | F7: 62503.66 | G7: 68363.91 | H7: 8017.69
C8: [005]云纵商家-微信支付宝 | D8: 17475.35 | F8: 493614.31 | G8: 497897.08 | H8: 13192.58
C9: [006]交通银行
C10: [007]招商银行 | F10: 4108.5 | G10: 3667 | H10: 441.5
C11: [008]京东外卖 | D11: 204.41 | F11: 1364.81 | G11: 1359.99 | H11: 209.23
C12: [009]万象卡 | D12: 21742.49 | F12: 5894.16 | H12: 27636.65
C13: [013]招商银行
A14: =资产负债表!A11 -> 预付款项 | B14: =资产负债表!B11 -> 241371.45 | C14: 预付库房租金 | D14: 388611.45 | G14: 147240 | H14: 241371.45 | J14: 预付库房租金 | K14: =B14-H14 -> 0
A15: 其他应收款 | B15: =资产负债表!B12 -> 7126.85 | C15: 员工往来 | D15: 9000 | H15: 9000 | J15: 1、开办投入中用于预付当期费用部分2、员工借款。以上计入员工往来 | K15: =B15-(H15+H16+H37+H45+H46+H47-I15-I16-I37-I45-I46-I47) -> -3.4560799e-11
C16: 公司往来 | E16: 284587.72 | F16: 51612.96 | G16: 34606.15 | I16: 267580.91 | J16: 公司之间应收应付往来款，计入公司往来
C17: 管理公司 | E17: 174893.17 | F17: 47492.2 | G17: 28825.81 | I17: 156226.78 | J17: 应付管理费
C18: 沈阳崎本 | J18: 公司之间应收应付往来款，计入公司往来
C19: 长春崎本 | E19: 40000 | I19: 40000 | J19: 公司之间应收应付往来款，计入公司往来
C20: 青岛崎本
C21: 南京崎本 | J21: 公司之间应收应付往来款，计入公司往来
C22: 成都崎本 | E22: 1332.32 | I22: 1332.32 | J22: 公司之间应收应付往来款，计入公司往来
C23: 海南蕊礼贸易有限公司 | E23: 50000 | I23: 50000 | J23: 公司之间应收应付往来款，计入公司往来
C24: 崎本-北京荟聚店
C25: 崎本-北京清河万象汇
C26: 崎本-珠海优特汇
C27: 沈阳乐姿网络传媒有限公司 | E27: 6087.03 | G27: 3821.58 | I27: 9908.61
C28: 崎本-大连高新 | D28: 358.5 | H28: 358.5
C29: 山亩-天津万象城 | E29: 3200 | G29: 1480 | I29: 4680
C30: 膨胀团-沈阳环宇城店
C31: 崎本-北京龙湖丽泽店 | E31: 12375.7 | I31: 12375.7
C32: 崎本-杭州万象城 | E32: 1480 | I32: 1480
C33: 崎本-郑州正弘城 | D33: 4422 | F33: 4120.76 | G33: 478.76 | H33: 8064
C37: 押金/保证金 | D37: 255640 | H37: 255640
C38: 租赁保证金 | D38: 241040 | H38: 241040
C39: 水电费押金 | D39: 1600 | H39: 1600
C40: 寝室押金 | D40: 6900 | H40: 6900
C41: 仓库押金 | D41: 4100 | H41: 4100
C42: 其他押金 | D42: 2000 | H42: 2000
C45: 代扣员工个人保险 | D45: 3869.09 | F45: 12002.31 | G45: 5803.64 | H45: 10067.76 | J45: 代扣员工个人保险
C46: 摊销费用 | D46: 1782.54 | G46: 1782.54 | J46: 按年缴费的宣传费、运营费用分期摊销
A48: 存货 | B48: =资产负债表!B13 -> 269867.51 | C48: 原材料 | D48: 264963.99 | F48: 277757.61 | G48: 282852.59 | H48: 259869.01 | K48: =B48-SUM(H48:H51) -> 0
C49: 库存商品 | D49: 9998.5 | H49: 9998.5
C50: 周转材料
C51: 低值易耗品
A52: 固定资产 | B52: =资产负债表!B25 -> 438898.36 | C52: 固定资产 | D52: 519922.43 | H52: 519922.43 | J52: 固定资产原值 | K52: =B52-SUM(H52:H53)+SUM(I52:I53) -> 0
C53: 累计折旧 | E53: 60265.84 | G53: 20758.23 | I53: 81024.07 | J53: 固定资产折旧
A54: 无形资产 | B54: =资产负债表!B29 -> 19259.41 | C54: 无形资产 | D54: 23000 | H54: 23000 | J54: 软件款 | K54: =B54-H54+I55 -> 0
C55: 累计摊销 | E55: 2782.26 | G55: 958.33 | I55: 3740.59 | J55: 累计摊销
A56: 长期待摊费用 | B56: =资产负债表!B32 -> 836817.44 | C56: 开办费 | D56: 859355.09 | G56: 40776.22 | H56: 818578.87 | J56: 开办费 | K56: =B56-SUM(H56:H57) -> 0
C57: 待摊费用-会员卡赠送 | D57: 14908.87 | F57: 8960 | G57: 5630.3 | H57: 18238.57 | J57: 会员卡赠送卡值
A58: 应付账款 | B58: =资产负债表!E10 -> 61912.29 | C58: 应付账款 | E58: 61460.65 | F58: 276390.85 | G58: 276842.49 | I58: 61912.29 | J58: 应付供应商货款/预付租金、水电费 | K58: =B58-I58 -> 0
A59: 预收款项 | B59: =资产负债表!E11 -> 120944.61 | C59: 预收账款 | E59: 110280.86 | F59: 36396.25 | G59: 47060 | I59: 120944.61 | J59: 预收会员卡储值 | K59: =B59-I59 -> 0
A60: 应付职工薪酬 | B60: =资产负债表!E12 -> 165741.65 | C60: 应付职工薪酬 | E60: 173935.15 | F60: 163935.15 | G60: 155741.65 | I60: 165741.65 | J60: 应付职工薪酬 | K60: =B60-I60 -> 0
A61: 应交税费 | B61: =资产负债表!E13 -> 0 | C61: 应交税费 | E61: 5956.55 | F61: 6351.58 | G61: 395.03 | K61: =B61-I61 -> 0
A62: 其他应付款 | B62: =资产负债表!E14 -> 18632.99 | C62: 员工报销未付款 | E62: 5682.99 | I62: 5682.99 | K62: =B62-SUM(I62:I64)+SUM(H62:H64) -> 0
C63: 应付股利
C64: 合同往来 | E64: 12950 | I64: 12950 | J64: 应付合同款余额
A65: 实收资本（或股本） | B65: =资产负债表!E32 -> 2018110.7 | C65: 实收资本 | E65: 1961000 | G65: 57110.68 | I65: 2018110.7 | J65: 开办投入中计入前期开办费、资产等前期投资余额。 | K65: =B65-I65 -> 0
A66: 未分配利润 | B66: =资产负债表!E41 -> 3162.39 | C66: 本年利润 | E66: 5777.06 | F66: 717421.78 | G66: 714807.11 | I66: 3162.39 | J66: 未分配净利润余额 | K66: =B66-SUM(I66+I68-H67) -> 0
C67: 未分配利润
